import java.io.EOFException;
import java.nio.charset.Charset;
import java.util.Collections;
import java.util.Set;

public final class bab
  implements qZa
{
  private static final Charset a = Charset.forName("UTF-8");
  private final bab.b b;
  private volatile Set<String> c = Collections.emptySet();
  private volatile bab.a d = bab.a.a;
  
  public bab(bab.b paramb)
  {
    this.b = paramb;
  }
  
  private void a(oZa paramoZa, int paramInt)
  {
    String str;
    if (this.c.contains(paramoZa.a(paramInt))) {
      str = "██";
    } else {
      str = paramoZa.b(paramInt);
    }
    bab.b localb = this.b;
    StringBuilder localStringBuilder = new StringBuilder();
    localStringBuilder.append(paramoZa.a(paramInt));
    localStringBuilder.append(": ");
    localStringBuilder.append(str);
    localb.a(localStringBuilder.toString());
  }
  
  static boolean a(jab paramjab)
  {
    try
    {
      jab localjab = new jab;
      localjab.<init>();
      long l;
      if (paramjab.size() < 64L) {
        l = paramjab.size();
      } else {
        l = 64L;
      }
      paramjab.a(localjab, 0L, l);
      for (int i = 0; (i < 16) && (!localjab.p()); i++)
      {
        int j = localjab.f();
        if (Character.isISOControl(j))
        {
          boolean bool = Character.isWhitespace(j);
          if (!bool) {
            return false;
          }
        }
      }
      return true;
    }
    catch (EOFException paramjab) {}
    return false;
  }
  
  private static boolean a(oZa paramoZa)
  {
    paramoZa = paramoZa.b("Content-Encoding");
    boolean bool;
    if ((paramoZa != null) && (!paramoZa.equalsIgnoreCase("identity")) && (!paramoZa.equalsIgnoreCase("gzip"))) {
      bool = true;
    } else {
      bool = false;
    }
    return bool;
  }
  
  /* Error */
  public BZa a(qZa.a parama)
    throws java.io.IOException
  {
    // Byte code:
    //   0: aload_0
    //   1: getfield 48	bab:d	Lbab$a;
    //   4: astore_2
    //   5: aload_1
    //   6: invokeinterface 143 1 0
    //   11: astore_3
    //   12: aload_2
    //   13: getstatic 46	bab$a:a	Lbab$a;
    //   16: if_acmpne +11 -> 27
    //   19: aload_1
    //   20: aload_3
    //   21: invokeinterface 146 2 0
    //   26: areturn
    //   27: getstatic 147	bab$a:d	Lbab$a;
    //   30: astore 4
    //   32: iconst_1
    //   33: istore 5
    //   35: aload_2
    //   36: aload 4
    //   38: if_acmpne +9 -> 47
    //   41: iconst_1
    //   42: istore 6
    //   44: goto +6 -> 50
    //   47: iconst_0
    //   48: istore 6
    //   50: iload 6
    //   52: ifne +19 -> 71
    //   55: aload_2
    //   56: getstatic 149	bab$a:c	Lbab$a;
    //   59: if_acmpne +6 -> 65
    //   62: goto +9 -> 71
    //   65: iconst_0
    //   66: istore 7
    //   68: goto +6 -> 74
    //   71: iconst_1
    //   72: istore 7
    //   74: aload_3
    //   75: invokevirtual 154	xZa:a	()LAZa;
    //   78: astore 8
    //   80: aload 8
    //   82: ifnull +6 -> 88
    //   85: goto +6 -> 91
    //   88: iconst_0
    //   89: istore 5
    //   91: aload_1
    //   92: invokeinterface 157 1 0
    //   97: astore_2
    //   98: new 68	java/lang/StringBuilder
    //   101: dup
    //   102: invokespecial 69	java/lang/StringBuilder:<init>	()V
    //   105: astore 4
    //   107: aload 4
    //   109: ldc -97
    //   111: invokevirtual 73	java/lang/StringBuilder:append	(Ljava/lang/String;)Ljava/lang/StringBuilder;
    //   114: pop
    //   115: aload 4
    //   117: aload_3
    //   118: invokevirtual 162	xZa:e	()Ljava/lang/String;
    //   121: invokevirtual 73	java/lang/StringBuilder:append	(Ljava/lang/String;)Ljava/lang/StringBuilder;
    //   124: pop
    //   125: aload 4
    //   127: bipush 32
    //   129: invokevirtual 165	java/lang/StringBuilder:append	(C)Ljava/lang/StringBuilder;
    //   132: pop
    //   133: aload 4
    //   135: aload_3
    //   136: invokevirtual 169	xZa:g	()LpZa;
    //   139: invokevirtual 172	java/lang/StringBuilder:append	(Ljava/lang/Object;)Ljava/lang/StringBuilder;
    //   142: pop
    //   143: aload_2
    //   144: ifnull +41 -> 185
    //   147: new 68	java/lang/StringBuilder
    //   150: dup
    //   151: invokespecial 69	java/lang/StringBuilder:<init>	()V
    //   154: astore 9
    //   156: aload 9
    //   158: ldc -82
    //   160: invokevirtual 73	java/lang/StringBuilder:append	(Ljava/lang/String;)Ljava/lang/StringBuilder;
    //   163: pop
    //   164: aload 9
    //   166: aload_2
    //   167: invokeinterface 179 1 0
    //   172: invokevirtual 172	java/lang/StringBuilder:append	(Ljava/lang/Object;)Ljava/lang/StringBuilder;
    //   175: pop
    //   176: aload 9
    //   178: invokevirtual 79	java/lang/StringBuilder:toString	()Ljava/lang/String;
    //   181: astore_2
    //   182: goto +6 -> 188
    //   185: ldc -75
    //   187: astore_2
    //   188: aload 4
    //   190: aload_2
    //   191: invokevirtual 73	java/lang/StringBuilder:append	(Ljava/lang/String;)Ljava/lang/StringBuilder;
    //   194: pop
    //   195: aload 4
    //   197: invokevirtual 79	java/lang/StringBuilder:toString	()Ljava/lang/String;
    //   200: astore 4
    //   202: aload 4
    //   204: astore_2
    //   205: iload 7
    //   207: ifne +55 -> 262
    //   210: aload 4
    //   212: astore_2
    //   213: iload 5
    //   215: ifeq +47 -> 262
    //   218: new 68	java/lang/StringBuilder
    //   221: dup
    //   222: invokespecial 69	java/lang/StringBuilder:<init>	()V
    //   225: astore_2
    //   226: aload_2
    //   227: aload 4
    //   229: invokevirtual 73	java/lang/StringBuilder:append	(Ljava/lang/String;)Ljava/lang/StringBuilder;
    //   232: pop
    //   233: aload_2
    //   234: ldc -73
    //   236: invokevirtual 73	java/lang/StringBuilder:append	(Ljava/lang/String;)Ljava/lang/StringBuilder;
    //   239: pop
    //   240: aload_2
    //   241: aload 8
    //   243: invokevirtual 187	AZa:a	()J
    //   246: invokevirtual 190	java/lang/StringBuilder:append	(J)Ljava/lang/StringBuilder;
    //   249: pop
    //   250: aload_2
    //   251: ldc -64
    //   253: invokevirtual 73	java/lang/StringBuilder:append	(Ljava/lang/String;)Ljava/lang/StringBuilder;
    //   256: pop
    //   257: aload_2
    //   258: invokevirtual 79	java/lang/StringBuilder:toString	()Ljava/lang/String;
    //   261: astore_2
    //   262: aload_0
    //   263: getfield 50	bab:b	Lbab$b;
    //   266: aload_2
    //   267: invokeinterface 82 2 0
    //   272: iload 7
    //   274: ifeq +563 -> 837
    //   277: iload 5
    //   279: ifeq +111 -> 390
    //   282: aload 8
    //   284: invokevirtual 195	AZa:b	()LrZa;
    //   287: ifnull +47 -> 334
    //   290: aload_0
    //   291: getfield 50	bab:b	Lbab$b;
    //   294: astore_2
    //   295: new 68	java/lang/StringBuilder
    //   298: dup
    //   299: invokespecial 69	java/lang/StringBuilder:<init>	()V
    //   302: astore 4
    //   304: aload 4
    //   306: ldc -59
    //   308: invokevirtual 73	java/lang/StringBuilder:append	(Ljava/lang/String;)Ljava/lang/StringBuilder;
    //   311: pop
    //   312: aload 4
    //   314: aload 8
    //   316: invokevirtual 195	AZa:b	()LrZa;
    //   319: invokevirtual 172	java/lang/StringBuilder:append	(Ljava/lang/Object;)Ljava/lang/StringBuilder;
    //   322: pop
    //   323: aload_2
    //   324: aload 4
    //   326: invokevirtual 79	java/lang/StringBuilder:toString	()Ljava/lang/String;
    //   329: invokeinterface 82 2 0
    //   334: aload 8
    //   336: invokevirtual 187	AZa:a	()J
    //   339: ldc2_w 198
    //   342: lcmp
    //   343: ifeq +47 -> 390
    //   346: aload_0
    //   347: getfield 50	bab:b	Lbab$b;
    //   350: astore_2
    //   351: new 68	java/lang/StringBuilder
    //   354: dup
    //   355: invokespecial 69	java/lang/StringBuilder:<init>	()V
    //   358: astore 4
    //   360: aload 4
    //   362: ldc -55
    //   364: invokevirtual 73	java/lang/StringBuilder:append	(Ljava/lang/String;)Ljava/lang/StringBuilder;
    //   367: pop
    //   368: aload 4
    //   370: aload 8
    //   372: invokevirtual 187	AZa:a	()J
    //   375: invokevirtual 190	java/lang/StringBuilder:append	(J)Ljava/lang/StringBuilder;
    //   378: pop
    //   379: aload_2
    //   380: aload 4
    //   382: invokevirtual 79	java/lang/StringBuilder:toString	()Ljava/lang/String;
    //   385: invokeinterface 82 2 0
    //   390: aload_3
    //   391: invokevirtual 204	xZa:c	()LoZa;
    //   394: astore_2
    //   395: aload_2
    //   396: invokevirtual 206	oZa:b	()I
    //   399: istore 10
    //   401: iconst_0
    //   402: istore 11
    //   404: iload 11
    //   406: iload 10
    //   408: if_icmpge +44 -> 452
    //   411: aload_2
    //   412: iload 11
    //   414: invokevirtual 56	oZa:a	(I)Ljava/lang/String;
    //   417: astore 4
    //   419: ldc -48
    //   421: aload 4
    //   423: invokevirtual 128	java/lang/String:equalsIgnoreCase	(Ljava/lang/String;)Z
    //   426: ifne +20 -> 446
    //   429: ldc -46
    //   431: aload 4
    //   433: invokevirtual 128	java/lang/String:equalsIgnoreCase	(Ljava/lang/String;)Z
    //   436: ifne +10 -> 446
    //   439: aload_0
    //   440: aload_2
    //   441: iload 11
    //   443: invokespecial 212	bab:a	(LoZa;I)V
    //   446: iinc 11 1
    //   449: goto -45 -> 404
    //   452: iload 6
    //   454: ifeq +342 -> 796
    //   457: iload 5
    //   459: ifne +6 -> 465
    //   462: goto +334 -> 796
    //   465: aload_3
    //   466: invokevirtual 204	xZa:c	()LoZa;
    //   469: invokestatic 214	bab:a	(LoZa;)Z
    //   472: ifeq +54 -> 526
    //   475: aload_0
    //   476: getfield 50	bab:b	Lbab$b;
    //   479: astore 4
    //   481: new 68	java/lang/StringBuilder
    //   484: dup
    //   485: invokespecial 69	java/lang/StringBuilder:<init>	()V
    //   488: astore_2
    //   489: aload_2
    //   490: ldc -40
    //   492: invokevirtual 73	java/lang/StringBuilder:append	(Ljava/lang/String;)Ljava/lang/StringBuilder;
    //   495: pop
    //   496: aload_2
    //   497: aload_3
    //   498: invokevirtual 162	xZa:e	()Ljava/lang/String;
    //   501: invokevirtual 73	java/lang/StringBuilder:append	(Ljava/lang/String;)Ljava/lang/StringBuilder;
    //   504: pop
    //   505: aload_2
    //   506: ldc -38
    //   508: invokevirtual 73	java/lang/StringBuilder:append	(Ljava/lang/String;)Ljava/lang/StringBuilder;
    //   511: pop
    //   512: aload 4
    //   514: aload_2
    //   515: invokevirtual 79	java/lang/StringBuilder:toString	()Ljava/lang/String;
    //   518: invokeinterface 82 2 0
    //   523: goto +314 -> 837
    //   526: aload 8
    //   528: invokevirtual 220	AZa:c	()Z
    //   531: ifeq +54 -> 585
    //   534: aload_0
    //   535: getfield 50	bab:b	Lbab$b;
    //   538: astore 4
    //   540: new 68	java/lang/StringBuilder
    //   543: dup
    //   544: invokespecial 69	java/lang/StringBuilder:<init>	()V
    //   547: astore_2
    //   548: aload_2
    //   549: ldc -40
    //   551: invokevirtual 73	java/lang/StringBuilder:append	(Ljava/lang/String;)Ljava/lang/StringBuilder;
    //   554: pop
    //   555: aload_2
    //   556: aload_3
    //   557: invokevirtual 162	xZa:e	()Ljava/lang/String;
    //   560: invokevirtual 73	java/lang/StringBuilder:append	(Ljava/lang/String;)Ljava/lang/StringBuilder;
    //   563: pop
    //   564: aload_2
    //   565: ldc -34
    //   567: invokevirtual 73	java/lang/StringBuilder:append	(Ljava/lang/String;)Ljava/lang/StringBuilder;
    //   570: pop
    //   571: aload 4
    //   573: aload_2
    //   574: invokevirtual 79	java/lang/StringBuilder:toString	()Ljava/lang/String;
    //   577: invokeinterface 82 2 0
    //   582: goto +255 -> 837
    //   585: new 87	jab
    //   588: dup
    //   589: invokespecial 88	jab:<init>	()V
    //   592: astore 4
    //   594: aload 8
    //   596: aload 4
    //   598: invokevirtual 225	AZa:a	(Lkab;)V
    //   601: getstatic 31	bab:a	Ljava/nio/charset/Charset;
    //   604: astore_2
    //   605: aload 8
    //   607: invokevirtual 195	AZa:b	()LrZa;
    //   610: astore 9
    //   612: aload 9
    //   614: ifnull +12 -> 626
    //   617: aload 9
    //   619: getstatic 31	bab:a	Ljava/nio/charset/Charset;
    //   622: invokevirtual 230	rZa:a	(Ljava/nio/charset/Charset;)Ljava/nio/charset/Charset;
    //   625: astore_2
    //   626: aload_0
    //   627: getfield 50	bab:b	Lbab$b;
    //   630: ldc -75
    //   632: invokeinterface 82 2 0
    //   637: aload 4
    //   639: invokestatic 232	bab:a	(Ljab;)Z
    //   642: ifeq +86 -> 728
    //   645: aload_0
    //   646: getfield 50	bab:b	Lbab$b;
    //   649: aload 4
    //   651: aload_2
    //   652: invokevirtual 235	jab:a	(Ljava/nio/charset/Charset;)Ljava/lang/String;
    //   655: invokeinterface 82 2 0
    //   660: aload_0
    //   661: getfield 50	bab:b	Lbab$b;
    //   664: astore 4
    //   666: new 68	java/lang/StringBuilder
    //   669: dup
    //   670: invokespecial 69	java/lang/StringBuilder:<init>	()V
    //   673: astore_2
    //   674: aload_2
    //   675: ldc -40
    //   677: invokevirtual 73	java/lang/StringBuilder:append	(Ljava/lang/String;)Ljava/lang/StringBuilder;
    //   680: pop
    //   681: aload_2
    //   682: aload_3
    //   683: invokevirtual 162	xZa:e	()Ljava/lang/String;
    //   686: invokevirtual 73	java/lang/StringBuilder:append	(Ljava/lang/String;)Ljava/lang/StringBuilder;
    //   689: pop
    //   690: aload_2
    //   691: ldc -73
    //   693: invokevirtual 73	java/lang/StringBuilder:append	(Ljava/lang/String;)Ljava/lang/StringBuilder;
    //   696: pop
    //   697: aload_2
    //   698: aload 8
    //   700: invokevirtual 187	AZa:a	()J
    //   703: invokevirtual 190	java/lang/StringBuilder:append	(J)Ljava/lang/StringBuilder;
    //   706: pop
    //   707: aload_2
    //   708: ldc -64
    //   710: invokevirtual 73	java/lang/StringBuilder:append	(Ljava/lang/String;)Ljava/lang/StringBuilder;
    //   713: pop
    //   714: aload 4
    //   716: aload_2
    //   717: invokevirtual 79	java/lang/StringBuilder:toString	()Ljava/lang/String;
    //   720: invokeinterface 82 2 0
    //   725: goto +112 -> 837
    //   728: aload_0
    //   729: getfield 50	bab:b	Lbab$b;
    //   732: astore 4
    //   734: new 68	java/lang/StringBuilder
    //   737: dup
    //   738: invokespecial 69	java/lang/StringBuilder:<init>	()V
    //   741: astore_2
    //   742: aload_2
    //   743: ldc -40
    //   745: invokevirtual 73	java/lang/StringBuilder:append	(Ljava/lang/String;)Ljava/lang/StringBuilder;
    //   748: pop
    //   749: aload_2
    //   750: aload_3
    //   751: invokevirtual 162	xZa:e	()Ljava/lang/String;
    //   754: invokevirtual 73	java/lang/StringBuilder:append	(Ljava/lang/String;)Ljava/lang/StringBuilder;
    //   757: pop
    //   758: aload_2
    //   759: ldc -19
    //   761: invokevirtual 73	java/lang/StringBuilder:append	(Ljava/lang/String;)Ljava/lang/StringBuilder;
    //   764: pop
    //   765: aload_2
    //   766: aload 8
    //   768: invokevirtual 187	AZa:a	()J
    //   771: invokevirtual 190	java/lang/StringBuilder:append	(J)Ljava/lang/StringBuilder;
    //   774: pop
    //   775: aload_2
    //   776: ldc -17
    //   778: invokevirtual 73	java/lang/StringBuilder:append	(Ljava/lang/String;)Ljava/lang/StringBuilder;
    //   781: pop
    //   782: aload 4
    //   784: aload_2
    //   785: invokevirtual 79	java/lang/StringBuilder:toString	()Ljava/lang/String;
    //   788: invokeinterface 82 2 0
    //   793: goto +44 -> 837
    //   796: aload_0
    //   797: getfield 50	bab:b	Lbab$b;
    //   800: astore 4
    //   802: new 68	java/lang/StringBuilder
    //   805: dup
    //   806: invokespecial 69	java/lang/StringBuilder:<init>	()V
    //   809: astore_2
    //   810: aload_2
    //   811: ldc -40
    //   813: invokevirtual 73	java/lang/StringBuilder:append	(Ljava/lang/String;)Ljava/lang/StringBuilder;
    //   816: pop
    //   817: aload_2
    //   818: aload_3
    //   819: invokevirtual 162	xZa:e	()Ljava/lang/String;
    //   822: invokevirtual 73	java/lang/StringBuilder:append	(Ljava/lang/String;)Ljava/lang/StringBuilder;
    //   825: pop
    //   826: aload 4
    //   828: aload_2
    //   829: invokevirtual 79	java/lang/StringBuilder:toString	()Ljava/lang/String;
    //   832: invokeinterface 82 2 0
    //   837: invokestatic 244	java/lang/System:nanoTime	()J
    //   840: lstore 12
    //   842: aload_1
    //   843: aload_3
    //   844: invokeinterface 146 2 0
    //   849: astore 8
    //   851: getstatic 250	java/util/concurrent/TimeUnit:NANOSECONDS	Ljava/util/concurrent/TimeUnit;
    //   854: invokestatic 244	java/lang/System:nanoTime	()J
    //   857: lload 12
    //   859: lsub
    //   860: invokevirtual 254	java/util/concurrent/TimeUnit:toMillis	(J)J
    //   863: lstore 12
    //   865: aload 8
    //   867: invokevirtual 259	BZa:a	()LDZa;
    //   870: astore 9
    //   872: aload 9
    //   874: invokevirtual 263	DZa:c	()J
    //   877: lstore 14
    //   879: lload 14
    //   881: ldc2_w 198
    //   884: lcmp
    //   885: ifeq +34 -> 919
    //   888: new 68	java/lang/StringBuilder
    //   891: dup
    //   892: invokespecial 69	java/lang/StringBuilder:<init>	()V
    //   895: astore_1
    //   896: aload_1
    //   897: lload 14
    //   899: invokevirtual 190	java/lang/StringBuilder:append	(J)Ljava/lang/StringBuilder;
    //   902: pop
    //   903: aload_1
    //   904: ldc_w 265
    //   907: invokevirtual 73	java/lang/StringBuilder:append	(Ljava/lang/String;)Ljava/lang/StringBuilder;
    //   910: pop
    //   911: aload_1
    //   912: invokevirtual 79	java/lang/StringBuilder:toString	()Ljava/lang/String;
    //   915: astore_1
    //   916: goto +7 -> 923
    //   919: ldc_w 267
    //   922: astore_1
    //   923: aload_0
    //   924: getfield 50	bab:b	Lbab$b;
    //   927: astore_3
    //   928: new 68	java/lang/StringBuilder
    //   931: dup
    //   932: invokespecial 69	java/lang/StringBuilder:<init>	()V
    //   935: astore 4
    //   937: aload 4
    //   939: ldc_w 269
    //   942: invokevirtual 73	java/lang/StringBuilder:append	(Ljava/lang/String;)Ljava/lang/StringBuilder;
    //   945: pop
    //   946: aload 4
    //   948: aload 8
    //   950: invokevirtual 271	BZa:c	()I
    //   953: invokevirtual 274	java/lang/StringBuilder:append	(I)Ljava/lang/StringBuilder;
    //   956: pop
    //   957: aload 8
    //   959: invokevirtual 276	BZa:g	()Ljava/lang/String;
    //   962: invokevirtual 279	java/lang/String:isEmpty	()Z
    //   965: ifeq +9 -> 974
    //   968: ldc -75
    //   970: astore_2
    //   971: goto +33 -> 1004
    //   974: new 68	java/lang/StringBuilder
    //   977: dup
    //   978: invokespecial 69	java/lang/StringBuilder:<init>	()V
    //   981: astore_2
    //   982: aload_2
    //   983: bipush 32
    //   985: invokevirtual 165	java/lang/StringBuilder:append	(C)Ljava/lang/StringBuilder;
    //   988: pop
    //   989: aload_2
    //   990: aload 8
    //   992: invokevirtual 276	BZa:g	()Ljava/lang/String;
    //   995: invokevirtual 73	java/lang/StringBuilder:append	(Ljava/lang/String;)Ljava/lang/StringBuilder;
    //   998: pop
    //   999: aload_2
    //   1000: invokevirtual 79	java/lang/StringBuilder:toString	()Ljava/lang/String;
    //   1003: astore_2
    //   1004: aload 4
    //   1006: aload_2
    //   1007: invokevirtual 73	java/lang/StringBuilder:append	(Ljava/lang/String;)Ljava/lang/StringBuilder;
    //   1010: pop
    //   1011: aload 4
    //   1013: bipush 32
    //   1015: invokevirtual 165	java/lang/StringBuilder:append	(C)Ljava/lang/StringBuilder;
    //   1018: pop
    //   1019: aload 4
    //   1021: aload 8
    //   1023: invokevirtual 282	BZa:k	()LxZa;
    //   1026: invokevirtual 169	xZa:g	()LpZa;
    //   1029: invokevirtual 172	java/lang/StringBuilder:append	(Ljava/lang/Object;)Ljava/lang/StringBuilder;
    //   1032: pop
    //   1033: aload 4
    //   1035: ldc -73
    //   1037: invokevirtual 73	java/lang/StringBuilder:append	(Ljava/lang/String;)Ljava/lang/StringBuilder;
    //   1040: pop
    //   1041: aload 4
    //   1043: lload 12
    //   1045: invokevirtual 190	java/lang/StringBuilder:append	(J)Ljava/lang/StringBuilder;
    //   1048: pop
    //   1049: aload 4
    //   1051: ldc_w 284
    //   1054: invokevirtual 73	java/lang/StringBuilder:append	(Ljava/lang/String;)Ljava/lang/StringBuilder;
    //   1057: pop
    //   1058: iload 7
    //   1060: ifne +41 -> 1101
    //   1063: new 68	java/lang/StringBuilder
    //   1066: dup
    //   1067: invokespecial 69	java/lang/StringBuilder:<init>	()V
    //   1070: astore_2
    //   1071: aload_2
    //   1072: ldc_w 286
    //   1075: invokevirtual 73	java/lang/StringBuilder:append	(Ljava/lang/String;)Ljava/lang/StringBuilder;
    //   1078: pop
    //   1079: aload_2
    //   1080: aload_1
    //   1081: invokevirtual 73	java/lang/StringBuilder:append	(Ljava/lang/String;)Ljava/lang/StringBuilder;
    //   1084: pop
    //   1085: aload_2
    //   1086: ldc_w 288
    //   1089: invokevirtual 73	java/lang/StringBuilder:append	(Ljava/lang/String;)Ljava/lang/StringBuilder;
    //   1092: pop
    //   1093: aload_2
    //   1094: invokevirtual 79	java/lang/StringBuilder:toString	()Ljava/lang/String;
    //   1097: astore_1
    //   1098: goto +6 -> 1104
    //   1101: ldc -75
    //   1103: astore_1
    //   1104: aload 4
    //   1106: aload_1
    //   1107: invokevirtual 73	java/lang/StringBuilder:append	(Ljava/lang/String;)Ljava/lang/StringBuilder;
    //   1110: pop
    //   1111: aload 4
    //   1113: bipush 41
    //   1115: invokevirtual 165	java/lang/StringBuilder:append	(C)Ljava/lang/StringBuilder;
    //   1118: pop
    //   1119: aload_3
    //   1120: aload 4
    //   1122: invokevirtual 79	java/lang/StringBuilder:toString	()Ljava/lang/String;
    //   1125: invokeinterface 82 2 0
    //   1130: iload 7
    //   1132: ifeq +493 -> 1625
    //   1135: aload 8
    //   1137: invokevirtual 290	BZa:e	()LoZa;
    //   1140: astore_2
    //   1141: aload_2
    //   1142: invokevirtual 206	oZa:b	()I
    //   1145: istore 5
    //   1147: iconst_0
    //   1148: istore 7
    //   1150: iload 7
    //   1152: iload 5
    //   1154: if_icmpge +16 -> 1170
    //   1157: aload_0
    //   1158: aload_2
    //   1159: iload 7
    //   1161: invokespecial 212	bab:a	(LoZa;I)V
    //   1164: iinc 7 1
    //   1167: goto -17 -> 1150
    //   1170: iload 6
    //   1172: ifeq +441 -> 1613
    //   1175: aload 8
    //   1177: invokestatic 295	i_a:b	(LBZa;)Z
    //   1180: ifne +6 -> 1186
    //   1183: goto +430 -> 1613
    //   1186: aload 8
    //   1188: invokevirtual 290	BZa:e	()LoZa;
    //   1191: invokestatic 214	bab:a	(LoZa;)Z
    //   1194: ifeq +18 -> 1212
    //   1197: aload_0
    //   1198: getfield 50	bab:b	Lbab$b;
    //   1201: ldc_w 297
    //   1204: invokeinterface 82 2 0
    //   1209: goto +416 -> 1625
    //   1212: aload 9
    //   1214: invokevirtual 300	DZa:e	()Llab;
    //   1217: astore_1
    //   1218: aload_1
    //   1219: ldc2_w 301
    //   1222: invokeinterface 307 3 0
    //   1227: pop
    //   1228: aload_1
    //   1229: invokeinterface 311 1 0
    //   1234: astore_1
    //   1235: ldc -126
    //   1237: aload_2
    //   1238: ldc 117
    //   1240: invokevirtual 120	oZa:b	(Ljava/lang/String;)Ljava/lang/String;
    //   1243: invokevirtual 128	java/lang/String:equalsIgnoreCase	(Ljava/lang/String;)Z
    //   1246: istore 16
    //   1248: aconst_null
    //   1249: astore_3
    //   1250: iload 16
    //   1252: ifeq +98 -> 1350
    //   1255: aload_1
    //   1256: invokevirtual 92	jab:size	()J
    //   1259: invokestatic 317	java/lang/Long:valueOf	(J)Ljava/lang/Long;
    //   1262: astore_2
    //   1263: new 319	qab
    //   1266: dup
    //   1267: aload_1
    //   1268: invokevirtual 322	jab:clone	()Ljab;
    //   1271: invokespecial 325	qab:<init>	(LEab;)V
    //   1274: astore 17
    //   1276: aload_3
    //   1277: astore_1
    //   1278: new 87	jab
    //   1281: astore 4
    //   1283: aload_3
    //   1284: astore_1
    //   1285: aload 4
    //   1287: invokespecial 88	jab:<init>	()V
    //   1290: aload_3
    //   1291: astore_1
    //   1292: aload 4
    //   1294: aload 17
    //   1296: invokevirtual 328	jab:a	(LEab;)J
    //   1299: pop2
    //   1300: aload 17
    //   1302: invokevirtual 331	qab:close	()V
    //   1305: aload 4
    //   1307: astore_1
    //   1308: goto +44 -> 1352
    //   1311: astore_2
    //   1312: goto +8 -> 1320
    //   1315: astore_2
    //   1316: aload_2
    //   1317: astore_1
    //   1318: aload_2
    //   1319: athrow
    //   1320: aload_1
    //   1321: ifnull +22 -> 1343
    //   1324: aload 17
    //   1326: invokevirtual 331	qab:close	()V
    //   1329: goto +19 -> 1348
    //   1332: astore 4
    //   1334: aload_1
    //   1335: aload 4
    //   1337: invokevirtual 335	java/lang/Throwable:addSuppressed	(Ljava/lang/Throwable;)V
    //   1340: goto +8 -> 1348
    //   1343: aload 17
    //   1345: invokevirtual 331	qab:close	()V
    //   1348: aload_2
    //   1349: athrow
    //   1350: aconst_null
    //   1351: astore_2
    //   1352: getstatic 31	bab:a	Ljava/nio/charset/Charset;
    //   1355: astore 4
    //   1357: aload 9
    //   1359: invokevirtual 337	DZa:d	()LrZa;
    //   1362: astore_3
    //   1363: aload_3
    //   1364: ifnull +12 -> 1376
    //   1367: aload_3
    //   1368: getstatic 31	bab:a	Ljava/nio/charset/Charset;
    //   1371: invokevirtual 230	rZa:a	(Ljava/nio/charset/Charset;)Ljava/nio/charset/Charset;
    //   1374: astore 4
    //   1376: aload_1
    //   1377: invokestatic 232	bab:a	(Ljab;)Z
    //   1380: ifne +69 -> 1449
    //   1383: aload_0
    //   1384: getfield 50	bab:b	Lbab$b;
    //   1387: ldc -75
    //   1389: invokeinterface 82 2 0
    //   1394: aload_0
    //   1395: getfield 50	bab:b	Lbab$b;
    //   1398: astore_2
    //   1399: new 68	java/lang/StringBuilder
    //   1402: dup
    //   1403: invokespecial 69	java/lang/StringBuilder:<init>	()V
    //   1406: astore 4
    //   1408: aload 4
    //   1410: ldc_w 339
    //   1413: invokevirtual 73	java/lang/StringBuilder:append	(Ljava/lang/String;)Ljava/lang/StringBuilder;
    //   1416: pop
    //   1417: aload 4
    //   1419: aload_1
    //   1420: invokevirtual 92	jab:size	()J
    //   1423: invokevirtual 190	java/lang/StringBuilder:append	(J)Ljava/lang/StringBuilder;
    //   1426: pop
    //   1427: aload 4
    //   1429: ldc -17
    //   1431: invokevirtual 73	java/lang/StringBuilder:append	(Ljava/lang/String;)Ljava/lang/StringBuilder;
    //   1434: pop
    //   1435: aload_2
    //   1436: aload 4
    //   1438: invokevirtual 79	java/lang/StringBuilder:toString	()Ljava/lang/String;
    //   1441: invokeinterface 82 2 0
    //   1446: aload 8
    //   1448: areturn
    //   1449: lload 14
    //   1451: lconst_0
    //   1452: lcmp
    //   1453: ifeq +32 -> 1485
    //   1456: aload_0
    //   1457: getfield 50	bab:b	Lbab$b;
    //   1460: ldc -75
    //   1462: invokeinterface 82 2 0
    //   1467: aload_0
    //   1468: getfield 50	bab:b	Lbab$b;
    //   1471: aload_1
    //   1472: invokevirtual 322	jab:clone	()Ljab;
    //   1475: aload 4
    //   1477: invokevirtual 235	jab:a	(Ljava/nio/charset/Charset;)Ljava/lang/String;
    //   1480: invokeinterface 82 2 0
    //   1485: aload_2
    //   1486: ifnull +75 -> 1561
    //   1489: aload_0
    //   1490: getfield 50	bab:b	Lbab$b;
    //   1493: astore_3
    //   1494: new 68	java/lang/StringBuilder
    //   1497: dup
    //   1498: invokespecial 69	java/lang/StringBuilder:<init>	()V
    //   1501: astore 4
    //   1503: aload 4
    //   1505: ldc_w 341
    //   1508: invokevirtual 73	java/lang/StringBuilder:append	(Ljava/lang/String;)Ljava/lang/StringBuilder;
    //   1511: pop
    //   1512: aload 4
    //   1514: aload_1
    //   1515: invokevirtual 92	jab:size	()J
    //   1518: invokevirtual 190	java/lang/StringBuilder:append	(J)Ljava/lang/StringBuilder;
    //   1521: pop
    //   1522: aload 4
    //   1524: ldc_w 343
    //   1527: invokevirtual 73	java/lang/StringBuilder:append	(Ljava/lang/String;)Ljava/lang/StringBuilder;
    //   1530: pop
    //   1531: aload 4
    //   1533: aload_2
    //   1534: invokevirtual 172	java/lang/StringBuilder:append	(Ljava/lang/Object;)Ljava/lang/StringBuilder;
    //   1537: pop
    //   1538: aload 4
    //   1540: ldc_w 345
    //   1543: invokevirtual 73	java/lang/StringBuilder:append	(Ljava/lang/String;)Ljava/lang/StringBuilder;
    //   1546: pop
    //   1547: aload_3
    //   1548: aload 4
    //   1550: invokevirtual 79	java/lang/StringBuilder:toString	()Ljava/lang/String;
    //   1553: invokeinterface 82 2 0
    //   1558: goto +67 -> 1625
    //   1561: aload_0
    //   1562: getfield 50	bab:b	Lbab$b;
    //   1565: astore 4
    //   1567: new 68	java/lang/StringBuilder
    //   1570: dup
    //   1571: invokespecial 69	java/lang/StringBuilder:<init>	()V
    //   1574: astore_2
    //   1575: aload_2
    //   1576: ldc_w 341
    //   1579: invokevirtual 73	java/lang/StringBuilder:append	(Ljava/lang/String;)Ljava/lang/StringBuilder;
    //   1582: pop
    //   1583: aload_2
    //   1584: aload_1
    //   1585: invokevirtual 92	jab:size	()J
    //   1588: invokevirtual 190	java/lang/StringBuilder:append	(J)Ljava/lang/StringBuilder;
    //   1591: pop
    //   1592: aload_2
    //   1593: ldc -64
    //   1595: invokevirtual 73	java/lang/StringBuilder:append	(Ljava/lang/String;)Ljava/lang/StringBuilder;
    //   1598: pop
    //   1599: aload 4
    //   1601: aload_2
    //   1602: invokevirtual 79	java/lang/StringBuilder:toString	()Ljava/lang/String;
    //   1605: invokeinterface 82 2 0
    //   1610: goto +15 -> 1625
    //   1613: aload_0
    //   1614: getfield 50	bab:b	Lbab$b;
    //   1617: ldc_w 347
    //   1620: invokeinterface 82 2 0
    //   1625: aload 8
    //   1627: areturn
    //   1628: astore_1
    //   1629: aload_0
    //   1630: getfield 50	bab:b	Lbab$b;
    //   1633: astore 4
    //   1635: new 68	java/lang/StringBuilder
    //   1638: dup
    //   1639: invokespecial 69	java/lang/StringBuilder:<init>	()V
    //   1642: astore_2
    //   1643: aload_2
    //   1644: ldc_w 349
    //   1647: invokevirtual 73	java/lang/StringBuilder:append	(Ljava/lang/String;)Ljava/lang/StringBuilder;
    //   1650: pop
    //   1651: aload_2
    //   1652: aload_1
    //   1653: invokevirtual 172	java/lang/StringBuilder:append	(Ljava/lang/Object;)Ljava/lang/StringBuilder;
    //   1656: pop
    //   1657: aload 4
    //   1659: aload_2
    //   1660: invokevirtual 79	java/lang/StringBuilder:toString	()Ljava/lang/String;
    //   1663: invokeinterface 82 2 0
    //   1668: aload_1
    //   1669: athrow
    // Local variable table:
    //   start	length	slot	name	signature
    //   0	1670	0	this	bab
    //   0	1670	1	parama	qZa.a
    //   4	1259	2	localObject1	Object
    //   1311	1	2	localObject2	Object
    //   1315	34	2	localThrowable1	Throwable
    //   1351	309	2	localObject3	Object
    //   11	1537	3	localObject4	Object
    //   30	1276	4	localObject5	Object
    //   1332	4	4	localThrowable2	Throwable
    //   1355	303	4	localObject6	Object
    //   33	1122	5	i	int
    //   42	1129	6	j	int
    //   66	1099	7	k	int
    //   78	1548	8	localObject7	Object
    //   154	1204	9	localObject8	Object
    //   399	10	10	m	int
    //   402	45	11	n	int
    //   840	204	12	l1	long
    //   877	573	14	l2	long
    //   1246	5	16	bool	boolean
    //   1274	70	17	localqab	qab
    // Exception table:
    //   from	to	target	type
    //   1278	1283	1311	finally
    //   1285	1290	1311	finally
    //   1292	1300	1311	finally
    //   1318	1320	1311	finally
    //   1278	1283	1315	java/lang/Throwable
    //   1285	1290	1315	java/lang/Throwable
    //   1292	1300	1315	java/lang/Throwable
    //   1324	1329	1332	java/lang/Throwable
    //   842	851	1628	java/lang/Exception
  }
  
  public bab a(bab.a parama)
  {
    if (parama != null)
    {
      this.d = parama;
      return this;
    }
    throw new NullPointerException("level == null. Use Level.NONE instead.");
  }
  
  public static enum a
  {
    private a() {}
  }
  
  public static abstract interface b
  {
    public static final b a = aab.a;
    
    public abstract void a(String paramString);
  }
}


/* Location:              /Applications/dex2jar/classes2-dex2jar.jar!/bab.class
 * Java compiler version: 6 (50.0)
 * JD-Core Version:       0.7.1
 */