public final class mAa
{
  public static final mAa a = new mAa();
  
  /* Error */
  public final tka a(tka paramtka)
  {
    // Byte code:
    //   0: aload_1
    //   1: ldc 18
    //   3: invokestatic 24	oXa:b	(Ljava/lang/Object;Ljava/lang/String;)V
    //   6: aload_1
    //   7: invokevirtual 29	tka:a	()Ljava/lang/String;
    //   10: astore_2
    //   11: aload_2
    //   12: invokevirtual 35	java/lang/String:hashCode	()I
    //   15: lookupswitch	default:+329->344, -2075523360:+800->815, -1856560363:+788->803, -1663019586:+776->791, -1624760229:+764->779, -1616157814:+752->767, -1406316010:+740->755, -1405842175:+728->743, -1380612710:+716->731, -1360334095:+704->719, -1357517635:+692->707, -1110440649:+680->695, -1110258756:+668->683, -1048873313:+656->671, -980228552:+644->659, -934871637:+632->647, -905411385:+620->635, -892364808:+608->623, -891901482:+596->611, -566947070:+584->599, -278389504:+572->587, 103158:+560->575, 2990433:+548->563, 3059428:+536->551, 3351650:+524->539, 3506021:+512->527, 3615689:+500->515, 3641989:+488->503, 93838169:+476->491, 95346418:+464->479, 97513422:+452->467, 104076845:+440->455, 105888192:+428->443, 108405406:+416->431, 109324790:+404->419, 462452390:+392->407, 1026124518:+380->395, 1136629407:+368->383, 1363664645:+356->371, 1544324133:+344->359, 1650323088:+332->347
    //   344: goto +483 -> 827
    //   347: aload_2
    //   348: ldc 37
    //   350: invokevirtual 41	java/lang/String:equals	(Ljava/lang/Object;)Z
    //   353: ifeq +474 -> 827
    //   356: goto +473 -> 829
    //   359: aload_2
    //   360: ldc 43
    //   362: invokevirtual 41	java/lang/String:equals	(Ljava/lang/Object;)Z
    //   365: ifeq +462 -> 827
    //   368: goto +461 -> 829
    //   371: aload_2
    //   372: ldc 45
    //   374: invokevirtual 41	java/lang/String:equals	(Ljava/lang/Object;)Z
    //   377: ifeq +450 -> 827
    //   380: goto +449 -> 829
    //   383: aload_2
    //   384: ldc 47
    //   386: invokevirtual 41	java/lang/String:equals	(Ljava/lang/Object;)Z
    //   389: ifeq +438 -> 827
    //   392: goto +437 -> 829
    //   395: aload_2
    //   396: ldc 49
    //   398: invokevirtual 41	java/lang/String:equals	(Ljava/lang/Object;)Z
    //   401: ifeq +426 -> 827
    //   404: goto +425 -> 829
    //   407: aload_2
    //   408: ldc 51
    //   410: invokevirtual 41	java/lang/String:equals	(Ljava/lang/Object;)Z
    //   413: ifeq +414 -> 827
    //   416: goto +413 -> 829
    //   419: aload_2
    //   420: ldc 53
    //   422: invokevirtual 41	java/lang/String:equals	(Ljava/lang/Object;)Z
    //   425: ifeq +402 -> 827
    //   428: goto +401 -> 829
    //   431: aload_2
    //   432: ldc 55
    //   434: invokevirtual 41	java/lang/String:equals	(Ljava/lang/Object;)Z
    //   437: ifeq +390 -> 827
    //   440: goto +389 -> 829
    //   443: aload_2
    //   444: ldc 57
    //   446: invokevirtual 41	java/lang/String:equals	(Ljava/lang/Object;)Z
    //   449: ifeq +378 -> 827
    //   452: goto +377 -> 829
    //   455: aload_2
    //   456: ldc 59
    //   458: invokevirtual 41	java/lang/String:equals	(Ljava/lang/Object;)Z
    //   461: ifeq +366 -> 827
    //   464: goto +365 -> 829
    //   467: aload_2
    //   468: ldc 61
    //   470: invokevirtual 41	java/lang/String:equals	(Ljava/lang/Object;)Z
    //   473: ifeq +354 -> 827
    //   476: goto +353 -> 829
    //   479: aload_2
    //   480: ldc 63
    //   482: invokevirtual 41	java/lang/String:equals	(Ljava/lang/Object;)Z
    //   485: ifeq +342 -> 827
    //   488: goto +341 -> 829
    //   491: aload_2
    //   492: ldc 65
    //   494: invokevirtual 41	java/lang/String:equals	(Ljava/lang/Object;)Z
    //   497: ifeq +330 -> 827
    //   500: goto +329 -> 829
    //   503: aload_2
    //   504: ldc 67
    //   506: invokevirtual 41	java/lang/String:equals	(Ljava/lang/Object;)Z
    //   509: ifeq +318 -> 827
    //   512: goto +317 -> 829
    //   515: aload_2
    //   516: ldc 69
    //   518: invokevirtual 41	java/lang/String:equals	(Ljava/lang/Object;)Z
    //   521: ifeq +306 -> 827
    //   524: goto +305 -> 829
    //   527: aload_2
    //   528: ldc 71
    //   530: invokevirtual 41	java/lang/String:equals	(Ljava/lang/Object;)Z
    //   533: ifeq +294 -> 827
    //   536: goto +293 -> 829
    //   539: aload_2
    //   540: ldc 73
    //   542: invokevirtual 41	java/lang/String:equals	(Ljava/lang/Object;)Z
    //   545: ifeq +282 -> 827
    //   548: goto +281 -> 829
    //   551: aload_2
    //   552: ldc 75
    //   554: invokevirtual 41	java/lang/String:equals	(Ljava/lang/Object;)Z
    //   557: ifeq +270 -> 827
    //   560: goto +269 -> 829
    //   563: aload_2
    //   564: ldc 77
    //   566: invokevirtual 41	java/lang/String:equals	(Ljava/lang/Object;)Z
    //   569: ifeq +258 -> 827
    //   572: goto +257 -> 829
    //   575: aload_2
    //   576: ldc 79
    //   578: invokevirtual 41	java/lang/String:equals	(Ljava/lang/Object;)Z
    //   581: ifeq +246 -> 827
    //   584: goto +245 -> 829
    //   587: aload_2
    //   588: ldc 81
    //   590: invokevirtual 41	java/lang/String:equals	(Ljava/lang/Object;)Z
    //   593: ifeq +234 -> 827
    //   596: goto +233 -> 829
    //   599: aload_2
    //   600: ldc 83
    //   602: invokevirtual 41	java/lang/String:equals	(Ljava/lang/Object;)Z
    //   605: ifeq +222 -> 827
    //   608: goto +221 -> 829
    //   611: aload_2
    //   612: ldc 85
    //   614: invokevirtual 41	java/lang/String:equals	(Ljava/lang/Object;)Z
    //   617: ifeq +210 -> 827
    //   620: goto +209 -> 829
    //   623: aload_2
    //   624: ldc 87
    //   626: invokevirtual 41	java/lang/String:equals	(Ljava/lang/Object;)Z
    //   629: ifeq +198 -> 827
    //   632: goto +197 -> 829
    //   635: aload_2
    //   636: ldc 89
    //   638: invokevirtual 41	java/lang/String:equals	(Ljava/lang/Object;)Z
    //   641: ifeq +186 -> 827
    //   644: goto +185 -> 829
    //   647: aload_2
    //   648: ldc 91
    //   650: invokevirtual 41	java/lang/String:equals	(Ljava/lang/Object;)Z
    //   653: ifeq +174 -> 827
    //   656: goto +173 -> 829
    //   659: aload_2
    //   660: ldc 93
    //   662: invokevirtual 41	java/lang/String:equals	(Ljava/lang/Object;)Z
    //   665: ifeq +162 -> 827
    //   668: goto +161 -> 829
    //   671: aload_2
    //   672: ldc 95
    //   674: invokevirtual 41	java/lang/String:equals	(Ljava/lang/Object;)Z
    //   677: ifeq +150 -> 827
    //   680: goto +149 -> 829
    //   683: aload_2
    //   684: ldc 97
    //   686: invokevirtual 41	java/lang/String:equals	(Ljava/lang/Object;)Z
    //   689: ifeq +138 -> 827
    //   692: goto +137 -> 829
    //   695: aload_2
    //   696: ldc 99
    //   698: invokevirtual 41	java/lang/String:equals	(Ljava/lang/Object;)Z
    //   701: ifeq +126 -> 827
    //   704: goto +125 -> 829
    //   707: aload_2
    //   708: ldc 101
    //   710: invokevirtual 41	java/lang/String:equals	(Ljava/lang/Object;)Z
    //   713: ifeq +114 -> 827
    //   716: goto +113 -> 829
    //   719: aload_2
    //   720: ldc 103
    //   722: invokevirtual 41	java/lang/String:equals	(Ljava/lang/Object;)Z
    //   725: ifeq +102 -> 827
    //   728: goto +101 -> 829
    //   731: aload_2
    //   732: ldc 105
    //   734: invokevirtual 41	java/lang/String:equals	(Ljava/lang/Object;)Z
    //   737: ifeq +90 -> 827
    //   740: goto +89 -> 829
    //   743: aload_2
    //   744: ldc 107
    //   746: invokevirtual 41	java/lang/String:equals	(Ljava/lang/Object;)Z
    //   749: ifeq +78 -> 827
    //   752: goto +77 -> 829
    //   755: aload_2
    //   756: ldc 109
    //   758: invokevirtual 41	java/lang/String:equals	(Ljava/lang/Object;)Z
    //   761: ifeq +66 -> 827
    //   764: goto +65 -> 829
    //   767: aload_2
    //   768: ldc 111
    //   770: invokevirtual 41	java/lang/String:equals	(Ljava/lang/Object;)Z
    //   773: ifeq +54 -> 827
    //   776: goto +53 -> 829
    //   779: aload_2
    //   780: ldc 113
    //   782: invokevirtual 41	java/lang/String:equals	(Ljava/lang/Object;)Z
    //   785: ifeq +42 -> 827
    //   788: goto +41 -> 829
    //   791: aload_2
    //   792: ldc 115
    //   794: invokevirtual 41	java/lang/String:equals	(Ljava/lang/Object;)Z
    //   797: ifeq +30 -> 827
    //   800: goto +29 -> 829
    //   803: aload_2
    //   804: ldc 117
    //   806: invokevirtual 41	java/lang/String:equals	(Ljava/lang/Object;)Z
    //   809: ifeq +18 -> 827
    //   812: goto +17 -> 829
    //   815: aload_2
    //   816: ldc 119
    //   818: invokevirtual 41	java/lang/String:equals	(Ljava/lang/Object;)Z
    //   821: ifeq +6 -> 827
    //   824: goto +5 -> 829
    //   827: aconst_null
    //   828: astore_1
    //   829: aload_1
    //   830: areturn
    // Local variable table:
    //   start	length	slot	name	signature
    //   0	831	0	this	mAa
    //   0	831	1	paramtka	tka
    //   10	806	2	str	String
  }
}


/* Location:              /Applications/dex2jar/classes2-dex2jar.jar!/mAa.class
 * Java compiler version: 6 (50.0)
 * JD-Core Version:       0.7.1
 */