package com.google.android.gms.common.api.internal;

import com.google.android.gms.common.api.l;

final class wa
  implements Runnable
{
  wa(va paramva, l paraml) {}
  
  /* Error */
  public final void run()
  {
    // Byte code:
    //   0: getstatic 28	com/google/android/gms/common/api/internal/BasePendingResult:a	Ljava/lang/ThreadLocal;
    //   3: iconst_1
    //   4: invokestatic 34	java/lang/Boolean:valueOf	(Z)Ljava/lang/Boolean;
    //   7: invokevirtual 40	java/lang/ThreadLocal:set	(Ljava/lang/Object;)V
    //   10: aload_0
    //   11: getfield 14	com/google/android/gms/common/api/internal/wa:b	Lcom/google/android/gms/common/api/internal/va;
    //   14: invokestatic 45	com/google/android/gms/common/api/internal/va:a	(Lcom/google/android/gms/common/api/internal/va;)Lcom/google/android/gms/common/api/o;
    //   17: aload_0
    //   18: getfield 16	com/google/android/gms/common/api/internal/wa:a	Lcom/google/android/gms/common/api/l;
    //   21: invokevirtual 50	com/google/android/gms/common/api/o:a	(Lcom/google/android/gms/common/api/l;)Lcom/google/android/gms/common/api/g;
    //   24: astore_1
    //   25: aload_0
    //   26: getfield 14	com/google/android/gms/common/api/internal/wa:b	Lcom/google/android/gms/common/api/internal/va;
    //   29: invokestatic 53	com/google/android/gms/common/api/internal/va:b	(Lcom/google/android/gms/common/api/internal/va;)Lcom/google/android/gms/common/api/internal/xa;
    //   32: aload_0
    //   33: getfield 14	com/google/android/gms/common/api/internal/wa:b	Lcom/google/android/gms/common/api/internal/va;
    //   36: invokestatic 53	com/google/android/gms/common/api/internal/va:b	(Lcom/google/android/gms/common/api/internal/va;)Lcom/google/android/gms/common/api/internal/xa;
    //   39: iconst_0
    //   40: aload_1
    //   41: invokevirtual 59	android/os/Handler:obtainMessage	(ILjava/lang/Object;)Landroid/os/Message;
    //   44: invokevirtual 63	android/os/Handler:sendMessage	(Landroid/os/Message;)Z
    //   47: pop
    //   48: getstatic 28	com/google/android/gms/common/api/internal/BasePendingResult:a	Ljava/lang/ThreadLocal;
    //   51: iconst_0
    //   52: invokestatic 34	java/lang/Boolean:valueOf	(Z)Ljava/lang/Boolean;
    //   55: invokevirtual 40	java/lang/ThreadLocal:set	(Ljava/lang/Object;)V
    //   58: aload_0
    //   59: getfield 14	com/google/android/gms/common/api/internal/wa:b	Lcom/google/android/gms/common/api/internal/va;
    //   62: aload_0
    //   63: getfield 16	com/google/android/gms/common/api/internal/wa:a	Lcom/google/android/gms/common/api/l;
    //   66: invokestatic 65	com/google/android/gms/common/api/internal/va:a	(Lcom/google/android/gms/common/api/internal/va;Lcom/google/android/gms/common/api/l;)V
    //   69: aload_0
    //   70: getfield 14	com/google/android/gms/common/api/internal/wa:b	Lcom/google/android/gms/common/api/internal/va;
    //   73: invokestatic 69	com/google/android/gms/common/api/internal/va:c	(Lcom/google/android/gms/common/api/internal/va;)Ljava/lang/ref/WeakReference;
    //   76: invokevirtual 75	java/lang/ref/WeakReference:get	()Ljava/lang/Object;
    //   79: checkcast 77	com/google/android/gms/common/api/f
    //   82: astore_1
    //   83: aload_1
    //   84: ifnull +11 -> 95
    //   87: aload_1
    //   88: aload_0
    //   89: getfield 14	com/google/android/gms/common/api/internal/wa:b	Lcom/google/android/gms/common/api/internal/va;
    //   92: invokevirtual 80	com/google/android/gms/common/api/f:a	(Lcom/google/android/gms/common/api/internal/va;)V
    //   95: return
    //   96: astore_1
    //   97: goto +75 -> 172
    //   100: astore_1
    //   101: aload_0
    //   102: getfield 14	com/google/android/gms/common/api/internal/wa:b	Lcom/google/android/gms/common/api/internal/va;
    //   105: invokestatic 53	com/google/android/gms/common/api/internal/va:b	(Lcom/google/android/gms/common/api/internal/va;)Lcom/google/android/gms/common/api/internal/xa;
    //   108: aload_0
    //   109: getfield 14	com/google/android/gms/common/api/internal/wa:b	Lcom/google/android/gms/common/api/internal/va;
    //   112: invokestatic 53	com/google/android/gms/common/api/internal/va:b	(Lcom/google/android/gms/common/api/internal/va;)Lcom/google/android/gms/common/api/internal/xa;
    //   115: iconst_1
    //   116: aload_1
    //   117: invokevirtual 59	android/os/Handler:obtainMessage	(ILjava/lang/Object;)Landroid/os/Message;
    //   120: invokevirtual 63	android/os/Handler:sendMessage	(Landroid/os/Message;)Z
    //   123: pop
    //   124: getstatic 28	com/google/android/gms/common/api/internal/BasePendingResult:a	Ljava/lang/ThreadLocal;
    //   127: iconst_0
    //   128: invokestatic 34	java/lang/Boolean:valueOf	(Z)Ljava/lang/Boolean;
    //   131: invokevirtual 40	java/lang/ThreadLocal:set	(Ljava/lang/Object;)V
    //   134: aload_0
    //   135: getfield 14	com/google/android/gms/common/api/internal/wa:b	Lcom/google/android/gms/common/api/internal/va;
    //   138: aload_0
    //   139: getfield 16	com/google/android/gms/common/api/internal/wa:a	Lcom/google/android/gms/common/api/l;
    //   142: invokestatic 65	com/google/android/gms/common/api/internal/va:a	(Lcom/google/android/gms/common/api/internal/va;Lcom/google/android/gms/common/api/l;)V
    //   145: aload_0
    //   146: getfield 14	com/google/android/gms/common/api/internal/wa:b	Lcom/google/android/gms/common/api/internal/va;
    //   149: invokestatic 69	com/google/android/gms/common/api/internal/va:c	(Lcom/google/android/gms/common/api/internal/va;)Ljava/lang/ref/WeakReference;
    //   152: invokevirtual 75	java/lang/ref/WeakReference:get	()Ljava/lang/Object;
    //   155: checkcast 77	com/google/android/gms/common/api/f
    //   158: astore_1
    //   159: aload_1
    //   160: ifnull +11 -> 171
    //   163: aload_1
    //   164: aload_0
    //   165: getfield 14	com/google/android/gms/common/api/internal/wa:b	Lcom/google/android/gms/common/api/internal/va;
    //   168: invokevirtual 80	com/google/android/gms/common/api/f:a	(Lcom/google/android/gms/common/api/internal/va;)V
    //   171: return
    //   172: getstatic 28	com/google/android/gms/common/api/internal/BasePendingResult:a	Ljava/lang/ThreadLocal;
    //   175: iconst_0
    //   176: invokestatic 34	java/lang/Boolean:valueOf	(Z)Ljava/lang/Boolean;
    //   179: invokevirtual 40	java/lang/ThreadLocal:set	(Ljava/lang/Object;)V
    //   182: aload_0
    //   183: getfield 14	com/google/android/gms/common/api/internal/wa:b	Lcom/google/android/gms/common/api/internal/va;
    //   186: aload_0
    //   187: getfield 16	com/google/android/gms/common/api/internal/wa:a	Lcom/google/android/gms/common/api/l;
    //   190: invokestatic 65	com/google/android/gms/common/api/internal/va:a	(Lcom/google/android/gms/common/api/internal/va;Lcom/google/android/gms/common/api/l;)V
    //   193: aload_0
    //   194: getfield 14	com/google/android/gms/common/api/internal/wa:b	Lcom/google/android/gms/common/api/internal/va;
    //   197: invokestatic 69	com/google/android/gms/common/api/internal/va:c	(Lcom/google/android/gms/common/api/internal/va;)Ljava/lang/ref/WeakReference;
    //   200: invokevirtual 75	java/lang/ref/WeakReference:get	()Ljava/lang/Object;
    //   203: checkcast 77	com/google/android/gms/common/api/f
    //   206: astore_2
    //   207: aload_2
    //   208: ifnull +11 -> 219
    //   211: aload_2
    //   212: aload_0
    //   213: getfield 14	com/google/android/gms/common/api/internal/wa:b	Lcom/google/android/gms/common/api/internal/va;
    //   216: invokevirtual 80	com/google/android/gms/common/api/f:a	(Lcom/google/android/gms/common/api/internal/va;)V
    //   219: aload_1
    //   220: athrow
    // Local variable table:
    //   start	length	slot	name	signature
    //   0	221	0	this	wa
    //   24	64	1	localObject1	Object
    //   96	1	1	localObject2	Object
    //   100	17	1	localRuntimeException	RuntimeException
    //   158	62	1	localf1	com.google.android.gms.common.api.f
    //   206	6	2	localf2	com.google.android.gms.common.api.f
    // Exception table:
    //   from	to	target	type
    //   0	48	96	finally
    //   101	124	96	finally
    //   0	48	100	java/lang/RuntimeException
  }
}


/* Location:              /Applications/dex2jar/classes-dex2jar.jar!/com/google/android/gms/common/api/internal/wa.class
 * Java compiler version: 6 (50.0)
 * JD-Core Version:       0.7.1
 */