package com.google.android.gms.internal.ads;

import android.content.Context;
import android.os.Binder;
import com.google.android.gms.common.internal.c;

@yh
public final class cd
  implements fY
{
  private volatile Tc a;
  private final Context b;
  
  public cd(Context paramContext)
  {
    this.b = paramContext;
  }
  
  private final void a()
  {
    if (this.a == null) {
      return;
    }
    this.a.a();
    Binder.flushPendingCommands();
  }
  
  /* Error */
  public final HZ a(Iaa<?> paramIaa)
    throws xb
  {
    // Byte code:
    //   0: aload_1
    //   1: invokestatic 45	com/google/android/gms/internal/ads/Uc:a	(Lcom/google/android/gms/internal/ads/Iaa;)Lcom/google/android/gms/internal/ads/Uc;
    //   4: astore_1
    //   5: invokestatic 51	com/google/android/gms/ads/internal/k:j	()Lcom/google/android/gms/common/util/e;
    //   8: invokeinterface 56 1 0
    //   13: lstore_2
    //   14: new 58	com/google/android/gms/internal/ads/Hm
    //   17: astore 4
    //   19: aload 4
    //   21: invokespecial 59	com/google/android/gms/internal/ads/Hm:<init>	()V
    //   24: new 61	com/google/android/gms/internal/ads/gd
    //   27: astore 5
    //   29: aload 5
    //   31: aload_0
    //   32: aload 4
    //   34: invokespecial 64	com/google/android/gms/internal/ads/gd:<init>	(Lcom/google/android/gms/internal/ads/cd;Lcom/google/android/gms/internal/ads/Hm;)V
    //   37: new 66	com/google/android/gms/internal/ads/hd
    //   40: astore 6
    //   42: aload 6
    //   44: aload_0
    //   45: aload 4
    //   47: invokespecial 67	com/google/android/gms/internal/ads/hd:<init>	(Lcom/google/android/gms/internal/ads/cd;Lcom/google/android/gms/internal/ads/Hm;)V
    //   50: new 69	com/google/android/gms/internal/ads/Tc
    //   53: astore 7
    //   55: aload 7
    //   57: aload_0
    //   58: getfield 18	com/google/android/gms/internal/ads/cd:b	Landroid/content/Context;
    //   61: invokestatic 73	com/google/android/gms/ads/internal/k:q	()Lcom/google/android/gms/internal/ads/ul;
    //   64: invokevirtual 78	com/google/android/gms/internal/ads/ul:b	()Landroid/os/Looper;
    //   67: aload 5
    //   69: aload 6
    //   71: invokespecial 81	com/google/android/gms/internal/ads/Tc:<init>	(Landroid/content/Context;Landroid/os/Looper;Lcom/google/android/gms/common/internal/c$a;Lcom/google/android/gms/common/internal/c$b;)V
    //   74: aload_0
    //   75: aload 7
    //   77: putfield 21	com/google/android/gms/internal/ads/cd:a	Lcom/google/android/gms/internal/ads/Tc;
    //   80: aload_0
    //   81: getfield 21	com/google/android/gms/internal/ads/cd:a	Lcom/google/android/gms/internal/ads/Tc;
    //   84: invokevirtual 84	com/google/android/gms/common/internal/c:m	()V
    //   87: new 86	com/google/android/gms/internal/ads/dd
    //   90: astore 7
    //   92: aload 7
    //   94: aload_0
    //   95: aload_1
    //   96: invokespecial 89	com/google/android/gms/internal/ads/dd:<init>	(Lcom/google/android/gms/internal/ads/cd;Lcom/google/android/gms/internal/ads/Uc;)V
    //   99: aload 4
    //   101: aload 7
    //   103: getstatic 94	com/google/android/gms/internal/ads/tk:a	Lcom/google/android/gms/internal/ads/Bm;
    //   106: invokestatic 99	com/google/android/gms/internal/ads/gm:a	(Lcom/google/android/gms/internal/ads/xm;Lcom/google/android/gms/internal/ads/am;Ljava/util/concurrent/Executor;)Lcom/google/android/gms/internal/ads/xm;
    //   109: astore_1
    //   110: getstatic 105	com/google/android/gms/internal/ads/ra:Bd	Lcom/google/android/gms/internal/ads/ga;
    //   113: astore 4
    //   115: aload_1
    //   116: invokestatic 111	com/google/android/gms/internal/ads/Kea:e	()Lcom/google/android/gms/internal/ads/oa;
    //   119: aload 4
    //   121: invokevirtual 116	com/google/android/gms/internal/ads/oa:a	(Lcom/google/android/gms/internal/ads/ga;)Ljava/lang/Object;
    //   124: checkcast 118	java/lang/Integer
    //   127: invokevirtual 122	java/lang/Integer:intValue	()I
    //   130: i2l
    //   131: getstatic 128	java/util/concurrent/TimeUnit:MILLISECONDS	Ljava/util/concurrent/TimeUnit;
    //   134: getstatic 132	com/google/android/gms/internal/ads/tk:c	Ljava/util/concurrent/ScheduledExecutorService;
    //   137: invokestatic 135	com/google/android/gms/internal/ads/gm:a	(Lcom/google/android/gms/internal/ads/xm;JLjava/util/concurrent/TimeUnit;Ljava/util/concurrent/ScheduledExecutorService;)Lcom/google/android/gms/internal/ads/xm;
    //   140: astore 4
    //   142: new 137	com/google/android/gms/internal/ads/fd
    //   145: astore_1
    //   146: aload_1
    //   147: aload_0
    //   148: invokespecial 139	com/google/android/gms/internal/ads/fd:<init>	(Lcom/google/android/gms/internal/ads/cd;)V
    //   151: aload 4
    //   153: aload_1
    //   154: getstatic 94	com/google/android/gms/internal/ads/tk:a	Lcom/google/android/gms/internal/ads/Bm;
    //   157: invokeinterface 144 3 0
    //   162: aload 4
    //   164: invokeinterface 150 1 0
    //   169: checkcast 152	android/os/ParcelFileDescriptor
    //   172: astore_1
    //   173: invokestatic 51	com/google/android/gms/ads/internal/k:j	()Lcom/google/android/gms/common/util/e;
    //   176: invokeinterface 56 1 0
    //   181: lstore 8
    //   183: new 154	java/lang/StringBuilder
    //   186: dup
    //   187: bipush 52
    //   189: invokespecial 157	java/lang/StringBuilder:<init>	(I)V
    //   192: astore 4
    //   194: aload 4
    //   196: ldc -97
    //   198: invokevirtual 163	java/lang/StringBuilder:append	(Ljava/lang/String;)Ljava/lang/StringBuilder;
    //   201: pop
    //   202: aload 4
    //   204: lload 8
    //   206: lload_2
    //   207: lsub
    //   208: invokevirtual 166	java/lang/StringBuilder:append	(J)Ljava/lang/StringBuilder;
    //   211: pop
    //   212: aload 4
    //   214: ldc -88
    //   216: invokevirtual 163	java/lang/StringBuilder:append	(Ljava/lang/String;)Ljava/lang/StringBuilder;
    //   219: pop
    //   220: aload 4
    //   222: invokevirtual 172	java/lang/StringBuilder:toString	()Ljava/lang/String;
    //   225: invokestatic 178	com/google/android/gms/internal/ads/mk:f	(Ljava/lang/String;)V
    //   228: new 180	com/google/android/gms/internal/ads/Ph
    //   231: dup
    //   232: aload_1
    //   233: invokespecial 183	com/google/android/gms/internal/ads/Ph:<init>	(Landroid/os/ParcelFileDescriptor;)V
    //   236: getstatic 189	com/google/android/gms/internal/ads/Xc:CREATOR	Landroid/os/Parcelable$Creator;
    //   239: invokevirtual 192	com/google/android/gms/internal/ads/Ph:a	(Landroid/os/Parcelable$Creator;)Liq;
    //   242: checkcast 185	com/google/android/gms/internal/ads/Xc
    //   245: astore 4
    //   247: aload 4
    //   249: ifnonnull +5 -> 254
    //   252: aconst_null
    //   253: areturn
    //   254: aload 4
    //   256: getfield 195	com/google/android/gms/internal/ads/Xc:a	Z
    //   259: ifne +99 -> 358
    //   262: aload 4
    //   264: getfield 198	com/google/android/gms/internal/ads/Xc:e	[Ljava/lang/String;
    //   267: arraylength
    //   268: aload 4
    //   270: getfield 200	com/google/android/gms/internal/ads/Xc:f	[Ljava/lang/String;
    //   273: arraylength
    //   274: if_icmpeq +5 -> 279
    //   277: aconst_null
    //   278: areturn
    //   279: new 202	java/util/HashMap
    //   282: dup
    //   283: invokespecial 203	java/util/HashMap:<init>	()V
    //   286: astore_1
    //   287: iconst_0
    //   288: istore 10
    //   290: aload 4
    //   292: getfield 198	com/google/android/gms/internal/ads/Xc:e	[Ljava/lang/String;
    //   295: astore 7
    //   297: iload 10
    //   299: aload 7
    //   301: arraylength
    //   302: if_icmpge +27 -> 329
    //   305: aload_1
    //   306: aload 7
    //   308: iload 10
    //   310: aaload
    //   311: aload 4
    //   313: getfield 200	com/google/android/gms/internal/ads/Xc:f	[Ljava/lang/String;
    //   316: iload 10
    //   318: aaload
    //   319: invokevirtual 207	java/util/HashMap:put	(Ljava/lang/Object;Ljava/lang/Object;)Ljava/lang/Object;
    //   322: pop
    //   323: iinc 10 1
    //   326: goto -36 -> 290
    //   329: new 209	com/google/android/gms/internal/ads/HZ
    //   332: dup
    //   333: aload 4
    //   335: getfield 212	com/google/android/gms/internal/ads/Xc:c	I
    //   338: aload 4
    //   340: getfield 216	com/google/android/gms/internal/ads/Xc:d	[B
    //   343: aload_1
    //   344: aload 4
    //   346: getfield 219	com/google/android/gms/internal/ads/Xc:g	Z
    //   349: aload 4
    //   351: getfield 223	com/google/android/gms/internal/ads/Xc:h	J
    //   354: invokespecial 226	com/google/android/gms/internal/ads/HZ:<init>	(I[BLjava/util/Map;ZJ)V
    //   357: areturn
    //   358: new 36	com/google/android/gms/internal/ads/xb
    //   361: dup
    //   362: aload 4
    //   364: getfield 229	com/google/android/gms/internal/ads/Xc:b	Ljava/lang/String;
    //   367: invokespecial 231	com/google/android/gms/internal/ads/xb:<init>	(Ljava/lang/String;)V
    //   370: athrow
    //   371: astore 4
    //   373: invokestatic 51	com/google/android/gms/ads/internal/k:j	()Lcom/google/android/gms/common/util/e;
    //   376: invokeinterface 56 1 0
    //   381: lstore 8
    //   383: new 154	java/lang/StringBuilder
    //   386: dup
    //   387: bipush 52
    //   389: invokespecial 157	java/lang/StringBuilder:<init>	(I)V
    //   392: astore_1
    //   393: aload_1
    //   394: ldc -97
    //   396: invokevirtual 163	java/lang/StringBuilder:append	(Ljava/lang/String;)Ljava/lang/StringBuilder;
    //   399: pop
    //   400: aload_1
    //   401: lload 8
    //   403: lload_2
    //   404: lsub
    //   405: invokevirtual 166	java/lang/StringBuilder:append	(J)Ljava/lang/StringBuilder;
    //   408: pop
    //   409: aload_1
    //   410: ldc -88
    //   412: invokevirtual 163	java/lang/StringBuilder:append	(Ljava/lang/String;)Ljava/lang/StringBuilder;
    //   415: pop
    //   416: aload_1
    //   417: invokevirtual 172	java/lang/StringBuilder:toString	()Ljava/lang/String;
    //   420: invokestatic 178	com/google/android/gms/internal/ads/mk:f	(Ljava/lang/String;)V
    //   423: aload 4
    //   425: athrow
    //   426: astore_1
    //   427: invokestatic 51	com/google/android/gms/ads/internal/k:j	()Lcom/google/android/gms/common/util/e;
    //   430: invokeinterface 56 1 0
    //   435: lstore 8
    //   437: new 154	java/lang/StringBuilder
    //   440: dup
    //   441: bipush 52
    //   443: invokespecial 157	java/lang/StringBuilder:<init>	(I)V
    //   446: astore_1
    //   447: aload_1
    //   448: ldc -97
    //   450: invokevirtual 163	java/lang/StringBuilder:append	(Ljava/lang/String;)Ljava/lang/StringBuilder;
    //   453: pop
    //   454: aload_1
    //   455: lload 8
    //   457: lload_2
    //   458: lsub
    //   459: invokevirtual 166	java/lang/StringBuilder:append	(J)Ljava/lang/StringBuilder;
    //   462: pop
    //   463: aload_1
    //   464: ldc -88
    //   466: invokevirtual 163	java/lang/StringBuilder:append	(Ljava/lang/String;)Ljava/lang/StringBuilder;
    //   469: pop
    //   470: aload_1
    //   471: invokevirtual 172	java/lang/StringBuilder:toString	()Ljava/lang/String;
    //   474: invokestatic 178	com/google/android/gms/internal/ads/mk:f	(Ljava/lang/String;)V
    //   477: aconst_null
    //   478: areturn
    // Local variable table:
    //   start	length	slot	name	signature
    //   0	479	0	this	cd
    //   0	479	1	paramIaa	Iaa<?>
    //   13	445	2	l1	long
    //   17	346	4	localObject1	Object
    //   371	53	4	localObject2	Object
    //   27	41	5	localgd	gd
    //   40	30	6	localhd	hd
    //   53	254	7	localObject3	Object
    //   181	275	8	l2	long
    //   288	36	10	i	int
    // Exception table:
    //   from	to	target	type
    //   14	173	371	finally
    //   14	173	426	java/lang/InterruptedException
    //   14	173	426	java/util/concurrent/ExecutionException
  }
}


/* Location:              /Applications/dex2jar/classes-dex2jar.jar!/com/google/android/gms/internal/ads/cd.class
 * Java compiler version: 6 (50.0)
 * JD-Core Version:       0.7.1
 */