package com.google.android.gms.internal.ads;

import android.annotation.TargetApi;
import android.content.Context;
import android.graphics.SurfaceTexture;
import android.graphics.SurfaceTexture.OnFrameAvailableListener;
import android.opengl.GLES20;
import android.util.Log;
import java.nio.ByteBuffer;
import java.nio.ByteOrder;
import java.nio.FloatBuffer;
import java.util.concurrent.CountDownLatch;
import javax.microedition.khronos.egl.EGL10;
import javax.microedition.khronos.egl.EGLContext;
import javax.microedition.khronos.egl.EGLDisplay;
import javax.microedition.khronos.egl.EGLSurface;

@yh
@TargetApi(14)
public final class un
  extends Thread
  implements SurfaceTexture.OnFrameAvailableListener, tn
{
  private static final float[] a = { -1.0F, -1.0F, -1.0F, 1.0F, -1.0F, -1.0F, -1.0F, 1.0F, -1.0F, 1.0F, 1.0F, -1.0F };
  private volatile boolean A;
  private volatile boolean B;
  private final rn b;
  private final float[] c;
  private final float[] d;
  private final float[] e;
  private final float[] f;
  private final float[] g;
  private final float[] h;
  private final float[] i;
  private float j;
  private float k;
  private float l;
  private int m;
  private int n;
  private SurfaceTexture o;
  private SurfaceTexture p;
  private int q;
  private int r;
  private int s;
  private FloatBuffer t = ByteBuffer.allocateDirect(a.length << 2).order(ByteOrder.nativeOrder()).asFloatBuffer();
  private final CountDownLatch u;
  private final Object v;
  private EGL10 w;
  private EGLDisplay x;
  private EGLContext y;
  private EGLSurface z;
  
  public un(Context paramContext)
  {
    super("SphericalVideoProcessor");
    this.t.put(a).position(0);
    this.c = new float[9];
    this.d = new float[9];
    this.e = new float[9];
    this.f = new float[9];
    this.g = new float[9];
    this.h = new float[9];
    this.i = new float[9];
    this.j = NaN.0F;
    this.b = new rn(paramContext);
    this.b.a(this);
    this.u = new CountDownLatch(1);
    this.v = new Object();
  }
  
  private static int a(int paramInt, String paramString)
  {
    int i1 = GLES20.glCreateShader(paramInt);
    a("createShader");
    int i2 = i1;
    if (i1 != 0)
    {
      GLES20.glShaderSource(i1, paramString);
      a("shaderSource");
      GLES20.glCompileShader(i1);
      a("compileShader");
      paramString = new int[1];
      GLES20.glGetShaderiv(i1, 35713, paramString, 0);
      a("getShaderiv");
      i2 = i1;
      if (paramString[0] == 0)
      {
        paramString = new StringBuilder(37);
        paramString.append("Could not compile shader ");
        paramString.append(paramInt);
        paramString.append(":");
        Log.e("SphericalVideoRenderer", paramString.toString());
        Log.e("SphericalVideoRenderer", GLES20.glGetShaderInfoLog(i1));
        GLES20.glDeleteShader(i1);
        a("deleteShader");
        i2 = 0;
      }
    }
    return i2;
  }
  
  private static void a(String paramString)
  {
    int i1 = GLES20.glGetError();
    if (i1 != 0)
    {
      StringBuilder localStringBuilder = new StringBuilder(String.valueOf(paramString).length() + 21);
      localStringBuilder.append(paramString);
      localStringBuilder.append(": glError ");
      localStringBuilder.append(i1);
      Log.e("SphericalVideoRenderer", localStringBuilder.toString());
    }
  }
  
  private static void a(float[] paramArrayOfFloat, float paramFloat)
  {
    paramArrayOfFloat[0] = 1.0F;
    paramArrayOfFloat[1] = 0.0F;
    paramArrayOfFloat[2] = 0.0F;
    paramArrayOfFloat[3] = 0.0F;
    double d1 = paramFloat;
    paramArrayOfFloat[4] = ((float)Math.cos(d1));
    paramArrayOfFloat[5] = ((float)-Math.sin(d1));
    paramArrayOfFloat[6] = 0.0F;
    paramArrayOfFloat[7] = ((float)Math.sin(d1));
    paramArrayOfFloat[8] = ((float)Math.cos(d1));
  }
  
  private static void a(float[] paramArrayOfFloat1, float[] paramArrayOfFloat2, float[] paramArrayOfFloat3)
  {
    paramArrayOfFloat1[0] = (paramArrayOfFloat2[0] * paramArrayOfFloat3[0] + paramArrayOfFloat2[1] * paramArrayOfFloat3[3] + paramArrayOfFloat2[2] * paramArrayOfFloat3[6]);
    paramArrayOfFloat1[1] = (paramArrayOfFloat2[0] * paramArrayOfFloat3[1] + paramArrayOfFloat2[1] * paramArrayOfFloat3[4] + paramArrayOfFloat2[2] * paramArrayOfFloat3[7]);
    paramArrayOfFloat1[2] = (paramArrayOfFloat2[0] * paramArrayOfFloat3[2] + paramArrayOfFloat2[1] * paramArrayOfFloat3[5] + paramArrayOfFloat2[2] * paramArrayOfFloat3[8]);
    paramArrayOfFloat1[3] = (paramArrayOfFloat2[3] * paramArrayOfFloat3[0] + paramArrayOfFloat2[4] * paramArrayOfFloat3[3] + paramArrayOfFloat2[5] * paramArrayOfFloat3[6]);
    paramArrayOfFloat1[4] = (paramArrayOfFloat2[3] * paramArrayOfFloat3[1] + paramArrayOfFloat2[4] * paramArrayOfFloat3[4] + paramArrayOfFloat2[5] * paramArrayOfFloat3[7]);
    paramArrayOfFloat1[5] = (paramArrayOfFloat2[3] * paramArrayOfFloat3[2] + paramArrayOfFloat2[4] * paramArrayOfFloat3[5] + paramArrayOfFloat2[5] * paramArrayOfFloat3[8]);
    paramArrayOfFloat1[6] = (paramArrayOfFloat2[6] * paramArrayOfFloat3[0] + paramArrayOfFloat2[7] * paramArrayOfFloat3[3] + paramArrayOfFloat2[8] * paramArrayOfFloat3[6]);
    paramArrayOfFloat1[7] = (paramArrayOfFloat2[6] * paramArrayOfFloat3[1] + paramArrayOfFloat2[7] * paramArrayOfFloat3[4] + paramArrayOfFloat2[8] * paramArrayOfFloat3[7]);
    paramArrayOfFloat1[8] = (paramArrayOfFloat2[6] * paramArrayOfFloat3[2] + paramArrayOfFloat2[7] * paramArrayOfFloat3[5] + paramArrayOfFloat2[8] * paramArrayOfFloat3[8]);
  }
  
  private static void b(float[] paramArrayOfFloat, float paramFloat)
  {
    double d1 = paramFloat;
    paramArrayOfFloat[0] = ((float)Math.cos(d1));
    paramArrayOfFloat[1] = ((float)-Math.sin(d1));
    paramArrayOfFloat[2] = 0.0F;
    paramArrayOfFloat[3] = ((float)Math.sin(d1));
    paramArrayOfFloat[4] = ((float)Math.cos(d1));
    paramArrayOfFloat[5] = 0.0F;
    paramArrayOfFloat[6] = 0.0F;
    paramArrayOfFloat[7] = 0.0F;
    paramArrayOfFloat[8] = 1.0F;
  }
  
  private final boolean d()
  {
    Object localObject = this.z;
    boolean bool1 = false;
    boolean bool2 = bool1;
    if (localObject != null)
    {
      EGLSurface localEGLSurface = EGL10.EGL_NO_SURFACE;
      bool2 = bool1;
      if (localObject != localEGLSurface)
      {
        bool1 = this.w.eglMakeCurrent(this.x, localEGLSurface, localEGLSurface, EGL10.EGL_NO_CONTEXT);
        bool2 = this.w.eglDestroySurface(this.x, this.z) | bool1 | false;
        this.z = null;
      }
    }
    localObject = this.y;
    bool1 = bool2;
    if (localObject != null)
    {
      bool1 = bool2 | this.w.eglDestroyContext(this.x, (EGLContext)localObject);
      this.y = null;
    }
    localObject = this.x;
    bool2 = bool1;
    if (localObject != null)
    {
      bool2 = bool1 | this.w.eglTerminate((EGLDisplay)localObject);
      this.x = null;
    }
    return bool2;
  }
  
  public final void a()
  {
    synchronized (this.v)
    {
      this.v.notifyAll();
      return;
    }
  }
  
  public final void a(float paramFloat1, float paramFloat2)
  {
    int i1 = this.n;
    int i2 = this.m;
    float f1;
    if (i1 > i2)
    {
      paramFloat1 = paramFloat1 * 1.7453293F / i1;
      paramFloat2 *= 1.7453293F;
      f1 = i1;
    }
    else
    {
      paramFloat1 = paramFloat1 * 1.7453293F / i2;
      paramFloat2 *= 1.7453293F;
      f1 = i2;
    }
    paramFloat2 /= f1;
    this.k -= paramFloat1;
    this.l -= paramFloat2;
    if (this.l < -1.5707964F) {
      this.l = -1.5707964F;
    }
    if (this.l > 1.5707964F) {
      this.l = 1.5707964F;
    }
  }
  
  public final void a(int paramInt1, int paramInt2)
  {
    synchronized (this.v)
    {
      this.n = paramInt1;
      this.m = paramInt2;
      this.A = true;
      this.v.notifyAll();
      return;
    }
  }
  
  public final void a(SurfaceTexture paramSurfaceTexture, int paramInt1, int paramInt2)
  {
    this.n = paramInt1;
    this.m = paramInt2;
    this.p = paramSurfaceTexture;
  }
  
  public final void b()
  {
    synchronized (this.v)
    {
      this.B = true;
      this.p = null;
      this.v.notifyAll();
      return;
    }
  }
  
  public final SurfaceTexture c()
  {
    if (this.p == null) {
      return null;
    }
    try
    {
      this.u.await();
      return this.o;
    }
    catch (InterruptedException localInterruptedException)
    {
      for (;;) {}
    }
  }
  
  public final void onFrameAvailable(SurfaceTexture arg1)
  {
    this.s += 1;
    synchronized (this.v)
    {
      this.v.notifyAll();
      return;
    }
  }
  
  /* Error */
  public final void run()
  {
    // Byte code:
    //   0: aload_0
    //   1: getfield 280	com/google/android/gms/internal/ads/un:p	Landroid/graphics/SurfaceTexture;
    //   4: ifnonnull +17 -> 21
    //   7: ldc_w 301
    //   10: invokestatic 305	com/google/android/gms/internal/ads/Tl:b	(Ljava/lang/String;)V
    //   13: aload_0
    //   14: getfield 131	com/google/android/gms/internal/ads/un:u	Ljava/util/concurrent/CountDownLatch;
    //   17: invokevirtual 308	java/util/concurrent/CountDownLatch:countDown	()V
    //   20: return
    //   21: aload_0
    //   22: invokestatic 314	javax/microedition/khronos/egl/EGLContext:getEGL	()Ljavax/microedition/khronos/egl/EGL;
    //   25: checkcast 231	javax/microedition/khronos/egl/EGL10
    //   28: putfield 236	com/google/android/gms/internal/ads/un:w	Ljavax/microedition/khronos/egl/EGL10;
    //   31: aload_0
    //   32: aload_0
    //   33: getfield 236	com/google/android/gms/internal/ads/un:w	Ljavax/microedition/khronos/egl/EGL10;
    //   36: getstatic 317	javax/microedition/khronos/egl/EGL10:EGL_DEFAULT_DISPLAY	Ljava/lang/Object;
    //   39: invokeinterface 321 2 0
    //   44: putfield 238	com/google/android/gms/internal/ads/un:x	Ljavax/microedition/khronos/egl/EGLDisplay;
    //   47: aload_0
    //   48: getfield 238	com/google/android/gms/internal/ads/un:x	Ljavax/microedition/khronos/egl/EGLDisplay;
    //   51: astore_1
    //   52: aload_1
    //   53: getstatic 324	javax/microedition/khronos/egl/EGL10:EGL_NO_DISPLAY	Ljavax/microedition/khronos/egl/EGLDisplay;
    //   56: if_acmpne +8 -> 64
    //   59: iconst_0
    //   60: istore_2
    //   61: goto +271 -> 332
    //   64: iconst_2
    //   65: newarray <illegal type>
    //   67: astore_3
    //   68: aload_0
    //   69: getfield 236	com/google/android/gms/internal/ads/un:w	Ljavax/microedition/khronos/egl/EGL10;
    //   72: aload_1
    //   73: aload_3
    //   74: invokeinterface 328 3 0
    //   79: ifne +6 -> 85
    //   82: goto -23 -> 59
    //   85: iconst_1
    //   86: newarray <illegal type>
    //   88: astore_1
    //   89: iconst_1
    //   90: anewarray 330	javax/microedition/khronos/egl/EGLConfig
    //   93: astore_3
    //   94: aload_0
    //   95: getfield 236	com/google/android/gms/internal/ads/un:w	Ljavax/microedition/khronos/egl/EGL10;
    //   98: aload_0
    //   99: getfield 238	com/google/android/gms/internal/ads/un:x	Ljavax/microedition/khronos/egl/EGLDisplay;
    //   102: bipush 11
    //   104: newarray <illegal type>
    //   106: dup
    //   107: iconst_0
    //   108: sipush 12352
    //   111: iastore
    //   112: dup
    //   113: iconst_1
    //   114: iconst_4
    //   115: iastore
    //   116: dup
    //   117: iconst_2
    //   118: sipush 12324
    //   121: iastore
    //   122: dup
    //   123: iconst_3
    //   124: bipush 8
    //   126: iastore
    //   127: dup
    //   128: iconst_4
    //   129: sipush 12323
    //   132: iastore
    //   133: dup
    //   134: iconst_5
    //   135: bipush 8
    //   137: iastore
    //   138: dup
    //   139: bipush 6
    //   141: sipush 12322
    //   144: iastore
    //   145: dup
    //   146: bipush 7
    //   148: bipush 8
    //   150: iastore
    //   151: dup
    //   152: bipush 8
    //   154: sipush 12325
    //   157: iastore
    //   158: dup
    //   159: bipush 9
    //   161: bipush 16
    //   163: iastore
    //   164: dup
    //   165: bipush 10
    //   167: sipush 12344
    //   170: iastore
    //   171: aload_3
    //   172: iconst_1
    //   173: aload_1
    //   174: invokeinterface 334 6 0
    //   179: ifeq +16 -> 195
    //   182: aload_1
    //   183: iconst_0
    //   184: iaload
    //   185: ifle +10 -> 195
    //   188: aload_3
    //   189: iconst_0
    //   190: aaload
    //   191: astore_3
    //   192: goto +5 -> 197
    //   195: aconst_null
    //   196: astore_3
    //   197: aload_3
    //   198: ifnonnull +6 -> 204
    //   201: goto -142 -> 59
    //   204: aload_0
    //   205: aload_0
    //   206: getfield 236	com/google/android/gms/internal/ads/un:w	Ljavax/microedition/khronos/egl/EGL10;
    //   209: aload_0
    //   210: getfield 238	com/google/android/gms/internal/ads/un:x	Ljavax/microedition/khronos/egl/EGLDisplay;
    //   213: aload_3
    //   214: getstatic 241	javax/microedition/khronos/egl/EGL10:EGL_NO_CONTEXT	Ljavax/microedition/khronos/egl/EGLContext;
    //   217: iconst_3
    //   218: newarray <illegal type>
    //   220: dup
    //   221: iconst_0
    //   222: sipush 12440
    //   225: iastore
    //   226: dup
    //   227: iconst_1
    //   228: iconst_2
    //   229: iastore
    //   230: dup
    //   231: iconst_2
    //   232: sipush 12344
    //   235: iastore
    //   236: invokeinterface 338 5 0
    //   241: putfield 251	com/google/android/gms/internal/ads/un:y	Ljavax/microedition/khronos/egl/EGLContext;
    //   244: aload_0
    //   245: getfield 251	com/google/android/gms/internal/ads/un:y	Ljavax/microedition/khronos/egl/EGLContext;
    //   248: astore_1
    //   249: aload_1
    //   250: ifnull -191 -> 59
    //   253: aload_1
    //   254: getstatic 241	javax/microedition/khronos/egl/EGL10:EGL_NO_CONTEXT	Ljavax/microedition/khronos/egl/EGLContext;
    //   257: if_acmpne +6 -> 263
    //   260: goto -201 -> 59
    //   263: aload_0
    //   264: aload_0
    //   265: getfield 236	com/google/android/gms/internal/ads/un:w	Ljavax/microedition/khronos/egl/EGL10;
    //   268: aload_0
    //   269: getfield 238	com/google/android/gms/internal/ads/un:x	Ljavax/microedition/khronos/egl/EGLDisplay;
    //   272: aload_3
    //   273: aload_0
    //   274: getfield 280	com/google/android/gms/internal/ads/un:p	Landroid/graphics/SurfaceTexture;
    //   277: aconst_null
    //   278: invokeinterface 342 5 0
    //   283: putfield 229	com/google/android/gms/internal/ads/un:z	Ljavax/microedition/khronos/egl/EGLSurface;
    //   286: aload_0
    //   287: getfield 229	com/google/android/gms/internal/ads/un:z	Ljavax/microedition/khronos/egl/EGLSurface;
    //   290: astore_3
    //   291: aload_3
    //   292: ifnull -233 -> 59
    //   295: aload_3
    //   296: getstatic 234	javax/microedition/khronos/egl/EGL10:EGL_NO_SURFACE	Ljavax/microedition/khronos/egl/EGLSurface;
    //   299: if_acmpne +6 -> 305
    //   302: goto -243 -> 59
    //   305: aload_0
    //   306: getfield 236	com/google/android/gms/internal/ads/un:w	Ljavax/microedition/khronos/egl/EGL10;
    //   309: aload_0
    //   310: getfield 238	com/google/android/gms/internal/ads/un:x	Ljavax/microedition/khronos/egl/EGLDisplay;
    //   313: aload_3
    //   314: aload_3
    //   315: aload_0
    //   316: getfield 251	com/google/android/gms/internal/ads/un:y	Ljavax/microedition/khronos/egl/EGLContext;
    //   319: invokeinterface 245 5 0
    //   324: ifne +6 -> 330
    //   327: goto -268 -> 59
    //   330: iconst_1
    //   331: istore_2
    //   332: getstatic 348	com/google/android/gms/internal/ads/ra:Kb	Lcom/google/android/gms/internal/ads/ga;
    //   335: astore_3
    //   336: invokestatic 353	com/google/android/gms/internal/ads/Kea:e	()Lcom/google/android/gms/internal/ads/oa;
    //   339: aload_3
    //   340: invokevirtual 358	com/google/android/gms/internal/ads/oa:a	(Lcom/google/android/gms/internal/ads/ga;)Ljava/lang/Object;
    //   343: checkcast 206	java/lang/String
    //   346: aload_3
    //   347: invokevirtual 363	com/google/android/gms/internal/ads/ga:c	()Ljava/lang/Object;
    //   350: invokevirtual 367	java/lang/String:equals	(Ljava/lang/Object;)Z
    //   353: ifne +17 -> 370
    //   356: invokestatic 353	com/google/android/gms/internal/ads/Kea:e	()Lcom/google/android/gms/internal/ads/oa;
    //   359: aload_3
    //   360: invokevirtual 358	com/google/android/gms/internal/ads/oa:a	(Lcom/google/android/gms/internal/ads/ga;)Ljava/lang/Object;
    //   363: checkcast 206	java/lang/String
    //   366: astore_3
    //   367: goto +7 -> 374
    //   370: ldc_w 369
    //   373: astore_3
    //   374: ldc_w 370
    //   377: aload_3
    //   378: invokestatic 372	com/google/android/gms/internal/ads/un:a	(ILjava/lang/String;)I
    //   381: istore 4
    //   383: iload 4
    //   385: ifne +9 -> 394
    //   388: iconst_0
    //   389: istore 5
    //   391: goto +195 -> 586
    //   394: getstatic 375	com/google/android/gms/internal/ads/ra:Lb	Lcom/google/android/gms/internal/ads/ga;
    //   397: astore_3
    //   398: invokestatic 353	com/google/android/gms/internal/ads/Kea:e	()Lcom/google/android/gms/internal/ads/oa;
    //   401: aload_3
    //   402: invokevirtual 358	com/google/android/gms/internal/ads/oa:a	(Lcom/google/android/gms/internal/ads/ga;)Ljava/lang/Object;
    //   405: checkcast 206	java/lang/String
    //   408: aload_3
    //   409: invokevirtual 363	com/google/android/gms/internal/ads/ga:c	()Ljava/lang/Object;
    //   412: invokevirtual 367	java/lang/String:equals	(Ljava/lang/Object;)Z
    //   415: ifne +17 -> 432
    //   418: invokestatic 353	com/google/android/gms/internal/ads/Kea:e	()Lcom/google/android/gms/internal/ads/oa;
    //   421: aload_3
    //   422: invokevirtual 358	com/google/android/gms/internal/ads/oa:a	(Lcom/google/android/gms/internal/ads/ga;)Ljava/lang/Object;
    //   425: checkcast 206	java/lang/String
    //   428: astore_3
    //   429: goto +7 -> 436
    //   432: ldc_w 377
    //   435: astore_3
    //   436: ldc_w 378
    //   439: aload_3
    //   440: invokestatic 372	com/google/android/gms/internal/ads/un:a	(ILjava/lang/String;)I
    //   443: istore 6
    //   445: iload 6
    //   447: ifne +6 -> 453
    //   450: goto -62 -> 388
    //   453: invokestatic 381	android/opengl/GLES20:glCreateProgram	()I
    //   456: istore 7
    //   458: ldc_w 383
    //   461: invokestatic 148	com/google/android/gms/internal/ads/un:a	(Ljava/lang/String;)V
    //   464: iload 7
    //   466: istore 5
    //   468: iload 7
    //   470: ifeq +116 -> 586
    //   473: iload 7
    //   475: iload 4
    //   477: invokestatic 386	android/opengl/GLES20:glAttachShader	(II)V
    //   480: ldc_w 388
    //   483: invokestatic 148	com/google/android/gms/internal/ads/un:a	(Ljava/lang/String;)V
    //   486: iload 7
    //   488: iload 6
    //   490: invokestatic 386	android/opengl/GLES20:glAttachShader	(II)V
    //   493: ldc_w 388
    //   496: invokestatic 148	com/google/android/gms/internal/ads/un:a	(Ljava/lang/String;)V
    //   499: iload 7
    //   501: invokestatic 391	android/opengl/GLES20:glLinkProgram	(I)V
    //   504: ldc_w 393
    //   507: invokestatic 148	com/google/android/gms/internal/ads/un:a	(Ljava/lang/String;)V
    //   510: iconst_1
    //   511: newarray <illegal type>
    //   513: astore_3
    //   514: iload 7
    //   516: ldc_w 394
    //   519: aload_3
    //   520: iconst_0
    //   521: invokestatic 397	android/opengl/GLES20:glGetProgramiv	(II[II)V
    //   524: ldc_w 399
    //   527: invokestatic 148	com/google/android/gms/internal/ads/un:a	(Ljava/lang/String;)V
    //   530: aload_3
    //   531: iconst_0
    //   532: iaload
    //   533: iconst_1
    //   534: if_icmpeq +37 -> 571
    //   537: ldc -74
    //   539: ldc_w 401
    //   542: invokestatic 191	android/util/Log:e	(Ljava/lang/String;Ljava/lang/String;)I
    //   545: pop
    //   546: ldc -74
    //   548: iload 7
    //   550: invokestatic 404	android/opengl/GLES20:glGetProgramInfoLog	(I)Ljava/lang/String;
    //   553: invokestatic 191	android/util/Log:e	(Ljava/lang/String;Ljava/lang/String;)I
    //   556: pop
    //   557: iload 7
    //   559: invokestatic 407	android/opengl/GLES20:glDeleteProgram	(I)V
    //   562: ldc_w 409
    //   565: invokestatic 148	com/google/android/gms/internal/ads/un:a	(Ljava/lang/String;)V
    //   568: goto -180 -> 388
    //   571: iload 7
    //   573: invokestatic 412	android/opengl/GLES20:glValidateProgram	(I)V
    //   576: ldc_w 414
    //   579: invokestatic 148	com/google/android/gms/internal/ads/un:a	(Ljava/lang/String;)V
    //   582: iload 7
    //   584: istore 5
    //   586: aload_0
    //   587: iload 5
    //   589: putfield 416	com/google/android/gms/internal/ads/un:q	I
    //   592: aload_0
    //   593: getfield 416	com/google/android/gms/internal/ads/un:q	I
    //   596: invokestatic 419	android/opengl/GLES20:glUseProgram	(I)V
    //   599: ldc_w 421
    //   602: invokestatic 148	com/google/android/gms/internal/ads/un:a	(Ljava/lang/String;)V
    //   605: aload_0
    //   606: getfield 416	com/google/android/gms/internal/ads/un:q	I
    //   609: ldc_w 423
    //   612: invokestatic 426	android/opengl/GLES20:glGetAttribLocation	(ILjava/lang/String;)I
    //   615: istore 5
    //   617: iload 5
    //   619: iconst_3
    //   620: sipush 5126
    //   623: iconst_0
    //   624: bipush 12
    //   626: aload_0
    //   627: getfield 88	com/google/android/gms/internal/ads/un:t	Ljava/nio/FloatBuffer;
    //   630: invokestatic 430	android/opengl/GLES20:glVertexAttribPointer	(IIIZILjava/nio/Buffer;)V
    //   633: ldc_w 432
    //   636: invokestatic 148	com/google/android/gms/internal/ads/un:a	(Ljava/lang/String;)V
    //   639: iload 5
    //   641: invokestatic 435	android/opengl/GLES20:glEnableVertexAttribArray	(I)V
    //   644: ldc_w 437
    //   647: invokestatic 148	com/google/android/gms/internal/ads/un:a	(Ljava/lang/String;)V
    //   650: iconst_1
    //   651: newarray <illegal type>
    //   653: astore_3
    //   654: iconst_1
    //   655: aload_3
    //   656: iconst_0
    //   657: invokestatic 441	android/opengl/GLES20:glGenTextures	(I[II)V
    //   660: ldc_w 443
    //   663: invokestatic 148	com/google/android/gms/internal/ads/un:a	(Ljava/lang/String;)V
    //   666: aload_3
    //   667: iconst_0
    //   668: iaload
    //   669: istore 7
    //   671: ldc_w 444
    //   674: iload 7
    //   676: invokestatic 447	android/opengl/GLES20:glBindTexture	(II)V
    //   679: ldc_w 449
    //   682: invokestatic 148	com/google/android/gms/internal/ads/un:a	(Ljava/lang/String;)V
    //   685: ldc_w 444
    //   688: sipush 10240
    //   691: sipush 9729
    //   694: invokestatic 453	android/opengl/GLES20:glTexParameteri	(III)V
    //   697: ldc_w 455
    //   700: invokestatic 148	com/google/android/gms/internal/ads/un:a	(Ljava/lang/String;)V
    //   703: ldc_w 444
    //   706: sipush 10241
    //   709: sipush 9729
    //   712: invokestatic 453	android/opengl/GLES20:glTexParameteri	(III)V
    //   715: ldc_w 455
    //   718: invokestatic 148	com/google/android/gms/internal/ads/un:a	(Ljava/lang/String;)V
    //   721: ldc_w 444
    //   724: sipush 10242
    //   727: ldc_w 456
    //   730: invokestatic 453	android/opengl/GLES20:glTexParameteri	(III)V
    //   733: ldc_w 455
    //   736: invokestatic 148	com/google/android/gms/internal/ads/un:a	(Ljava/lang/String;)V
    //   739: ldc_w 444
    //   742: sipush 10243
    //   745: ldc_w 456
    //   748: invokestatic 453	android/opengl/GLES20:glTexParameteri	(III)V
    //   751: ldc_w 455
    //   754: invokestatic 148	com/google/android/gms/internal/ads/un:a	(Ljava/lang/String;)V
    //   757: aload_0
    //   758: aload_0
    //   759: getfield 416	com/google/android/gms/internal/ads/un:q	I
    //   762: ldc_w 458
    //   765: invokestatic 461	android/opengl/GLES20:glGetUniformLocation	(ILjava/lang/String;)I
    //   768: putfield 463	com/google/android/gms/internal/ads/un:r	I
    //   771: aload_0
    //   772: getfield 463	com/google/android/gms/internal/ads/un:r	I
    //   775: iconst_1
    //   776: iconst_0
    //   777: bipush 9
    //   779: newarray <illegal type>
    //   781: dup
    //   782: iconst_0
    //   783: fconst_1
    //   784: fastore
    //   785: dup
    //   786: iconst_1
    //   787: fconst_0
    //   788: fastore
    //   789: dup
    //   790: iconst_2
    //   791: fconst_0
    //   792: fastore
    //   793: dup
    //   794: iconst_3
    //   795: fconst_0
    //   796: fastore
    //   797: dup
    //   798: iconst_4
    //   799: fconst_1
    //   800: fastore
    //   801: dup
    //   802: iconst_5
    //   803: fconst_0
    //   804: fastore
    //   805: dup
    //   806: bipush 6
    //   808: fconst_0
    //   809: fastore
    //   810: dup
    //   811: bipush 7
    //   813: fconst_0
    //   814: fastore
    //   815: dup
    //   816: bipush 8
    //   818: fconst_1
    //   819: fastore
    //   820: iconst_0
    //   821: invokestatic 467	android/opengl/GLES20:glUniformMatrix3fv	(IIZ[FI)V
    //   824: aload_0
    //   825: getfield 416	com/google/android/gms/internal/ads/un:q	I
    //   828: ifeq +9 -> 837
    //   831: iconst_1
    //   832: istore 5
    //   834: goto +6 -> 840
    //   837: iconst_0
    //   838: istore 5
    //   840: iload_2
    //   841: ifeq +696 -> 1537
    //   844: iload 5
    //   846: ifne +6 -> 852
    //   849: goto +688 -> 1537
    //   852: aload_0
    //   853: new 469	android/graphics/SurfaceTexture
    //   856: dup
    //   857: iload 7
    //   859: invokespecial 470	android/graphics/SurfaceTexture:<init>	(I)V
    //   862: putfield 290	com/google/android/gms/internal/ads/un:o	Landroid/graphics/SurfaceTexture;
    //   865: aload_0
    //   866: getfield 290	com/google/android/gms/internal/ads/un:o	Landroid/graphics/SurfaceTexture;
    //   869: aload_0
    //   870: invokevirtual 474	android/graphics/SurfaceTexture:setOnFrameAvailableListener	(Landroid/graphics/SurfaceTexture$OnFrameAvailableListener;)V
    //   873: aload_0
    //   874: getfield 131	com/google/android/gms/internal/ads/un:u	Ljava/util/concurrent/CountDownLatch;
    //   877: invokevirtual 308	java/util/concurrent/CountDownLatch:countDown	()V
    //   880: aload_0
    //   881: getfield 121	com/google/android/gms/internal/ads/un:b	Lcom/google/android/gms/internal/ads/rn;
    //   884: invokevirtual 476	com/google/android/gms/internal/ads/rn:a	()V
    //   887: aload_0
    //   888: iconst_1
    //   889: putfield 277	com/google/android/gms/internal/ads/un:A	Z
    //   892: aload_0
    //   893: getfield 282	com/google/android/gms/internal/ads/un:B	Z
    //   896: ifne +507 -> 1403
    //   899: aload_0
    //   900: getfield 294	com/google/android/gms/internal/ads/un:s	I
    //   903: ifle +23 -> 926
    //   906: aload_0
    //   907: getfield 290	com/google/android/gms/internal/ads/un:o	Landroid/graphics/SurfaceTexture;
    //   910: invokevirtual 479	android/graphics/SurfaceTexture:updateTexImage	()V
    //   913: aload_0
    //   914: aload_0
    //   915: getfield 294	com/google/android/gms/internal/ads/un:s	I
    //   918: iconst_1
    //   919: isub
    //   920: putfield 294	com/google/android/gms/internal/ads/un:s	I
    //   923: goto -24 -> 899
    //   926: aload_0
    //   927: getfield 121	com/google/android/gms/internal/ads/un:b	Lcom/google/android/gms/internal/ads/rn;
    //   930: aload_0
    //   931: getfield 100	com/google/android/gms/internal/ads/un:c	[F
    //   934: invokevirtual 482	com/google/android/gms/internal/ads/rn:a	([F)Z
    //   937: ifeq +165 -> 1102
    //   940: aload_0
    //   941: getfield 115	com/google/android/gms/internal/ads/un:j	F
    //   944: invokestatic 488	java/lang/Float:isNaN	(F)Z
    //   947: ifeq +136 -> 1083
    //   950: aload_0
    //   951: getfield 100	com/google/android/gms/internal/ads/un:c	[F
    //   954: astore_3
    //   955: iconst_3
    //   956: newarray <illegal type>
    //   958: astore_1
    //   959: aload_1
    //   960: iconst_0
    //   961: fconst_0
    //   962: fastore
    //   963: aload_1
    //   964: iconst_1
    //   965: fconst_1
    //   966: fastore
    //   967: aload_1
    //   968: iconst_2
    //   969: fconst_0
    //   970: fastore
    //   971: iconst_3
    //   972: newarray <illegal type>
    //   974: astore 8
    //   976: aload 8
    //   978: iconst_0
    //   979: aload_3
    //   980: iconst_0
    //   981: faload
    //   982: aload_1
    //   983: iconst_0
    //   984: faload
    //   985: fmul
    //   986: aload_3
    //   987: iconst_1
    //   988: faload
    //   989: aload_1
    //   990: iconst_1
    //   991: faload
    //   992: fmul
    //   993: fadd
    //   994: aload_3
    //   995: iconst_2
    //   996: faload
    //   997: aload_1
    //   998: iconst_2
    //   999: faload
    //   1000: fmul
    //   1001: fadd
    //   1002: fastore
    //   1003: aload 8
    //   1005: iconst_1
    //   1006: aload_3
    //   1007: iconst_3
    //   1008: faload
    //   1009: aload_1
    //   1010: iconst_0
    //   1011: faload
    //   1012: fmul
    //   1013: aload_3
    //   1014: iconst_4
    //   1015: faload
    //   1016: aload_1
    //   1017: iconst_1
    //   1018: faload
    //   1019: fmul
    //   1020: fadd
    //   1021: aload_3
    //   1022: iconst_5
    //   1023: faload
    //   1024: aload_1
    //   1025: iconst_2
    //   1026: faload
    //   1027: fmul
    //   1028: fadd
    //   1029: fastore
    //   1030: aload 8
    //   1032: iconst_2
    //   1033: aload_3
    //   1034: bipush 6
    //   1036: faload
    //   1037: aload_1
    //   1038: iconst_0
    //   1039: faload
    //   1040: fmul
    //   1041: aload_3
    //   1042: bipush 7
    //   1044: faload
    //   1045: aload_1
    //   1046: iconst_1
    //   1047: faload
    //   1048: fmul
    //   1049: fadd
    //   1050: aload_3
    //   1051: bipush 8
    //   1053: faload
    //   1054: aload_1
    //   1055: iconst_2
    //   1056: faload
    //   1057: fmul
    //   1058: fadd
    //   1059: fastore
    //   1060: aload_0
    //   1061: aload 8
    //   1063: iconst_1
    //   1064: faload
    //   1065: f2d
    //   1066: aload 8
    //   1068: iconst_0
    //   1069: faload
    //   1070: f2d
    //   1071: invokestatic 492	java/lang/Math:atan2	(DD)D
    //   1074: d2f
    //   1075: ldc_w 274
    //   1078: fsub
    //   1079: fneg
    //   1080: putfield 115	com/google/android/gms/internal/ads/un:j	F
    //   1083: aload_0
    //   1084: getfield 110	com/google/android/gms/internal/ads/un:h	[F
    //   1087: aload_0
    //   1088: getfield 115	com/google/android/gms/internal/ads/un:j	F
    //   1091: aload_0
    //   1092: getfield 270	com/google/android/gms/internal/ads/un:k	F
    //   1095: fadd
    //   1096: invokestatic 494	com/google/android/gms/internal/ads/un:b	([FF)V
    //   1099: goto +24 -> 1123
    //   1102: aload_0
    //   1103: getfield 100	com/google/android/gms/internal/ads/un:c	[F
    //   1106: ldc_w 273
    //   1109: invokestatic 496	com/google/android/gms/internal/ads/un:a	([FF)V
    //   1112: aload_0
    //   1113: getfield 110	com/google/android/gms/internal/ads/un:h	[F
    //   1116: aload_0
    //   1117: getfield 270	com/google/android/gms/internal/ads/un:k	F
    //   1120: invokestatic 494	com/google/android/gms/internal/ads/un:b	([FF)V
    //   1123: aload_0
    //   1124: getfield 102	com/google/android/gms/internal/ads/un:d	[F
    //   1127: ldc_w 274
    //   1130: invokestatic 496	com/google/android/gms/internal/ads/un:a	([FF)V
    //   1133: aload_0
    //   1134: getfield 104	com/google/android/gms/internal/ads/un:e	[F
    //   1137: aload_0
    //   1138: getfield 110	com/google/android/gms/internal/ads/un:h	[F
    //   1141: aload_0
    //   1142: getfield 102	com/google/android/gms/internal/ads/un:d	[F
    //   1145: invokestatic 498	com/google/android/gms/internal/ads/un:a	([F[F[F)V
    //   1148: aload_0
    //   1149: getfield 106	com/google/android/gms/internal/ads/un:f	[F
    //   1152: aload_0
    //   1153: getfield 100	com/google/android/gms/internal/ads/un:c	[F
    //   1156: aload_0
    //   1157: getfield 104	com/google/android/gms/internal/ads/un:e	[F
    //   1160: invokestatic 498	com/google/android/gms/internal/ads/un:a	([F[F[F)V
    //   1163: aload_0
    //   1164: getfield 108	com/google/android/gms/internal/ads/un:g	[F
    //   1167: aload_0
    //   1168: getfield 272	com/google/android/gms/internal/ads/un:l	F
    //   1171: invokestatic 496	com/google/android/gms/internal/ads/un:a	([FF)V
    //   1174: aload_0
    //   1175: getfield 112	com/google/android/gms/internal/ads/un:i	[F
    //   1178: aload_0
    //   1179: getfield 108	com/google/android/gms/internal/ads/un:g	[F
    //   1182: aload_0
    //   1183: getfield 106	com/google/android/gms/internal/ads/un:f	[F
    //   1186: invokestatic 498	com/google/android/gms/internal/ads/un:a	([F[F[F)V
    //   1189: aload_0
    //   1190: getfield 463	com/google/android/gms/internal/ads/un:r	I
    //   1193: iconst_1
    //   1194: iconst_0
    //   1195: aload_0
    //   1196: getfield 112	com/google/android/gms/internal/ads/un:i	[F
    //   1199: iconst_0
    //   1200: invokestatic 467	android/opengl/GLES20:glUniformMatrix3fv	(IIZ[FI)V
    //   1203: iconst_5
    //   1204: iconst_0
    //   1205: iconst_4
    //   1206: invokestatic 501	android/opengl/GLES20:glDrawArrays	(III)V
    //   1209: ldc_w 503
    //   1212: invokestatic 148	com/google/android/gms/internal/ads/un:a	(Ljava/lang/String;)V
    //   1215: invokestatic 506	android/opengl/GLES20:glFinish	()V
    //   1218: aload_0
    //   1219: getfield 236	com/google/android/gms/internal/ads/un:w	Ljavax/microedition/khronos/egl/EGL10;
    //   1222: aload_0
    //   1223: getfield 238	com/google/android/gms/internal/ads/un:x	Ljavax/microedition/khronos/egl/EGLDisplay;
    //   1226: aload_0
    //   1227: getfield 229	com/google/android/gms/internal/ads/un:z	Ljavax/microedition/khronos/egl/EGLSurface;
    //   1230: invokeinterface 509 3 0
    //   1235: pop
    //   1236: aload_0
    //   1237: getfield 277	com/google/android/gms/internal/ads/un:A	Z
    //   1240: ifeq +118 -> 1358
    //   1243: iconst_0
    //   1244: iconst_0
    //   1245: aload_0
    //   1246: getfield 265	com/google/android/gms/internal/ads/un:n	I
    //   1249: aload_0
    //   1250: getfield 267	com/google/android/gms/internal/ads/un:m	I
    //   1253: invokestatic 513	android/opengl/GLES20:glViewport	(IIII)V
    //   1256: ldc_w 515
    //   1259: invokestatic 148	com/google/android/gms/internal/ads/un:a	(Ljava/lang/String;)V
    //   1262: aload_0
    //   1263: getfield 416	com/google/android/gms/internal/ads/un:q	I
    //   1266: ldc_w 517
    //   1269: invokestatic 461	android/opengl/GLES20:glGetUniformLocation	(ILjava/lang/String;)I
    //   1272: istore 5
    //   1274: aload_0
    //   1275: getfield 416	com/google/android/gms/internal/ads/un:q	I
    //   1278: ldc_w 519
    //   1281: invokestatic 461	android/opengl/GLES20:glGetUniformLocation	(ILjava/lang/String;)I
    //   1284: istore_2
    //   1285: aload_0
    //   1286: getfield 265	com/google/android/gms/internal/ads/un:n	I
    //   1289: aload_0
    //   1290: getfield 267	com/google/android/gms/internal/ads/un:m	I
    //   1293: if_icmple +33 -> 1326
    //   1296: iload 5
    //   1298: ldc_w 520
    //   1301: invokestatic 524	android/opengl/GLES20:glUniform1f	(IF)V
    //   1304: iload_2
    //   1305: aload_0
    //   1306: getfield 267	com/google/android/gms/internal/ads/un:m	I
    //   1309: i2f
    //   1310: ldc_w 520
    //   1313: fmul
    //   1314: aload_0
    //   1315: getfield 265	com/google/android/gms/internal/ads/un:n	I
    //   1318: i2f
    //   1319: fdiv
    //   1320: invokestatic 524	android/opengl/GLES20:glUniform1f	(IF)V
    //   1323: goto +30 -> 1353
    //   1326: iload 5
    //   1328: aload_0
    //   1329: getfield 265	com/google/android/gms/internal/ads/un:n	I
    //   1332: i2f
    //   1333: ldc_w 520
    //   1336: fmul
    //   1337: aload_0
    //   1338: getfield 267	com/google/android/gms/internal/ads/un:m	I
    //   1341: i2f
    //   1342: fdiv
    //   1343: invokestatic 524	android/opengl/GLES20:glUniform1f	(IF)V
    //   1346: iload_2
    //   1347: ldc_w 520
    //   1350: invokestatic 524	android/opengl/GLES20:glUniform1f	(IF)V
    //   1353: aload_0
    //   1354: iconst_0
    //   1355: putfield 277	com/google/android/gms/internal/ads/un:A	Z
    //   1358: aload_0
    //   1359: getfield 137	com/google/android/gms/internal/ads/un:v	Ljava/lang/Object;
    //   1362: astore_3
    //   1363: aload_3
    //   1364: monitorenter
    //   1365: aload_0
    //   1366: getfield 282	com/google/android/gms/internal/ads/un:B	Z
    //   1369: ifne +24 -> 1393
    //   1372: aload_0
    //   1373: getfield 277	com/google/android/gms/internal/ads/un:A	Z
    //   1376: ifne +17 -> 1393
    //   1379: aload_0
    //   1380: getfield 294	com/google/android/gms/internal/ads/un:s	I
    //   1383: ifne +10 -> 1393
    //   1386: aload_0
    //   1387: getfield 137	com/google/android/gms/internal/ads/un:v	Ljava/lang/Object;
    //   1390: invokevirtual 527	java/lang/Object:wait	()V
    //   1393: aload_3
    //   1394: monitorexit
    //   1395: goto -503 -> 892
    //   1398: astore_1
    //   1399: aload_3
    //   1400: monitorexit
    //   1401: aload_1
    //   1402: athrow
    //   1403: aload_0
    //   1404: getfield 121	com/google/android/gms/internal/ads/un:b	Lcom/google/android/gms/internal/ads/rn;
    //   1407: invokevirtual 529	com/google/android/gms/internal/ads/rn:b	()V
    //   1410: aload_0
    //   1411: getfield 290	com/google/android/gms/internal/ads/un:o	Landroid/graphics/SurfaceTexture;
    //   1414: aconst_null
    //   1415: invokevirtual 474	android/graphics/SurfaceTexture:setOnFrameAvailableListener	(Landroid/graphics/SurfaceTexture$OnFrameAvailableListener;)V
    //   1418: aload_0
    //   1419: aconst_null
    //   1420: putfield 290	com/google/android/gms/internal/ads/un:o	Landroid/graphics/SurfaceTexture;
    //   1423: aload_0
    //   1424: invokespecial 531	com/google/android/gms/internal/ads/un:d	()Z
    //   1427: pop
    //   1428: return
    //   1429: astore_3
    //   1430: goto +80 -> 1510
    //   1433: astore_3
    //   1434: ldc_w 533
    //   1437: aload_3
    //   1438: invokestatic 536	com/google/android/gms/internal/ads/Tl:b	(Ljava/lang/String;Ljava/lang/Throwable;)V
    //   1441: invokestatic 541	com/google/android/gms/ads/internal/k:g	()Lcom/google/android/gms/internal/ads/Zj;
    //   1444: aload_3
    //   1445: ldc_w 543
    //   1448: invokevirtual 548	com/google/android/gms/internal/ads/Zj:a	(Ljava/lang/Throwable;Ljava/lang/String;)V
    //   1451: aload_0
    //   1452: getfield 121	com/google/android/gms/internal/ads/un:b	Lcom/google/android/gms/internal/ads/rn;
    //   1455: invokevirtual 529	com/google/android/gms/internal/ads/rn:b	()V
    //   1458: aload_0
    //   1459: getfield 290	com/google/android/gms/internal/ads/un:o	Landroid/graphics/SurfaceTexture;
    //   1462: aconst_null
    //   1463: invokevirtual 474	android/graphics/SurfaceTexture:setOnFrameAvailableListener	(Landroid/graphics/SurfaceTexture$OnFrameAvailableListener;)V
    //   1466: aload_0
    //   1467: aconst_null
    //   1468: putfield 290	com/google/android/gms/internal/ads/un:o	Landroid/graphics/SurfaceTexture;
    //   1471: aload_0
    //   1472: invokespecial 531	com/google/android/gms/internal/ads/un:d	()Z
    //   1475: pop
    //   1476: return
    //   1477: astore_3
    //   1478: ldc_w 550
    //   1481: invokestatic 552	com/google/android/gms/internal/ads/Tl:d	(Ljava/lang/String;)V
    //   1484: aload_0
    //   1485: getfield 121	com/google/android/gms/internal/ads/un:b	Lcom/google/android/gms/internal/ads/rn;
    //   1488: invokevirtual 529	com/google/android/gms/internal/ads/rn:b	()V
    //   1491: aload_0
    //   1492: getfield 290	com/google/android/gms/internal/ads/un:o	Landroid/graphics/SurfaceTexture;
    //   1495: aconst_null
    //   1496: invokevirtual 474	android/graphics/SurfaceTexture:setOnFrameAvailableListener	(Landroid/graphics/SurfaceTexture$OnFrameAvailableListener;)V
    //   1499: aload_0
    //   1500: aconst_null
    //   1501: putfield 290	com/google/android/gms/internal/ads/un:o	Landroid/graphics/SurfaceTexture;
    //   1504: aload_0
    //   1505: invokespecial 531	com/google/android/gms/internal/ads/un:d	()Z
    //   1508: pop
    //   1509: return
    //   1510: aload_0
    //   1511: getfield 121	com/google/android/gms/internal/ads/un:b	Lcom/google/android/gms/internal/ads/rn;
    //   1514: invokevirtual 529	com/google/android/gms/internal/ads/rn:b	()V
    //   1517: aload_0
    //   1518: getfield 290	com/google/android/gms/internal/ads/un:o	Landroid/graphics/SurfaceTexture;
    //   1521: aconst_null
    //   1522: invokevirtual 474	android/graphics/SurfaceTexture:setOnFrameAvailableListener	(Landroid/graphics/SurfaceTexture$OnFrameAvailableListener;)V
    //   1525: aload_0
    //   1526: aconst_null
    //   1527: putfield 290	com/google/android/gms/internal/ads/un:o	Landroid/graphics/SurfaceTexture;
    //   1530: aload_0
    //   1531: invokespecial 531	com/google/android/gms/internal/ads/un:d	()Z
    //   1534: pop
    //   1535: aload_3
    //   1536: athrow
    //   1537: aload_0
    //   1538: getfield 236	com/google/android/gms/internal/ads/un:w	Ljavax/microedition/khronos/egl/EGL10;
    //   1541: invokeinterface 555 1 0
    //   1546: invokestatic 560	android/opengl/GLUtils:getEGLErrorString	(I)Ljava/lang/String;
    //   1549: invokestatic 210	java/lang/String:valueOf	(Ljava/lang/Object;)Ljava/lang/String;
    //   1552: astore_3
    //   1553: aload_3
    //   1554: invokevirtual 213	java/lang/String:length	()I
    //   1557: ifeq +14 -> 1571
    //   1560: ldc_w 562
    //   1563: aload_3
    //   1564: invokevirtual 566	java/lang/String:concat	(Ljava/lang/String;)Ljava/lang/String;
    //   1567: astore_3
    //   1568: goto +14 -> 1582
    //   1571: new 206	java/lang/String
    //   1574: dup
    //   1575: ldc_w 562
    //   1578: invokespecial 567	java/lang/String:<init>	(Ljava/lang/String;)V
    //   1581: astore_3
    //   1582: aload_3
    //   1583: invokestatic 305	com/google/android/gms/internal/ads/Tl:b	(Ljava/lang/String;)V
    //   1586: invokestatic 541	com/google/android/gms/ads/internal/k:g	()Lcom/google/android/gms/internal/ads/Zj;
    //   1589: new 299	java/lang/Throwable
    //   1592: dup
    //   1593: aload_3
    //   1594: invokespecial 568	java/lang/Throwable:<init>	(Ljava/lang/String;)V
    //   1597: ldc_w 570
    //   1600: invokevirtual 548	com/google/android/gms/internal/ads/Zj:a	(Ljava/lang/Throwable;Ljava/lang/String;)V
    //   1603: aload_0
    //   1604: invokespecial 531	com/google/android/gms/internal/ads/un:d	()Z
    //   1607: pop
    //   1608: aload_0
    //   1609: getfield 131	com/google/android/gms/internal/ads/un:u	Ljava/util/concurrent/CountDownLatch;
    //   1612: invokevirtual 308	java/util/concurrent/CountDownLatch:countDown	()V
    //   1615: return
    //   1616: astore_3
    //   1617: goto -725 -> 892
    // Local variable table:
    //   start	length	slot	name	signature
    //   0	1620	0	this	un
    //   51	1004	1	localObject1	Object
    //   1398	4	1	localObject2	Object
    //   60	1287	2	i1	int
    //   1429	1	3	localObject4	Object
    //   1433	12	3	localThrowable	Throwable
    //   1477	59	3	localIllegalStateException	IllegalStateException
    //   1552	42	3	str	String
    //   1616	1	3	localInterruptedException	InterruptedException
    //   381	95	4	i2	int
    //   389	938	5	i3	int
    //   443	46	6	i4	int
    //   456	402	7	i5	int
    //   974	93	8	arrayOfFloat	float[]
    // Exception table:
    //   from	to	target	type
    //   1365	1393	1398	finally
    //   1393	1395	1398	finally
    //   1399	1401	1398	finally
    //   887	892	1429	finally
    //   892	899	1429	finally
    //   899	923	1429	finally
    //   926	959	1429	finally
    //   971	976	1429	finally
    //   1060	1083	1429	finally
    //   1083	1099	1429	finally
    //   1102	1123	1429	finally
    //   1123	1323	1429	finally
    //   1326	1353	1429	finally
    //   1353	1358	1429	finally
    //   1358	1365	1429	finally
    //   1401	1403	1429	finally
    //   1434	1451	1429	finally
    //   1478	1484	1429	finally
    //   887	892	1433	java/lang/Throwable
    //   892	899	1433	java/lang/Throwable
    //   899	923	1433	java/lang/Throwable
    //   926	959	1433	java/lang/Throwable
    //   971	976	1433	java/lang/Throwable
    //   1060	1083	1433	java/lang/Throwable
    //   1083	1099	1433	java/lang/Throwable
    //   1102	1123	1433	java/lang/Throwable
    //   1123	1323	1433	java/lang/Throwable
    //   1326	1353	1433	java/lang/Throwable
    //   1353	1358	1433	java/lang/Throwable
    //   1358	1365	1433	java/lang/Throwable
    //   1401	1403	1433	java/lang/Throwable
    //   887	892	1477	java/lang/IllegalStateException
    //   892	899	1477	java/lang/IllegalStateException
    //   899	923	1477	java/lang/IllegalStateException
    //   926	959	1477	java/lang/IllegalStateException
    //   971	976	1477	java/lang/IllegalStateException
    //   1060	1083	1477	java/lang/IllegalStateException
    //   1083	1099	1477	java/lang/IllegalStateException
    //   1102	1123	1477	java/lang/IllegalStateException
    //   1123	1323	1477	java/lang/IllegalStateException
    //   1326	1353	1477	java/lang/IllegalStateException
    //   1353	1358	1477	java/lang/IllegalStateException
    //   1358	1365	1477	java/lang/IllegalStateException
    //   1401	1403	1477	java/lang/IllegalStateException
    //   1358	1365	1616	java/lang/InterruptedException
    //   1401	1403	1616	java/lang/InterruptedException
  }
}


/* Location:              /Applications/dex2jar/classes-dex2jar.jar!/com/google/android/gms/internal/ads/un.class
 * Java compiler version: 6 (50.0)
 * JD-Core Version:       0.7.1
 */