package com.google.android.gms.measurement.internal;

import qK;

final class pb
  implements Runnable
{
  pb(jb paramjb, pc parampc, qK paramqK) {}
  
  /* Error */
  public final void run()
  {
    // Byte code:
    //   0: aconst_null
    //   1: astore_1
    //   2: aconst_null
    //   3: astore_2
    //   4: aload_2
    //   5: astore_3
    //   6: aload_1
    //   7: astore 4
    //   9: aload_0
    //   10: getfield 16	com/google/android/gms/measurement/internal/pb:c	Lcom/google/android/gms/measurement/internal/jb;
    //   13: invokestatic 33	com/google/android/gms/measurement/internal/jb:d	(Lcom/google/android/gms/measurement/internal/jb;)Lcom/google/android/gms/measurement/internal/n;
    //   16: astore 5
    //   18: aload 5
    //   20: ifnonnull +39 -> 59
    //   23: aload_2
    //   24: astore_3
    //   25: aload_1
    //   26: astore 4
    //   28: aload_0
    //   29: getfield 16	com/google/android/gms/measurement/internal/pb:c	Lcom/google/android/gms/measurement/internal/jb;
    //   32: invokevirtual 36	com/google/android/gms/measurement/internal/jb:c	()Lcom/google/android/gms/measurement/internal/v;
    //   35: invokevirtual 42	com/google/android/gms/measurement/internal/v:s	()Lcom/google/android/gms/measurement/internal/x;
    //   38: ldc 44
    //   40: invokevirtual 49	com/google/android/gms/measurement/internal/x:a	(Ljava/lang/String;)V
    //   43: aload_0
    //   44: getfield 16	com/google/android/gms/measurement/internal/pb:c	Lcom/google/android/gms/measurement/internal/jb;
    //   47: invokevirtual 53	com/google/android/gms/measurement/internal/jb:e	()Lcom/google/android/gms/measurement/internal/hc;
    //   50: aload_0
    //   51: getfield 20	com/google/android/gms/measurement/internal/pb:b	LqK;
    //   54: aconst_null
    //   55: invokevirtual 58	com/google/android/gms/measurement/internal/hc:a	(LqK;Ljava/lang/String;)V
    //   58: return
    //   59: aload_2
    //   60: astore_3
    //   61: aload_1
    //   62: astore 4
    //   64: aload 5
    //   66: aload_0
    //   67: getfield 18	com/google/android/gms/measurement/internal/pb:a	Lcom/google/android/gms/measurement/internal/pc;
    //   70: invokeinterface 63 2 0
    //   75: astore_2
    //   76: aload_2
    //   77: ifnull +38 -> 115
    //   80: aload_2
    //   81: astore_3
    //   82: aload_2
    //   83: astore 4
    //   85: aload_0
    //   86: getfield 16	com/google/android/gms/measurement/internal/pb:c	Lcom/google/android/gms/measurement/internal/jb;
    //   89: invokevirtual 67	com/google/android/gms/measurement/internal/jb:o	()Lcom/google/android/gms/measurement/internal/Ha;
    //   92: aload_2
    //   93: invokevirtual 70	com/google/android/gms/measurement/internal/Ha:a	(Ljava/lang/String;)V
    //   96: aload_2
    //   97: astore_3
    //   98: aload_2
    //   99: astore 4
    //   101: aload_0
    //   102: getfield 16	com/google/android/gms/measurement/internal/pb:c	Lcom/google/android/gms/measurement/internal/jb;
    //   105: invokevirtual 74	com/google/android/gms/measurement/internal/jb:f	()Lcom/google/android/gms/measurement/internal/H;
    //   108: getfield 80	com/google/android/gms/measurement/internal/H:m	Lcom/google/android/gms/measurement/internal/M;
    //   111: aload_2
    //   112: invokevirtual 83	com/google/android/gms/measurement/internal/M:a	(Ljava/lang/String;)V
    //   115: aload_2
    //   116: astore_3
    //   117: aload_2
    //   118: astore 4
    //   120: aload_0
    //   121: getfield 16	com/google/android/gms/measurement/internal/pb:c	Lcom/google/android/gms/measurement/internal/jb;
    //   124: invokestatic 86	com/google/android/gms/measurement/internal/jb:e	(Lcom/google/android/gms/measurement/internal/jb;)V
    //   127: aload_0
    //   128: getfield 16	com/google/android/gms/measurement/internal/pb:c	Lcom/google/android/gms/measurement/internal/jb;
    //   131: invokevirtual 53	com/google/android/gms/measurement/internal/jb:e	()Lcom/google/android/gms/measurement/internal/hc;
    //   134: aload_0
    //   135: getfield 20	com/google/android/gms/measurement/internal/pb:b	LqK;
    //   138: aload_2
    //   139: invokevirtual 58	com/google/android/gms/measurement/internal/hc:a	(LqK;Ljava/lang/String;)V
    //   142: return
    //   143: astore 4
    //   145: goto +40 -> 185
    //   148: astore_2
    //   149: aload 4
    //   151: astore_3
    //   152: aload_0
    //   153: getfield 16	com/google/android/gms/measurement/internal/pb:c	Lcom/google/android/gms/measurement/internal/jb;
    //   156: invokevirtual 36	com/google/android/gms/measurement/internal/jb:c	()Lcom/google/android/gms/measurement/internal/v;
    //   159: invokevirtual 42	com/google/android/gms/measurement/internal/v:s	()Lcom/google/android/gms/measurement/internal/x;
    //   162: ldc 44
    //   164: aload_2
    //   165: invokevirtual 89	com/google/android/gms/measurement/internal/x:a	(Ljava/lang/String;Ljava/lang/Object;)V
    //   168: aload_0
    //   169: getfield 16	com/google/android/gms/measurement/internal/pb:c	Lcom/google/android/gms/measurement/internal/jb;
    //   172: invokevirtual 53	com/google/android/gms/measurement/internal/jb:e	()Lcom/google/android/gms/measurement/internal/hc;
    //   175: aload_0
    //   176: getfield 20	com/google/android/gms/measurement/internal/pb:b	LqK;
    //   179: aload 4
    //   181: invokevirtual 58	com/google/android/gms/measurement/internal/hc:a	(LqK;Ljava/lang/String;)V
    //   184: return
    //   185: aload_0
    //   186: getfield 16	com/google/android/gms/measurement/internal/pb:c	Lcom/google/android/gms/measurement/internal/jb;
    //   189: invokevirtual 53	com/google/android/gms/measurement/internal/jb:e	()Lcom/google/android/gms/measurement/internal/hc;
    //   192: aload_0
    //   193: getfield 20	com/google/android/gms/measurement/internal/pb:b	LqK;
    //   196: aload_3
    //   197: invokevirtual 58	com/google/android/gms/measurement/internal/hc:a	(LqK;Ljava/lang/String;)V
    //   200: aload 4
    //   202: athrow
    // Local variable table:
    //   start	length	slot	name	signature
    //   0	203	0	this	pb
    //   1	61	1	localObject1	Object
    //   3	136	2	str1	String
    //   148	17	2	localRemoteException	android.os.RemoteException
    //   5	192	3	localObject2	Object
    //   7	112	4	localObject3	Object
    //   143	58	4	str2	String
    //   16	49	5	localn	n
    // Exception table:
    //   from	to	target	type
    //   9	18	143	finally
    //   28	43	143	finally
    //   64	76	143	finally
    //   85	96	143	finally
    //   101	115	143	finally
    //   120	127	143	finally
    //   152	168	143	finally
    //   9	18	148	android/os/RemoteException
    //   28	43	148	android/os/RemoteException
    //   64	76	148	android/os/RemoteException
    //   85	96	148	android/os/RemoteException
    //   101	115	148	android/os/RemoteException
    //   120	127	148	android/os/RemoteException
  }
}


/* Location:              /Applications/dex2jar/classes-dex2jar.jar!/com/google/android/gms/measurement/internal/pb.class
 * Java compiler version: 6 (50.0)
 * JD-Core Version:       0.7.1
 */