package com.google.android.gms.measurement.internal;

import BG;
import FG;
import KG;
import LG;
import NG;
import OG;
import PG;
import android.text.TextUtils;
import gd;
import java.math.BigDecimal;
import java.util.ArrayList;
import java.util.Arrays;
import java.util.HashSet;
import java.util.Iterator;
import java.util.List;
import java.util.Locale;
import java.util.Map;
import java.util.Set;
import java.util.regex.Matcher;
import java.util.regex.Pattern;
import java.util.regex.PatternSyntaxException;
import kI.a;
import sG;
import tG;
import zG;
import zG.a;

final class rc
  extends Wb
{
  rc(Xb paramXb)
  {
    super(paramXb);
  }
  
  private final Boolean a(double paramDouble, NG paramNG)
  {
    try
    {
      BigDecimal localBigDecimal = new java/math/BigDecimal;
      localBigDecimal.<init>(paramDouble);
      paramNG = a(localBigDecimal, paramNG, Math.ulp(paramDouble));
      return paramNG;
    }
    catch (NumberFormatException paramNG) {}
    return null;
  }
  
  private final Boolean a(long paramLong, NG paramNG)
  {
    try
    {
      BigDecimal localBigDecimal = new java/math/BigDecimal;
      localBigDecimal.<init>(paramLong);
      paramNG = a(localBigDecimal, paramNG, 0.0D);
      return paramNG;
    }
    catch (NumberFormatException paramNG) {}
    return null;
  }
  
  private final Boolean a(KG paramKG, String paramString, List<BG> paramList, long paramLong)
  {
    Object localObject1 = paramKG.h;
    int i = 0;
    Boolean localBoolean = Boolean.valueOf(false);
    if (localObject1 != null)
    {
      localObject1 = a(paramLong, (NG)localObject1);
      if (localObject1 == null) {
        return null;
      }
      if (!((Boolean)localObject1).booleanValue()) {
        return localBoolean;
      }
    }
    HashSet localHashSet = new HashSet();
    for (localObject2 : paramKG.f)
    {
      if (TextUtils.isEmpty(((LG)localObject2).g))
      {
        c().v().a("null or empty param name in filter. event", d().a(paramString));
        return null;
      }
      localHashSet.add(((LG)localObject2).g);
    }
    localObject1 = new gd();
    Object localObject2 = paramList.iterator();
    Object localObject3;
    while (((Iterator)localObject2).hasNext())
    {
      paramList = (BG)((Iterator)localObject2).next();
      if (localHashSet.contains(paramList.m())) {
        if (paramList.q())
        {
          localObject3 = paramList.m();
          if (paramList.q()) {
            paramList = Long.valueOf(paramList.r());
          } else {
            paramList = null;
          }
          ((Map)localObject1).put(localObject3, paramList);
        }
        else if (paramList.s())
        {
          localObject3 = paramList.m();
          if (paramList.s()) {
            paramList = Double.valueOf(paramList.t());
          } else {
            paramList = null;
          }
          ((Map)localObject1).put(localObject3, paramList);
        }
        else if (paramList.o())
        {
          ((Map)localObject1).put(paramList.m(), paramList.p());
        }
        else
        {
          c().v().a("Unknown value for param. event, param", d().a(paramString), d().b(paramList.m()));
          return null;
        }
      }
    }
    paramList = paramKG.f;
    ??? = paramList.length;
    ??? = i;
    while (??? < ???)
    {
      localHashSet = paramList[???];
      boolean bool = Boolean.TRUE.equals(localHashSet.f);
      paramKG = localHashSet.g;
      if (TextUtils.isEmpty(paramKG))
      {
        c().v().a("Event has empty param name. event", d().a(paramString));
        return null;
      }
      localObject2 = ((Map)localObject1).get(paramKG);
      if ((localObject2 instanceof Long))
      {
        if (localHashSet.e == null)
        {
          c().v().a("No number filter for long param. event, param", d().a(paramString), d().b(paramKG));
          return null;
        }
        paramKG = a(((Long)localObject2).longValue(), localHashSet.e);
        if (paramKG == null) {
          return null;
        }
        if ((true ^ paramKG.booleanValue() ^ bool)) {
          return localBoolean;
        }
      }
      else if ((localObject2 instanceof Double))
      {
        if (localHashSet.e == null)
        {
          c().v().a("No number filter for double param. event, param", d().a(paramString), d().b(paramKG));
          return null;
        }
        paramKG = a(((Double)localObject2).doubleValue(), localHashSet.e);
        if (paramKG == null) {
          return null;
        }
        if ((true ^ paramKG.booleanValue() ^ bool)) {
          return localBoolean;
        }
      }
      else
      {
        if (!(localObject2 instanceof String)) {
          break label753;
        }
        localObject3 = localHashSet.d;
        if (localObject3 != null)
        {
          paramKG = a((String)localObject2, (PG)localObject3);
        }
        else
        {
          if (localHashSet.e == null) {
            break label723;
          }
          localObject2 = (String)localObject2;
          if (!cc.a((String)localObject2)) {
            break label693;
          }
          paramKG = a((String)localObject2, localHashSet.e);
        }
        if (paramKG == null) {
          return null;
        }
        if ((true ^ paramKG.booleanValue() ^ bool)) {
          return localBoolean;
        }
      }
      ???++;
      continue;
      label693:
      c().v().a("Invalid param value for number filter. event, param", d().a(paramString), d().b(paramKG));
      return null;
      label723:
      c().v().a("No filter for String param. event, param", d().a(paramString), d().b(paramKG));
      return null;
      label753:
      if (localObject2 == null)
      {
        c().A().a("Missing param for filter. event, param", d().a(paramString), d().b(paramKG));
        return localBoolean;
      }
      c().v().a("Unknown param type. event, param", d().a(paramString), d().b(paramKG));
      return null;
    }
    return Boolean.valueOf(true);
  }
  
  private final Boolean a(OG paramOG, FG paramFG)
  {
    paramOG = paramOG.f;
    if (paramOG == null)
    {
      c().v().a("Missing property filter. property", d().c(paramFG.m()));
      return null;
    }
    boolean bool = Boolean.TRUE.equals(paramOG.f);
    if (paramFG.q())
    {
      if (paramOG.e == null)
      {
        c().v().a("No number filter for long property. property", d().c(paramFG.m()));
        return null;
      }
      return a(a(paramFG.r(), paramOG.e), bool);
    }
    if (paramFG.s())
    {
      if (paramOG.e == null)
      {
        c().v().a("No number filter for double property. property", d().c(paramFG.m()));
        return null;
      }
      return a(a(paramFG.t(), paramOG.e), bool);
    }
    if (paramFG.o())
    {
      if (paramOG.d == null)
      {
        if (paramOG.e == null)
        {
          c().v().a("No string or number filter defined. property", d().c(paramFG.m()));
        }
        else
        {
          if (cc.a(paramFG.p())) {
            return a(a(paramFG.p(), paramOG.e), bool);
          }
          c().v().a("Invalid user property value for Numeric number filter. property, value", d().c(paramFG.m()), paramFG.p());
        }
        return null;
      }
      return a(a(paramFG.p(), paramOG.d), bool);
    }
    c().v().a("User property has no value, property", d().c(paramFG.m()));
    return null;
  }
  
  private static Boolean a(Boolean paramBoolean, boolean paramBoolean1)
  {
    if (paramBoolean == null) {
      return null;
    }
    return Boolean.valueOf(paramBoolean.booleanValue() ^ paramBoolean1);
  }
  
  private final Boolean a(String paramString, NG paramNG)
  {
    if (!cc.a(paramString)) {
      return null;
    }
    try
    {
      BigDecimal localBigDecimal = new java/math/BigDecimal;
      localBigDecimal.<init>(paramString);
      paramString = a(localBigDecimal, paramNG, 0.0D);
      return paramString;
    }
    catch (NumberFormatException paramString) {}
    return null;
  }
  
  private final Boolean a(String paramString, PG paramPG)
  {
    com.google.android.gms.common.internal.t.a(paramPG);
    if (paramString == null) {
      return null;
    }
    Object localObject1 = paramPG.c;
    if ((localObject1 != null) && (localObject1 != tG.a))
    {
      if (localObject1 == tG.g)
      {
        localObject1 = paramPG.f;
        if ((localObject1 == null) || (localObject1.length == 0)) {
          return null;
        }
      }
      else if (paramPG.d == null)
      {
        return null;
      }
      tG localtG = paramPG.c;
      localObject1 = paramPG.e;
      int i = 0;
      boolean bool;
      if ((localObject1 != null) && (((Boolean)localObject1).booleanValue())) {
        bool = true;
      } else {
        bool = false;
      }
      if ((!bool) && (localtG != tG.b) && (localtG != tG.g)) {
        localObject1 = paramPG.d.toUpperCase(Locale.ENGLISH);
      } else {
        localObject1 = paramPG.d;
      }
      Object localObject2 = paramPG.f;
      if (localObject2 == null)
      {
        paramPG = null;
      }
      else if (bool)
      {
        paramPG = Arrays.asList((Object[])localObject2);
      }
      else
      {
        paramPG = new ArrayList();
        int j = localObject2.length;
        while (i < j)
        {
          paramPG.add(localObject2[i].toUpperCase(Locale.ENGLISH));
          i++;
        }
      }
      if (localtG == tG.b) {
        localObject2 = localObject1;
      } else {
        localObject2 = null;
      }
      return a(paramString, localtG, bool, (String)localObject1, paramPG, (String)localObject2);
    }
    return null;
  }
  
  private final Boolean a(String paramString1, tG paramtG, boolean paramBoolean, String paramString2, List<String> paramList, String paramString3)
  {
    if (paramString1 == null) {
      return null;
    }
    if (paramtG == tG.g)
    {
      if ((paramList == null) || (paramList.size() == 0)) {
        return null;
      }
    }
    else if (paramString2 == null) {
      return null;
    }
    String str = paramString1;
    if (!paramBoolean) {
      if (paramtG == tG.b) {
        str = paramString1;
      } else {
        str = paramString1.toUpperCase(Locale.ENGLISH);
      }
    }
    switch (sc.a[paramtG.ordinal()])
    {
    default: 
      return null;
    case 6: 
      return Boolean.valueOf(paramList.contains(str));
    case 5: 
      return Boolean.valueOf(str.equals(paramString2));
    case 4: 
      return Boolean.valueOf(str.contains(paramString2));
    case 3: 
      return Boolean.valueOf(str.endsWith(paramString2));
    case 2: 
      return Boolean.valueOf(str.startsWith(paramString2));
    }
    int i;
    if (paramBoolean) {
      i = 0;
    } else {
      i = 66;
    }
    try
    {
      paramBoolean = Pattern.compile(paramString3, i).matcher(str).matches();
      return Boolean.valueOf(paramBoolean);
    }
    catch (PatternSyntaxException paramString1)
    {
      c().v().a("Invalid regular expression in REGEXP audience filter. expression", paramString3);
    }
    return null;
  }
  
  private static Boolean a(BigDecimal paramBigDecimal, NG paramNG, double paramDouble)
  {
    com.google.android.gms.common.internal.t.a(paramNG);
    Object localObject = paramNG.c;
    sG localsG;
    if ((localObject != null) && (localObject != sG.a))
    {
      if (localObject == sG.e)
      {
        if ((paramNG.f == null) || (paramNG.g == null)) {
          return null;
        }
      }
      else if (paramNG.e == null) {
        return null;
      }
      localsG = paramNG.c;
      if ((localsG == sG.e) && ((!cc.a(paramNG.f)) || (!cc.a(paramNG.g)))) {}
    }
    try
    {
      localBigDecimal = new java/math/BigDecimal;
      localBigDecimal.<init>(paramNG.f);
      localObject = new BigDecimal(paramNG.g);
      paramNG = localBigDecimal;
      localBigDecimal = null;
    }
    catch (NumberFormatException paramBigDecimal)
    {
      BigDecimal localBigDecimal;
      label427:
      for (;;) {}
    }
    return null;
    if (!cc.a(paramNG.e)) {
      return null;
    }
    try
    {
      localBigDecimal = new BigDecimal(paramNG.e);
      paramNG = null;
      localObject = paramNG;
      if (localsG == sG.e)
      {
        if (paramNG == null) {
          return null;
        }
      }
      else {
        if (localBigDecimal == null) {
          break label427;
        }
      }
      int i = sc.b[localsG.ordinal()];
      boolean bool1 = false;
      boolean bool2 = false;
      boolean bool3 = false;
      boolean bool4 = false;
      boolean bool5 = false;
      if (i != 1)
      {
        if (i != 2)
        {
          if (i != 3)
          {
            if (i == 4)
            {
              bool2 = bool5;
              if (paramBigDecimal.compareTo(paramNG) != -1)
              {
                bool2 = bool5;
                if (paramBigDecimal.compareTo((BigDecimal)localObject) != 1) {
                  bool2 = true;
                }
              }
              return Boolean.valueOf(bool2);
            }
          }
          else
          {
            if (paramDouble != 0.0D)
            {
              bool2 = bool1;
              if (paramBigDecimal.compareTo(localBigDecimal.subtract(new BigDecimal(paramDouble).multiply(new BigDecimal(2)))) == 1)
              {
                bool2 = bool1;
                if (paramBigDecimal.compareTo(localBigDecimal.add(new BigDecimal(paramDouble).multiply(new BigDecimal(2)))) == -1) {
                  bool2 = true;
                }
              }
              return Boolean.valueOf(bool2);
            }
            if (paramBigDecimal.compareTo(localBigDecimal) == 0) {
              bool2 = true;
            }
            return Boolean.valueOf(bool2);
          }
        }
        else
        {
          bool2 = bool3;
          if (paramBigDecimal.compareTo(localBigDecimal) == 1) {
            bool2 = true;
          }
          return Boolean.valueOf(bool2);
        }
      }
      else
      {
        bool2 = bool4;
        if (paramBigDecimal.compareTo(localBigDecimal) == -1) {
          bool2 = true;
        }
        return Boolean.valueOf(bool2);
      }
    }
    catch (NumberFormatException paramBigDecimal)
    {
      for (;;) {}
    }
    return null;
  }
  
  private static List<zG> a(Map<Integer, Long> paramMap)
  {
    if (paramMap == null) {
      return null;
    }
    ArrayList localArrayList = new ArrayList(paramMap.size());
    Iterator localIterator = paramMap.keySet().iterator();
    while (localIterator.hasNext())
    {
      int i = ((Integer)localIterator.next()).intValue();
      zG.a locala = zG.q();
      locala.a(i);
      locala.a(((Long)paramMap.get(Integer.valueOf(i))).longValue());
      localArrayList.add((zG)locala.J());
    }
    return localArrayList;
  }
  
  private static void a(Map<Integer, Long> paramMap, int paramInt, long paramLong)
  {
    Long localLong = (Long)paramMap.get(Integer.valueOf(paramInt));
    paramLong /= 1000L;
    if ((localLong == null) || (paramLong > localLong.longValue())) {
      paramMap.put(Integer.valueOf(paramInt), Long.valueOf(paramLong));
    }
  }
  
  private static boolean a(OG paramOG)
  {
    if (paramOG != null)
    {
      paramOG = paramOG.g;
      if ((paramOG != null) && (paramOG.booleanValue())) {
        return true;
      }
    }
    return false;
  }
  
  private static void b(Map<Integer, List<Long>> paramMap, int paramInt, long paramLong)
  {
    List localList = (List)paramMap.get(Integer.valueOf(paramInt));
    Object localObject = localList;
    if (localList == null)
    {
      localObject = new ArrayList();
      paramMap.put(Integer.valueOf(paramInt), localObject);
    }
    ((List)localObject).add(Long.valueOf(paramLong / 1000L));
  }
  
  /* Error */
  final yG[] a(String arg1, SG[] arg2, FG[] arg3)
  {
    // Byte code:
    //   0: aload_1
    //   1: astore 4
    //   3: aload_2
    //   4: astore 5
    //   6: aload_1
    //   7: invokestatic 444	com/google/android/gms/common/internal/t:b	(Ljava/lang/String;)Ljava/lang/String;
    //   10: pop
    //   11: new 52	java/util/HashSet
    //   14: dup
    //   15: invokespecial 55	java/util/HashSet:<init>	()V
    //   18: astore 6
    //   20: new 107	gd
    //   23: dup
    //   24: invokespecial 108	gd:<init>	()V
    //   27: astore 7
    //   29: new 107	gd
    //   32: dup
    //   33: invokespecial 108	gd:<init>	()V
    //   36: astore 8
    //   38: new 107	gd
    //   41: dup
    //   42: invokespecial 108	gd:<init>	()V
    //   45: astore 9
    //   47: new 107	gd
    //   50: dup
    //   51: invokespecial 108	gd:<init>	()V
    //   54: astore 10
    //   56: new 107	gd
    //   59: dup
    //   60: invokespecial 108	gd:<init>	()V
    //   63: astore 11
    //   65: aload_0
    //   66: invokevirtual 447	com/google/android/gms/measurement/internal/wa:g	()Lcom/google/android/gms/measurement/internal/wc;
    //   69: aload 4
    //   71: invokevirtual 451	com/google/android/gms/measurement/internal/wc:o	(Ljava/lang/String;)Z
    //   74: istore 12
    //   76: aload_0
    //   77: invokevirtual 447	com/google/android/gms/measurement/internal/wa:g	()Lcom/google/android/gms/measurement/internal/wc;
    //   80: aload 4
    //   82: getstatic 457	com/google/android/gms/measurement/internal/m:Ea	Lcom/google/android/gms/measurement/internal/m$a;
    //   85: invokevirtual 460	com/google/android/gms/measurement/internal/wc:d	(Ljava/lang/String;Lcom/google/android/gms/measurement/internal/m$a;)Z
    //   88: istore 13
    //   90: aload_0
    //   91: invokevirtual 465	com/google/android/gms/measurement/internal/Vb:o	()Lcom/google/android/gms/measurement/internal/zc;
    //   94: aload 4
    //   96: invokevirtual 470	com/google/android/gms/measurement/internal/zc:e	(Ljava/lang/String;)Ljava/util/Map;
    //   99: astore 14
    //   101: aload 10
    //   103: astore 15
    //   105: aload 9
    //   107: astore 16
    //   109: aload 8
    //   111: astore 17
    //   113: aload 6
    //   115: astore 18
    //   117: aload 14
    //   119: ifnull +582 -> 701
    //   122: aload 14
    //   124: invokeinterface 402 1 0
    //   129: invokeinterface 403 1 0
    //   134: astore 4
    //   136: aload 10
    //   138: astore 15
    //   140: aload 9
    //   142: astore 16
    //   144: aload 8
    //   146: astore 17
    //   148: aload 6
    //   150: astore 18
    //   152: aload 4
    //   154: invokeinterface 119 1 0
    //   159: ifeq +542 -> 701
    //   162: aload 4
    //   164: invokeinterface 123 1 0
    //   169: checkcast 405	java/lang/Integer
    //   172: invokevirtual 408	java/lang/Integer:intValue	()I
    //   175: istore 19
    //   177: aload 14
    //   179: iload 19
    //   181: invokestatic 421	java/lang/Integer:valueOf	(I)Ljava/lang/Integer;
    //   184: invokeinterface 191 2 0
    //   189: checkcast 472	DG
    //   192: astore 20
    //   194: aload 8
    //   196: iload 19
    //   198: invokestatic 421	java/lang/Integer:valueOf	(I)Ljava/lang/Integer;
    //   201: invokeinterface 191 2 0
    //   206: checkcast 474	java/util/BitSet
    //   209: astore 15
    //   211: aload 9
    //   213: iload 19
    //   215: invokestatic 421	java/lang/Integer:valueOf	(I)Ljava/lang/Integer;
    //   218: invokeinterface 191 2 0
    //   223: checkcast 474	java/util/BitSet
    //   226: astore 18
    //   228: iload 12
    //   230: ifeq +176 -> 406
    //   233: new 107	gd
    //   236: dup
    //   237: invokespecial 108	gd:<init>	()V
    //   240: astore 21
    //   242: aload 4
    //   244: astore 16
    //   246: aload 18
    //   248: astore 17
    //   250: aload 20
    //   252: ifnull +124 -> 376
    //   255: aload 20
    //   257: invokevirtual 476	DG:r	()I
    //   260: ifne +14 -> 274
    //   263: aload 4
    //   265: astore 16
    //   267: aload 18
    //   269: astore 17
    //   271: goto +105 -> 376
    //   274: aload 20
    //   276: invokevirtual 479	DG:q	()Ljava/util/List;
    //   279: invokeinterface 114 1 0
    //   284: astore 22
    //   286: aload 4
    //   288: astore 16
    //   290: aload 18
    //   292: astore 17
    //   294: aload 22
    //   296: invokeinterface 119 1 0
    //   301: ifeq +75 -> 376
    //   304: aload 22
    //   306: invokeinterface 123 1 0
    //   311: checkcast 410	zG
    //   314: astore 17
    //   316: aload 17
    //   318: invokevirtual 482	zG:n	()Z
    //   321: ifeq +52 -> 373
    //   324: aload 17
    //   326: invokevirtual 484	zG:m	()I
    //   329: istore 23
    //   331: aload 17
    //   333: invokevirtual 485	zG:o	()Z
    //   336: ifeq +16 -> 352
    //   339: aload 17
    //   341: invokevirtual 487	zG:p	()J
    //   344: invokestatic 144	java/lang/Long:valueOf	(J)Ljava/lang/Long;
    //   347: astore 17
    //   349: goto +6 -> 355
    //   352: aconst_null
    //   353: astore 17
    //   355: aload 21
    //   357: iload 23
    //   359: invokestatic 421	java/lang/Integer:valueOf	(I)Ljava/lang/Integer;
    //   362: aload 17
    //   364: invokeinterface 150 3 0
    //   369: pop
    //   370: goto +3 -> 373
    //   373: goto -87 -> 286
    //   376: aload 16
    //   378: astore 4
    //   380: aload 17
    //   382: astore 18
    //   384: aload 10
    //   386: iload 19
    //   388: invokestatic 421	java/lang/Integer:valueOf	(I)Ljava/lang/Integer;
    //   391: aload 21
    //   393: invokeinterface 150 3 0
    //   398: pop
    //   399: aload 21
    //   401: astore 17
    //   403: goto +6 -> 409
    //   406: aconst_null
    //   407: astore 17
    //   409: aload 15
    //   411: ifnonnull +54 -> 465
    //   414: new 474	java/util/BitSet
    //   417: dup
    //   418: invokespecial 488	java/util/BitSet:<init>	()V
    //   421: astore 16
    //   423: aload 8
    //   425: iload 19
    //   427: invokestatic 421	java/lang/Integer:valueOf	(I)Ljava/lang/Integer;
    //   430: aload 16
    //   432: invokeinterface 150 3 0
    //   437: pop
    //   438: new 474	java/util/BitSet
    //   441: dup
    //   442: invokespecial 488	java/util/BitSet:<init>	()V
    //   445: astore 18
    //   447: aload 9
    //   449: iload 19
    //   451: invokestatic 421	java/lang/Integer:valueOf	(I)Ljava/lang/Integer;
    //   454: aload 18
    //   456: invokeinterface 150 3 0
    //   461: pop
    //   462: goto +7 -> 469
    //   465: aload 15
    //   467: astore 16
    //   469: iconst_0
    //   470: istore 23
    //   472: iload 23
    //   474: aload 20
    //   476: invokevirtual 490	DG:n	()I
    //   479: bipush 6
    //   481: ishl
    //   482: if_icmpge +104 -> 586
    //   485: aload 20
    //   487: invokevirtual 492	DG:m	()Ljava/util/List;
    //   490: iload 23
    //   492: invokestatic 495	com/google/android/gms/measurement/internal/cc:a	(Ljava/util/List;I)Z
    //   495: ifeq +59 -> 554
    //   498: aload_0
    //   499: invokevirtual 77	com/google/android/gms/measurement/internal/wa:c	()Lcom/google/android/gms/measurement/internal/v;
    //   502: invokevirtual 229	com/google/android/gms/measurement/internal/v:A	()Lcom/google/android/gms/measurement/internal/x;
    //   505: ldc_w 497
    //   508: iload 19
    //   510: invokestatic 421	java/lang/Integer:valueOf	(I)Ljava/lang/Integer;
    //   513: iload 23
    //   515: invokestatic 421	java/lang/Integer:valueOf	(I)Ljava/lang/Integer;
    //   518: invokevirtual 176	com/google/android/gms/measurement/internal/x:a	(Ljava/lang/String;Ljava/lang/Object;Ljava/lang/Object;)V
    //   521: aload 18
    //   523: iload 23
    //   525: invokevirtual 500	java/util/BitSet:set	(I)V
    //   528: aload 20
    //   530: invokevirtual 502	DG:o	()Ljava/util/List;
    //   533: iload 23
    //   535: invokestatic 495	com/google/android/gms/measurement/internal/cc:a	(Ljava/util/List;I)Z
    //   538: ifeq +16 -> 554
    //   541: aload 16
    //   543: iload 23
    //   545: invokevirtual 500	java/util/BitSet:set	(I)V
    //   548: iconst_1
    //   549: istore 24
    //   551: goto +6 -> 557
    //   554: iconst_0
    //   555: istore 24
    //   557: aload 17
    //   559: ifnull +21 -> 580
    //   562: iload 24
    //   564: ifne +16 -> 580
    //   567: aload 17
    //   569: iload 23
    //   571: invokestatic 421	java/lang/Integer:valueOf	(I)Ljava/lang/Integer;
    //   574: invokeinterface 505 2 0
    //   579: pop
    //   580: iinc 23 1
    //   583: goto -111 -> 472
    //   586: invokestatic 511	yG:u	()LyG$a;
    //   589: astore 15
    //   591: aload 15
    //   593: iconst_0
    //   594: invokevirtual 516	yG$a:a	(Z)LyG$a;
    //   597: pop
    //   598: aload 15
    //   600: aload 20
    //   602: invokevirtual 519	yG$a:a	(LDG;)LyG$a;
    //   605: pop
    //   606: invokestatic 522	DG:u	()LDG$a;
    //   609: astore 21
    //   611: aload 21
    //   613: aload 16
    //   615: invokestatic 525	com/google/android/gms/measurement/internal/cc:a	(Ljava/util/BitSet;)Ljava/util/List;
    //   618: invokevirtual 530	DG$a:b	(Ljava/lang/Iterable;)LDG$a;
    //   621: pop
    //   622: aload 21
    //   624: aload 18
    //   626: invokestatic 525	com/google/android/gms/measurement/internal/cc:a	(Ljava/util/BitSet;)Ljava/util/List;
    //   629: invokevirtual 532	DG$a:a	(Ljava/lang/Iterable;)LDG$a;
    //   632: pop
    //   633: iload 12
    //   635: ifeq +34 -> 669
    //   638: aload 21
    //   640: aload 17
    //   642: invokestatic 534	com/google/android/gms/measurement/internal/rc:a	(Ljava/util/Map;)Ljava/util/List;
    //   645: invokevirtual 536	DG$a:c	(Ljava/lang/Iterable;)LDG$a;
    //   648: pop
    //   649: aload 11
    //   651: iload 19
    //   653: invokestatic 421	java/lang/Integer:valueOf	(I)Ljava/lang/Integer;
    //   656: new 107	gd
    //   659: dup
    //   660: invokespecial 108	gd:<init>	()V
    //   663: invokeinterface 150 3 0
    //   668: pop
    //   669: aload 15
    //   671: aload 21
    //   673: invokevirtual 539	yG$a:a	(LDG$a;)LyG$a;
    //   676: pop
    //   677: aload 7
    //   679: iload 19
    //   681: invokestatic 421	java/lang/Integer:valueOf	(I)Ljava/lang/Integer;
    //   684: aload 15
    //   686: invokevirtual 430	kI$a:J	()LTI;
    //   689: checkcast 507	yG
    //   692: invokeinterface 150 3 0
    //   697: pop
    //   698: goto -562 -> 136
    //   701: aload 15
    //   703: astore 4
    //   705: aload 16
    //   707: astore 9
    //   709: aload 17
    //   711: astore 6
    //   713: aload 18
    //   715: astore 10
    //   717: ldc_w 541
    //   720: astore 17
    //   722: ldc_w 543
    //   725: astore 18
    //   727: aload 11
    //   729: astore 25
    //   731: aload 18
    //   733: astore 26
    //   735: aload 17
    //   737: astore 27
    //   739: aload 7
    //   741: astore 28
    //   743: aload 9
    //   745: astore 22
    //   747: aload 4
    //   749: astore 14
    //   751: aload 6
    //   753: astore 20
    //   755: aload 10
    //   757: astore 21
    //   759: aload 5
    //   761: ifnull +2301 -> 3062
    //   764: new 107	gd
    //   767: dup
    //   768: invokespecial 108	gd:<init>	()V
    //   771: astore 21
    //   773: aload 5
    //   775: arraylength
    //   776: istore 23
    //   778: lconst_0
    //   779: lstore 29
    //   781: aconst_null
    //   782: astore 15
    //   784: aconst_null
    //   785: astore 14
    //   787: iconst_0
    //   788: istore 19
    //   790: aload 7
    //   792: astore 8
    //   794: aload 11
    //   796: astore 16
    //   798: aload 21
    //   800: astore 7
    //   802: aload 14
    //   804: astore 11
    //   806: aload_1
    //   807: astore 5
    //   809: aload 16
    //   811: astore 25
    //   813: aload 18
    //   815: astore 26
    //   817: aload 17
    //   819: astore 27
    //   821: aload 8
    //   823: astore 28
    //   825: aload 9
    //   827: astore 22
    //   829: aload 4
    //   831: astore 14
    //   833: aload 6
    //   835: astore 20
    //   837: aload 10
    //   839: astore 21
    //   841: iload 19
    //   843: iload 23
    //   845: if_icmpge +2217 -> 3062
    //   848: aload_2
    //   849: iload 19
    //   851: aaload
    //   852: astore 14
    //   854: aload 14
    //   856: getfield 546	SG:e	Ljava/lang/String;
    //   859: astore 20
    //   861: aload 14
    //   863: getfield 549	SG:d	[LBG;
    //   866: invokestatic 310	java/util/Arrays:asList	([Ljava/lang/Object;)Ljava/util/List;
    //   869: astore 22
    //   871: aload_0
    //   872: invokevirtual 447	com/google/android/gms/measurement/internal/wa:g	()Lcom/google/android/gms/measurement/internal/wc;
    //   875: aload 5
    //   877: getstatic 552	com/google/android/gms/measurement/internal/m:ca	Lcom/google/android/gms/measurement/internal/m$a;
    //   880: invokevirtual 460	com/google/android/gms/measurement/internal/wc:d	(Ljava/lang/String;Lcom/google/android/gms/measurement/internal/m$a;)Z
    //   883: ifeq +711 -> 1594
    //   886: aload_0
    //   887: invokevirtual 556	com/google/android/gms/measurement/internal/Vb:l	()Lcom/google/android/gms/measurement/internal/cc;
    //   890: pop
    //   891: aload 14
    //   893: ldc_w 558
    //   896: invokestatic 561	com/google/android/gms/measurement/internal/cc:b	(LSG;Ljava/lang/String;)Ljava/lang/Object;
    //   899: checkcast 141	java/lang/Long
    //   902: astore 27
    //   904: aload 27
    //   906: ifnull +9 -> 915
    //   909: iconst_1
    //   910: istore 31
    //   912: goto +6 -> 918
    //   915: iconst_0
    //   916: istore 31
    //   918: iload 31
    //   920: ifeq +20 -> 940
    //   923: aload 20
    //   925: ldc_w 563
    //   928: invokevirtual 335	java/lang/String:equals	(Ljava/lang/Object;)Z
    //   931: ifeq +9 -> 940
    //   934: iconst_1
    //   935: istore 24
    //   937: goto +6 -> 943
    //   940: iconst_0
    //   941: istore 24
    //   943: iload 24
    //   945: ifeq +534 -> 1479
    //   948: aload_0
    //   949: invokevirtual 556	com/google/android/gms/measurement/internal/Vb:l	()Lcom/google/android/gms/measurement/internal/cc;
    //   952: pop
    //   953: aload 14
    //   955: ldc_w 565
    //   958: invokestatic 561	com/google/android/gms/measurement/internal/cc:b	(LSG;Ljava/lang/String;)Ljava/lang/Object;
    //   961: checkcast 208	java/lang/String
    //   964: astore 28
    //   966: aload 28
    //   968: invokestatic 71	android/text/TextUtils:isEmpty	(Ljava/lang/CharSequence;)Z
    //   971: ifeq +21 -> 992
    //   974: aload_0
    //   975: invokevirtual 77	com/google/android/gms/measurement/internal/wa:c	()Lcom/google/android/gms/measurement/internal/v;
    //   978: invokevirtual 567	com/google/android/gms/measurement/internal/v:s	()Lcom/google/android/gms/measurement/internal/x;
    //   981: ldc_w 569
    //   984: aload 27
    //   986: invokevirtual 99	com/google/android/gms/measurement/internal/x:a	(Ljava/lang/String;Ljava/lang/Object;)V
    //   989: goto +431 -> 1420
    //   992: aload 15
    //   994: ifnull +44 -> 1038
    //   997: aload 11
    //   999: ifnull +39 -> 1038
    //   1002: aload 15
    //   1004: astore 20
    //   1006: aload 11
    //   1008: astore 21
    //   1010: lload 29
    //   1012: lstore 32
    //   1014: aload 27
    //   1016: invokevirtual 199	java/lang/Long:longValue	()J
    //   1019: aload 11
    //   1021: invokevirtual 199	java/lang/Long:longValue	()J
    //   1024: lcmp
    //   1025: ifeq +6 -> 1031
    //   1028: goto +10 -> 1038
    //   1031: aload 21
    //   1033: astore 15
    //   1035: goto +77 -> 1112
    //   1038: aload_0
    //   1039: invokevirtual 465	com/google/android/gms/measurement/internal/Vb:o	()Lcom/google/android/gms/measurement/internal/zc;
    //   1042: aload 5
    //   1044: aload 27
    //   1046: invokevirtual 572	com/google/android/gms/measurement/internal/zc:a	(Ljava/lang/String;Ljava/lang/Long;)Landroid/util/Pair;
    //   1049: astore 21
    //   1051: aload 21
    //   1053: ifnull +350 -> 1403
    //   1056: aload 21
    //   1058: getfield 578	android/util/Pair:first	Ljava/lang/Object;
    //   1061: astore 20
    //   1063: aload 20
    //   1065: ifnonnull +6 -> 1071
    //   1068: goto +335 -> 1403
    //   1071: aload 20
    //   1073: checkcast 545	SG
    //   1076: astore 20
    //   1078: aload 21
    //   1080: getfield 581	android/util/Pair:second	Ljava/lang/Object;
    //   1083: checkcast 141	java/lang/Long
    //   1086: invokevirtual 199	java/lang/Long:longValue	()J
    //   1089: lstore 32
    //   1091: aload_0
    //   1092: invokevirtual 556	com/google/android/gms/measurement/internal/Vb:l	()Lcom/google/android/gms/measurement/internal/cc;
    //   1095: pop
    //   1096: aload 20
    //   1098: ldc_w 558
    //   1101: invokestatic 561	com/google/android/gms/measurement/internal/cc:b	(LSG;Ljava/lang/String;)Ljava/lang/Object;
    //   1104: checkcast 141	java/lang/Long
    //   1107: astore 21
    //   1109: goto -78 -> 1031
    //   1112: lload 32
    //   1114: lconst_1
    //   1115: lsub
    //   1116: lstore 29
    //   1118: lload 29
    //   1120: lconst_0
    //   1121: lcmp
    //   1122: ifgt +91 -> 1213
    //   1125: aload_0
    //   1126: invokevirtual 465	com/google/android/gms/measurement/internal/Vb:o	()Lcom/google/android/gms/measurement/internal/zc;
    //   1129: astore 21
    //   1131: aload 21
    //   1133: invokevirtual 584	com/google/android/gms/measurement/internal/wa:j	()V
    //   1136: aload 21
    //   1138: invokevirtual 77	com/google/android/gms/measurement/internal/wa:c	()Lcom/google/android/gms/measurement/internal/v;
    //   1141: invokevirtual 229	com/google/android/gms/measurement/internal/v:A	()Lcom/google/android/gms/measurement/internal/x;
    //   1144: ldc_w 586
    //   1147: aload 5
    //   1149: invokevirtual 99	com/google/android/gms/measurement/internal/x:a	(Ljava/lang/String;Ljava/lang/Object;)V
    //   1152: aload 21
    //   1154: invokevirtual 590	com/google/android/gms/measurement/internal/zc:w	()Landroid/database/sqlite/SQLiteDatabase;
    //   1157: astore 11
    //   1159: aload 11
    //   1161: ldc_w 592
    //   1164: iconst_1
    //   1165: anewarray 208	java/lang/String
    //   1168: dup
    //   1169: iconst_0
    //   1170: aload 5
    //   1172: aastore
    //   1173: invokevirtual 598	android/database/sqlite/SQLiteDatabase:execSQL	(Ljava/lang/String;[Ljava/lang/Object;)V
    //   1176: goto +30 -> 1206
    //   1179: astore 11
    //   1181: goto +9 -> 1190
    //   1184: astore_1
    //   1185: goto +5 -> 1190
    //   1188: astore 11
    //   1190: aload 21
    //   1192: invokevirtual 77	com/google/android/gms/measurement/internal/wa:c	()Lcom/google/android/gms/measurement/internal/v;
    //   1195: invokevirtual 567	com/google/android/gms/measurement/internal/v:s	()Lcom/google/android/gms/measurement/internal/x;
    //   1198: ldc_w 600
    //   1201: aload 11
    //   1203: invokevirtual 99	com/google/android/gms/measurement/internal/x:a	(Ljava/lang/String;Ljava/lang/Object;)V
    //   1206: aload 14
    //   1208: astore 21
    //   1210: goto +26 -> 1236
    //   1213: aload_0
    //   1214: invokevirtual 465	com/google/android/gms/measurement/internal/Vb:o	()Lcom/google/android/gms/measurement/internal/zc;
    //   1217: astore 11
    //   1219: aload 11
    //   1221: aload_1
    //   1222: aload 27
    //   1224: lload 29
    //   1226: aload 20
    //   1228: invokevirtual 603	com/google/android/gms/measurement/internal/zc:a	(Ljava/lang/String;Ljava/lang/Long;JLSG;)Z
    //   1231: pop
    //   1232: aload 14
    //   1234: astore 21
    //   1236: new 312	java/util/ArrayList
    //   1239: dup
    //   1240: invokespecial 313	java/util/ArrayList:<init>	()V
    //   1243: astore 11
    //   1245: aload 20
    //   1247: getfield 549	SG:d	[LBG;
    //   1250: astore 14
    //   1252: aload 14
    //   1254: arraylength
    //   1255: istore 31
    //   1257: iconst_0
    //   1258: istore 24
    //   1260: iload 24
    //   1262: iload 31
    //   1264: if_icmpge +44 -> 1308
    //   1267: aload 14
    //   1269: iload 24
    //   1271: aaload
    //   1272: astore 27
    //   1274: aload_0
    //   1275: invokevirtual 556	com/google/android/gms/measurement/internal/Vb:l	()Lcom/google/android/gms/measurement/internal/cc;
    //   1278: pop
    //   1279: aload 21
    //   1281: aload 27
    //   1283: invokevirtual 129	BG:m	()Ljava/lang/String;
    //   1286: invokestatic 606	com/google/android/gms/measurement/internal/cc:a	(LSG;Ljava/lang/String;)LBG;
    //   1289: ifnonnull +13 -> 1302
    //   1292: aload 11
    //   1294: aload 27
    //   1296: invokeinterface 314 2 0
    //   1301: pop
    //   1302: iinc 24 1
    //   1305: goto -45 -> 1260
    //   1308: aload 11
    //   1310: invokeinterface 608 1 0
    //   1315: ifne +62 -> 1377
    //   1318: aload 22
    //   1320: invokeinterface 114 1 0
    //   1325: astore 14
    //   1327: aload 14
    //   1329: invokeinterface 119 1 0
    //   1334: ifeq +24 -> 1358
    //   1337: aload 11
    //   1339: aload 14
    //   1341: invokeinterface 123 1 0
    //   1346: checkcast 125	BG
    //   1349: invokeinterface 314 2 0
    //   1354: pop
    //   1355: goto -28 -> 1327
    //   1358: aload 20
    //   1360: astore 22
    //   1362: aload 28
    //   1364: astore 14
    //   1366: aload 11
    //   1368: astore 20
    //   1370: aload 22
    //   1372: astore 11
    //   1374: goto +252 -> 1626
    //   1377: aload_0
    //   1378: invokevirtual 77	com/google/android/gms/measurement/internal/wa:c	()Lcom/google/android/gms/measurement/internal/v;
    //   1381: invokevirtual 83	com/google/android/gms/measurement/internal/v:v	()Lcom/google/android/gms/measurement/internal/x;
    //   1384: ldc_w 610
    //   1387: aload 28
    //   1389: invokevirtual 99	com/google/android/gms/measurement/internal/x:a	(Ljava/lang/String;Ljava/lang/Object;)V
    //   1392: aload 20
    //   1394: astore 11
    //   1396: aload 28
    //   1398: astore 14
    //   1400: goto +222 -> 1622
    //   1403: aload_0
    //   1404: invokevirtual 77	com/google/android/gms/measurement/internal/wa:c	()Lcom/google/android/gms/measurement/internal/v;
    //   1407: invokevirtual 567	com/google/android/gms/measurement/internal/v:s	()Lcom/google/android/gms/measurement/internal/x;
    //   1410: ldc_w 612
    //   1413: aload 28
    //   1415: aload 27
    //   1417: invokevirtual 176	com/google/android/gms/measurement/internal/x:a	(Ljava/lang/String;Ljava/lang/Object;Ljava/lang/Object;)V
    //   1420: aload 16
    //   1422: astore 14
    //   1424: aload 7
    //   1426: astore 22
    //   1428: aload 18
    //   1430: astore 20
    //   1432: aload 17
    //   1434: astore 18
    //   1436: aload 9
    //   1438: astore 21
    //   1440: aload 6
    //   1442: astore 9
    //   1444: aload 4
    //   1446: astore 16
    //   1448: aload 11
    //   1450: astore 7
    //   1452: aload 10
    //   1454: astore 4
    //   1456: aload 8
    //   1458: astore 11
    //   1460: aload 22
    //   1462: astore 17
    //   1464: aload 14
    //   1466: astore 6
    //   1468: aload 20
    //   1470: astore 8
    //   1472: aload 21
    //   1474: astore 10
    //   1476: goto +1528 -> 3004
    //   1479: aload 14
    //   1481: astore 21
    //   1483: iload 23
    //   1485: istore 24
    //   1487: iload 31
    //   1489: ifeq +109 -> 1598
    //   1492: aload_0
    //   1493: invokevirtual 556	com/google/android/gms/measurement/internal/Vb:l	()Lcom/google/android/gms/measurement/internal/cc;
    //   1496: pop
    //   1497: lconst_0
    //   1498: invokestatic 144	java/lang/Long:valueOf	(J)Ljava/lang/Long;
    //   1501: astore 11
    //   1503: aload 21
    //   1505: ldc_w 614
    //   1508: invokestatic 561	com/google/android/gms/measurement/internal/cc:b	(LSG;Ljava/lang/String;)Ljava/lang/Object;
    //   1511: astore 15
    //   1513: aload 15
    //   1515: ifnonnull +10 -> 1525
    //   1518: aload 11
    //   1520: astore 15
    //   1522: goto +3 -> 1525
    //   1525: aload 15
    //   1527: checkcast 141	java/lang/Long
    //   1530: invokevirtual 199	java/lang/Long:longValue	()J
    //   1533: lstore 29
    //   1535: lload 29
    //   1537: lconst_0
    //   1538: lcmp
    //   1539: ifgt +21 -> 1560
    //   1542: aload_0
    //   1543: invokevirtual 77	com/google/android/gms/measurement/internal/wa:c	()Lcom/google/android/gms/measurement/internal/v;
    //   1546: invokevirtual 83	com/google/android/gms/measurement/internal/v:v	()Lcom/google/android/gms/measurement/internal/x;
    //   1549: ldc_w 616
    //   1552: aload 20
    //   1554: invokevirtual 99	com/google/android/gms/measurement/internal/x:a	(Ljava/lang/String;Ljava/lang/Object;)V
    //   1557: goto +18 -> 1575
    //   1560: aload_0
    //   1561: invokevirtual 465	com/google/android/gms/measurement/internal/Vb:o	()Lcom/google/android/gms/measurement/internal/zc;
    //   1564: aload_1
    //   1565: aload 27
    //   1567: lload 29
    //   1569: aload 21
    //   1571: invokevirtual 603	com/google/android/gms/measurement/internal/zc:a	(Ljava/lang/String;Ljava/lang/Long;JLSG;)Z
    //   1574: pop
    //   1575: aload 27
    //   1577: astore 15
    //   1579: aload 20
    //   1581: astore 14
    //   1583: aload 22
    //   1585: astore 20
    //   1587: aload 21
    //   1589: astore 11
    //   1591: goto +35 -> 1626
    //   1594: iload 23
    //   1596: istore 24
    //   1598: aload 11
    //   1600: astore 21
    //   1602: aload 15
    //   1604: astore 11
    //   1606: aload 21
    //   1608: astore 15
    //   1610: iload 24
    //   1612: istore 23
    //   1614: aload 14
    //   1616: astore 21
    //   1618: aload 20
    //   1620: astore 14
    //   1622: aload 22
    //   1624: astore 20
    //   1626: aload_0
    //   1627: invokevirtual 465	com/google/android/gms/measurement/internal/Vb:o	()Lcom/google/android/gms/measurement/internal/zc;
    //   1630: aload 5
    //   1632: aload 21
    //   1634: getfield 546	SG:e	Ljava/lang/String;
    //   1637: invokevirtual 619	com/google/android/gms/measurement/internal/zc:b	(Ljava/lang/String;Ljava/lang/String;)Lcom/google/android/gms/measurement/internal/g;
    //   1640: astore 22
    //   1642: aload 22
    //   1644: ifnonnull +62 -> 1706
    //   1647: aload_0
    //   1648: invokevirtual 77	com/google/android/gms/measurement/internal/wa:c	()Lcom/google/android/gms/measurement/internal/v;
    //   1651: invokevirtual 83	com/google/android/gms/measurement/internal/v:v	()Lcom/google/android/gms/measurement/internal/x;
    //   1654: ldc_w 621
    //   1657: aload_1
    //   1658: invokestatic 624	com/google/android/gms/measurement/internal/v:a	(Ljava/lang/String;)Ljava/lang/Object;
    //   1661: aload_0
    //   1662: invokevirtual 89	com/google/android/gms/measurement/internal/wa:d	()Lcom/google/android/gms/measurement/internal/t;
    //   1665: aload 14
    //   1667: invokevirtual 94	com/google/android/gms/measurement/internal/t:a	(Ljava/lang/String;)Ljava/lang/String;
    //   1670: invokevirtual 176	com/google/android/gms/measurement/internal/x:a	(Ljava/lang/String;Ljava/lang/Object;Ljava/lang/Object;)V
    //   1673: new 626	com/google/android/gms/measurement/internal/g
    //   1676: dup
    //   1677: aload_1
    //   1678: aload 21
    //   1680: getfield 546	SG:e	Ljava/lang/String;
    //   1683: lconst_1
    //   1684: lconst_1
    //   1685: aload 21
    //   1687: getfield 629	SG:f	Ljava/lang/Long;
    //   1690: invokevirtual 199	java/lang/Long:longValue	()J
    //   1693: lconst_0
    //   1694: aconst_null
    //   1695: aconst_null
    //   1696: aconst_null
    //   1697: aconst_null
    //   1698: invokespecial 632	com/google/android/gms/measurement/internal/g:<init>	(Ljava/lang/String;Ljava/lang/String;JJJJLjava/lang/Long;Ljava/lang/Long;Ljava/lang/Long;Ljava/lang/Boolean;)V
    //   1701: astore 25
    //   1703: goto +66 -> 1769
    //   1706: new 626	com/google/android/gms/measurement/internal/g
    //   1709: dup
    //   1710: aload 22
    //   1712: getfield 634	com/google/android/gms/measurement/internal/g:a	Ljava/lang/String;
    //   1715: aload 22
    //   1717: getfield 636	com/google/android/gms/measurement/internal/g:b	Ljava/lang/String;
    //   1720: aload 22
    //   1722: getfield 638	com/google/android/gms/measurement/internal/g:c	J
    //   1725: lconst_1
    //   1726: ladd
    //   1727: aload 22
    //   1729: getfield 640	com/google/android/gms/measurement/internal/g:d	J
    //   1732: lconst_1
    //   1733: ladd
    //   1734: aload 22
    //   1736: getfield 642	com/google/android/gms/measurement/internal/g:e	J
    //   1739: aload 22
    //   1741: getfield 644	com/google/android/gms/measurement/internal/g:f	J
    //   1744: aload 22
    //   1746: getfield 646	com/google/android/gms/measurement/internal/g:g	Ljava/lang/Long;
    //   1749: aload 22
    //   1751: getfield 648	com/google/android/gms/measurement/internal/g:h	Ljava/lang/Long;
    //   1754: aload 22
    //   1756: getfield 651	com/google/android/gms/measurement/internal/g:i	Ljava/lang/Long;
    //   1759: aload 22
    //   1761: getfield 653	com/google/android/gms/measurement/internal/g:j	Ljava/lang/Boolean;
    //   1764: invokespecial 632	com/google/android/gms/measurement/internal/g:<init>	(Ljava/lang/String;Ljava/lang/String;JJJJLjava/lang/Long;Ljava/lang/Long;Ljava/lang/Long;Ljava/lang/Boolean;)V
    //   1767: astore 25
    //   1769: aload 17
    //   1771: astore 27
    //   1773: aload 18
    //   1775: astore 26
    //   1777: aload 9
    //   1779: astore 22
    //   1781: aload 8
    //   1783: astore 17
    //   1785: aload 21
    //   1787: astore 34
    //   1789: aload 4
    //   1791: astore 28
    //   1793: aload_0
    //   1794: invokevirtual 465	com/google/android/gms/measurement/internal/Vb:o	()Lcom/google/android/gms/measurement/internal/zc;
    //   1797: aload 25
    //   1799: invokevirtual 656	com/google/android/gms/measurement/internal/zc:a	(Lcom/google/android/gms/measurement/internal/g;)V
    //   1802: aload 25
    //   1804: getfield 638	com/google/android/gms/measurement/internal/g:c	J
    //   1807: lstore 32
    //   1809: aload 7
    //   1811: aload 14
    //   1813: invokeinterface 191 2 0
    //   1818: checkcast 146	java/util/Map
    //   1821: astore 9
    //   1823: aload 9
    //   1825: astore 4
    //   1827: aload 9
    //   1829: ifnonnull +46 -> 1875
    //   1832: aload_0
    //   1833: invokevirtual 465	com/google/android/gms/measurement/internal/Vb:o	()Lcom/google/android/gms/measurement/internal/zc;
    //   1836: aload 5
    //   1838: aload 14
    //   1840: invokevirtual 659	com/google/android/gms/measurement/internal/zc:g	(Ljava/lang/String;Ljava/lang/String;)Ljava/util/Map;
    //   1843: astore 9
    //   1845: aload 9
    //   1847: astore 4
    //   1849: aload 9
    //   1851: ifnonnull +12 -> 1863
    //   1854: new 107	gd
    //   1857: dup
    //   1858: invokespecial 108	gd:<init>	()V
    //   1861: astore 4
    //   1863: aload 7
    //   1865: aload 14
    //   1867: aload 4
    //   1869: invokeinterface 150 3 0
    //   1874: pop
    //   1875: aload 4
    //   1877: astore 25
    //   1879: aload 25
    //   1881: invokeinterface 402 1 0
    //   1886: invokeinterface 403 1 0
    //   1891: astore 5
    //   1893: aload 27
    //   1895: astore 18
    //   1897: aload 6
    //   1899: astore 9
    //   1901: aload 26
    //   1903: astore 8
    //   1905: aload 22
    //   1907: astore 6
    //   1909: aload 16
    //   1911: astore 4
    //   1913: aload 17
    //   1915: astore 21
    //   1917: aload 5
    //   1919: astore 27
    //   1921: aload 25
    //   1923: astore 17
    //   1925: aload 7
    //   1927: astore 22
    //   1929: aload 28
    //   1931: astore 16
    //   1933: aload 14
    //   1935: astore 35
    //   1937: aload 27
    //   1939: invokeinterface 119 1 0
    //   1944: ifeq +1024 -> 2968
    //   1947: aload 27
    //   1949: invokeinterface 123 1 0
    //   1954: checkcast 405	java/lang/Integer
    //   1957: invokevirtual 408	java/lang/Integer:intValue	()I
    //   1960: istore 36
    //   1962: aload 10
    //   1964: iload 36
    //   1966: invokestatic 421	java/lang/Integer:valueOf	(I)Ljava/lang/Integer;
    //   1969: invokeinterface 132 2 0
    //   1974: ifeq +23 -> 1997
    //   1977: aload_0
    //   1978: invokevirtual 77	com/google/android/gms/measurement/internal/wa:c	()Lcom/google/android/gms/measurement/internal/v;
    //   1981: invokevirtual 229	com/google/android/gms/measurement/internal/v:A	()Lcom/google/android/gms/measurement/internal/x;
    //   1984: aload 8
    //   1986: iload 36
    //   1988: invokestatic 421	java/lang/Integer:valueOf	(I)Ljava/lang/Integer;
    //   1991: invokevirtual 99	com/google/android/gms/measurement/internal/x:a	(Ljava/lang/String;Ljava/lang/Object;)V
    //   1994: goto -57 -> 1937
    //   1997: aload 8
    //   1999: astore 37
    //   2001: aload 9
    //   2003: astore 38
    //   2005: aload 38
    //   2007: iload 36
    //   2009: invokestatic 421	java/lang/Integer:valueOf	(I)Ljava/lang/Integer;
    //   2012: invokeinterface 191 2 0
    //   2017: checkcast 474	java/util/BitSet
    //   2020: astore 7
    //   2022: aload 6
    //   2024: astore 39
    //   2026: aload 39
    //   2028: iload 36
    //   2030: invokestatic 421	java/lang/Integer:valueOf	(I)Ljava/lang/Integer;
    //   2033: invokeinterface 191 2 0
    //   2038: checkcast 474	java/util/BitSet
    //   2041: astore 6
    //   2043: iload 12
    //   2045: ifeq +40 -> 2085
    //   2048: aload 16
    //   2050: iload 36
    //   2052: invokestatic 421	java/lang/Integer:valueOf	(I)Ljava/lang/Integer;
    //   2055: invokeinterface 191 2 0
    //   2060: checkcast 146	java/util/Map
    //   2063: astore 9
    //   2065: aload 4
    //   2067: iload 36
    //   2069: invokestatic 421	java/lang/Integer:valueOf	(I)Ljava/lang/Integer;
    //   2072: invokeinterface 191 2 0
    //   2077: checkcast 146	java/util/Map
    //   2080: astore 8
    //   2082: goto +9 -> 2091
    //   2085: aconst_null
    //   2086: astore 9
    //   2088: aconst_null
    //   2089: astore 8
    //   2091: aload 4
    //   2093: astore 26
    //   2095: aload 21
    //   2097: iload 36
    //   2099: invokestatic 421	java/lang/Integer:valueOf	(I)Ljava/lang/Integer;
    //   2102: invokeinterface 191 2 0
    //   2107: checkcast 507	yG
    //   2110: ifnonnull +156 -> 2266
    //   2113: invokestatic 511	yG:u	()LyG$a;
    //   2116: astore 4
    //   2118: aload 4
    //   2120: iconst_1
    //   2121: invokevirtual 516	yG$a:a	(Z)LyG$a;
    //   2124: pop
    //   2125: aload 21
    //   2127: iload 36
    //   2129: invokestatic 421	java/lang/Integer:valueOf	(I)Ljava/lang/Integer;
    //   2132: aload 4
    //   2134: invokevirtual 430	kI$a:J	()LTI;
    //   2137: checkcast 507	yG
    //   2140: invokeinterface 150 3 0
    //   2145: pop
    //   2146: new 474	java/util/BitSet
    //   2149: dup
    //   2150: invokespecial 488	java/util/BitSet:<init>	()V
    //   2153: astore 4
    //   2155: aload 38
    //   2157: iload 36
    //   2159: invokestatic 421	java/lang/Integer:valueOf	(I)Ljava/lang/Integer;
    //   2162: aload 4
    //   2164: invokeinterface 150 3 0
    //   2169: pop
    //   2170: new 474	java/util/BitSet
    //   2173: dup
    //   2174: invokespecial 488	java/util/BitSet:<init>	()V
    //   2177: astore 14
    //   2179: aload 39
    //   2181: iload 36
    //   2183: invokestatic 421	java/lang/Integer:valueOf	(I)Ljava/lang/Integer;
    //   2186: aload 14
    //   2188: invokeinterface 150 3 0
    //   2193: pop
    //   2194: aload 14
    //   2196: astore 6
    //   2198: aload 4
    //   2200: astore 7
    //   2202: iload 12
    //   2204: ifeq +62 -> 2266
    //   2207: new 107	gd
    //   2210: dup
    //   2211: invokespecial 108	gd:<init>	()V
    //   2214: astore 25
    //   2216: aload 16
    //   2218: iload 36
    //   2220: invokestatic 421	java/lang/Integer:valueOf	(I)Ljava/lang/Integer;
    //   2223: aload 25
    //   2225: invokeinterface 150 3 0
    //   2230: pop
    //   2231: new 107	gd
    //   2234: dup
    //   2235: invokespecial 108	gd:<init>	()V
    //   2238: astore 5
    //   2240: aload 26
    //   2242: iload 36
    //   2244: invokestatic 421	java/lang/Integer:valueOf	(I)Ljava/lang/Integer;
    //   2247: aload 5
    //   2249: invokeinterface 150 3 0
    //   2254: pop
    //   2255: aload 14
    //   2257: astore 6
    //   2259: aload 4
    //   2261: astore 8
    //   2263: goto +15 -> 2278
    //   2266: aload 9
    //   2268: astore 25
    //   2270: aload 8
    //   2272: astore 5
    //   2274: aload 7
    //   2276: astore 8
    //   2278: aload 17
    //   2280: iload 36
    //   2282: invokestatic 421	java/lang/Integer:valueOf	(I)Ljava/lang/Integer;
    //   2285: invokeinterface 191 2 0
    //   2290: checkcast 110	java/util/List
    //   2293: invokeinterface 114 1 0
    //   2298: astore 40
    //   2300: aload 18
    //   2302: astore 14
    //   2304: aload 10
    //   2306: astore 28
    //   2308: aload 34
    //   2310: astore 4
    //   2312: aload 38
    //   2314: astore 10
    //   2316: aload 37
    //   2318: astore 9
    //   2320: aload 39
    //   2322: astore 18
    //   2324: aload 35
    //   2326: astore 7
    //   2328: aload 40
    //   2330: invokeinterface 119 1 0
    //   2335: ifeq +598 -> 2933
    //   2338: aload 40
    //   2340: invokeinterface 123 1 0
    //   2345: checkcast 34	KG
    //   2348: astore 37
    //   2350: aload_0
    //   2351: invokevirtual 77	com/google/android/gms/measurement/internal/wa:c	()Lcom/google/android/gms/measurement/internal/v;
    //   2354: iconst_2
    //   2355: invokevirtual 662	com/google/android/gms/measurement/internal/v:a	(I)Z
    //   2358: ifeq +62 -> 2420
    //   2361: aload_0
    //   2362: invokevirtual 77	com/google/android/gms/measurement/internal/wa:c	()Lcom/google/android/gms/measurement/internal/v;
    //   2365: invokevirtual 229	com/google/android/gms/measurement/internal/v:A	()Lcom/google/android/gms/measurement/internal/x;
    //   2368: ldc_w 664
    //   2371: iload 36
    //   2373: invokestatic 421	java/lang/Integer:valueOf	(I)Ljava/lang/Integer;
    //   2376: aload 37
    //   2378: getfield 667	KG:d	Ljava/lang/Integer;
    //   2381: aload_0
    //   2382: invokevirtual 89	com/google/android/gms/measurement/internal/wa:d	()Lcom/google/android/gms/measurement/internal/t;
    //   2385: aload 37
    //   2387: getfield 668	KG:e	Ljava/lang/String;
    //   2390: invokevirtual 94	com/google/android/gms/measurement/internal/t:a	(Ljava/lang/String;)Ljava/lang/String;
    //   2393: invokevirtual 671	com/google/android/gms/measurement/internal/x:a	(Ljava/lang/String;Ljava/lang/Object;Ljava/lang/Object;Ljava/lang/Object;)V
    //   2396: aload_0
    //   2397: invokevirtual 77	com/google/android/gms/measurement/internal/wa:c	()Lcom/google/android/gms/measurement/internal/v;
    //   2400: invokevirtual 229	com/google/android/gms/measurement/internal/v:A	()Lcom/google/android/gms/measurement/internal/x;
    //   2403: aload 14
    //   2405: aload_0
    //   2406: invokevirtual 556	com/google/android/gms/measurement/internal/Vb:l	()Lcom/google/android/gms/measurement/internal/cc;
    //   2409: aload 37
    //   2411: invokevirtual 674	com/google/android/gms/measurement/internal/cc:a	(LKG;)Ljava/lang/String;
    //   2414: invokevirtual 99	com/google/android/gms/measurement/internal/x:a	(Ljava/lang/String;Ljava/lang/Object;)V
    //   2417: goto +3 -> 2420
    //   2420: aload 37
    //   2422: getfield 667	KG:d	Ljava/lang/Integer;
    //   2425: astore 35
    //   2427: aload 35
    //   2429: ifnull +476 -> 2905
    //   2432: aload 35
    //   2434: invokevirtual 408	java/lang/Integer:intValue	()I
    //   2437: sipush 256
    //   2440: if_icmple +6 -> 2446
    //   2443: goto +462 -> 2905
    //   2446: iload 12
    //   2448: ifeq +303 -> 2751
    //   2451: aload 37
    //   2453: ifnull +29 -> 2482
    //   2456: aload 37
    //   2458: getfield 676	KG:i	Ljava/lang/Boolean;
    //   2461: astore 35
    //   2463: aload 35
    //   2465: ifnull +17 -> 2482
    //   2468: aload 35
    //   2470: invokevirtual 50	java/lang/Boolean:booleanValue	()Z
    //   2473: ifeq +9 -> 2482
    //   2476: iconst_1
    //   2477: istore 24
    //   2479: goto +6 -> 2485
    //   2482: iconst_0
    //   2483: istore 24
    //   2485: aload 37
    //   2487: ifnull +29 -> 2516
    //   2490: aload 37
    //   2492: getfield 677	KG:j	Ljava/lang/Boolean;
    //   2495: astore 35
    //   2497: aload 35
    //   2499: ifnull +17 -> 2516
    //   2502: aload 35
    //   2504: invokevirtual 50	java/lang/Boolean:booleanValue	()Z
    //   2507: ifeq +9 -> 2516
    //   2510: iconst_1
    //   2511: istore 31
    //   2513: goto +6 -> 2519
    //   2516: iconst_0
    //   2517: istore 31
    //   2519: aload 8
    //   2521: aload 37
    //   2523: getfield 667	KG:d	Ljava/lang/Integer;
    //   2526: invokevirtual 408	java/lang/Integer:intValue	()I
    //   2529: invokevirtual 679	java/util/BitSet:get	(I)Z
    //   2532: ifeq +39 -> 2571
    //   2535: iload 24
    //   2537: ifne +34 -> 2571
    //   2540: iload 31
    //   2542: ifne +29 -> 2571
    //   2545: aload_0
    //   2546: invokevirtual 77	com/google/android/gms/measurement/internal/wa:c	()Lcom/google/android/gms/measurement/internal/v;
    //   2549: invokevirtual 229	com/google/android/gms/measurement/internal/v:A	()Lcom/google/android/gms/measurement/internal/x;
    //   2552: ldc_w 681
    //   2555: iload 36
    //   2557: invokestatic 421	java/lang/Integer:valueOf	(I)Ljava/lang/Integer;
    //   2560: aload 37
    //   2562: getfield 667	KG:d	Ljava/lang/Integer;
    //   2565: invokevirtual 176	com/google/android/gms/measurement/internal/x:a	(Ljava/lang/String;Ljava/lang/Object;Ljava/lang/Object;)V
    //   2568: goto -240 -> 2328
    //   2571: aload 4
    //   2573: astore 34
    //   2575: aload_0
    //   2576: aload 37
    //   2578: aload 7
    //   2580: aload 20
    //   2582: lload 32
    //   2584: invokespecial 683	com/google/android/gms/measurement/internal/rc:a	(LKG;Ljava/lang/String;Ljava/util/List;J)Ljava/lang/Boolean;
    //   2587: astore 39
    //   2589: aload_0
    //   2590: invokevirtual 77	com/google/android/gms/measurement/internal/wa:c	()Lcom/google/android/gms/measurement/internal/v;
    //   2593: invokevirtual 229	com/google/android/gms/measurement/internal/v:A	()Lcom/google/android/gms/measurement/internal/x;
    //   2596: astore 38
    //   2598: aload 39
    //   2600: ifnonnull +11 -> 2611
    //   2603: ldc_w 685
    //   2606: astore 35
    //   2608: goto +7 -> 2615
    //   2611: aload 39
    //   2613: astore 35
    //   2615: aload 38
    //   2617: ldc_w 687
    //   2620: aload 35
    //   2622: invokevirtual 99	com/google/android/gms/measurement/internal/x:a	(Ljava/lang/String;Ljava/lang/Object;)V
    //   2625: aload 39
    //   2627: ifnonnull +19 -> 2646
    //   2630: aload 28
    //   2632: iload 36
    //   2634: invokestatic 421	java/lang/Integer:valueOf	(I)Ljava/lang/Integer;
    //   2637: invokeinterface 105 2 0
    //   2642: pop
    //   2643: goto +151 -> 2794
    //   2646: aload 6
    //   2648: aload 37
    //   2650: getfield 667	KG:d	Ljava/lang/Integer;
    //   2653: invokevirtual 408	java/lang/Integer:intValue	()I
    //   2656: invokevirtual 500	java/util/BitSet:set	(I)V
    //   2659: aload 39
    //   2661: invokevirtual 50	java/lang/Boolean:booleanValue	()Z
    //   2664: ifeq +130 -> 2794
    //   2667: aload 8
    //   2669: aload 37
    //   2671: getfield 667	KG:d	Ljava/lang/Integer;
    //   2674: invokevirtual 408	java/lang/Integer:intValue	()I
    //   2677: invokevirtual 500	java/util/BitSet:set	(I)V
    //   2680: iload 24
    //   2682: ifne +8 -> 2690
    //   2685: iload 31
    //   2687: ifeq +107 -> 2794
    //   2690: aload 34
    //   2692: getfield 629	SG:f	Ljava/lang/Long;
    //   2695: ifnull +99 -> 2794
    //   2698: iload 31
    //   2700: ifeq +27 -> 2727
    //   2703: aload 5
    //   2705: aload 37
    //   2707: getfield 667	KG:d	Ljava/lang/Integer;
    //   2710: invokevirtual 408	java/lang/Integer:intValue	()I
    //   2713: aload 34
    //   2715: getfield 629	SG:f	Ljava/lang/Long;
    //   2718: invokevirtual 199	java/lang/Long:longValue	()J
    //   2721: invokestatic 689	com/google/android/gms/measurement/internal/rc:b	(Ljava/util/Map;IJ)V
    //   2724: goto +70 -> 2794
    //   2727: aload 25
    //   2729: aload 37
    //   2731: getfield 667	KG:d	Ljava/lang/Integer;
    //   2734: invokevirtual 408	java/lang/Integer:intValue	()I
    //   2737: aload 34
    //   2739: getfield 629	SG:f	Ljava/lang/Long;
    //   2742: invokevirtual 199	java/lang/Long:longValue	()J
    //   2745: invokestatic 691	com/google/android/gms/measurement/internal/rc:a	(Ljava/util/Map;IJ)V
    //   2748: goto +46 -> 2794
    //   2751: aload 8
    //   2753: astore 34
    //   2755: aload 34
    //   2757: aload 37
    //   2759: getfield 667	KG:d	Ljava/lang/Integer;
    //   2762: invokevirtual 408	java/lang/Integer:intValue	()I
    //   2765: invokevirtual 679	java/util/BitSet:get	(I)Z
    //   2768: ifeq +29 -> 2797
    //   2771: aload_0
    //   2772: invokevirtual 77	com/google/android/gms/measurement/internal/wa:c	()Lcom/google/android/gms/measurement/internal/v;
    //   2775: invokevirtual 229	com/google/android/gms/measurement/internal/v:A	()Lcom/google/android/gms/measurement/internal/x;
    //   2778: ldc_w 693
    //   2781: iload 36
    //   2783: invokestatic 421	java/lang/Integer:valueOf	(I)Ljava/lang/Integer;
    //   2786: aload 37
    //   2788: getfield 667	KG:d	Ljava/lang/Integer;
    //   2791: invokevirtual 176	com/google/android/gms/measurement/internal/x:a	(Ljava/lang/String;Ljava/lang/Object;Ljava/lang/Object;)V
    //   2794: goto +136 -> 2930
    //   2797: aload_0
    //   2798: aload 37
    //   2800: aload 7
    //   2802: aload 20
    //   2804: lload 32
    //   2806: invokespecial 683	com/google/android/gms/measurement/internal/rc:a	(LKG;Ljava/lang/String;Ljava/util/List;J)Ljava/lang/Boolean;
    //   2809: astore 39
    //   2811: aload_0
    //   2812: invokevirtual 77	com/google/android/gms/measurement/internal/wa:c	()Lcom/google/android/gms/measurement/internal/v;
    //   2815: invokevirtual 229	com/google/android/gms/measurement/internal/v:A	()Lcom/google/android/gms/measurement/internal/x;
    //   2818: astore 38
    //   2820: aload 39
    //   2822: ifnonnull +11 -> 2833
    //   2825: ldc_w 685
    //   2828: astore 35
    //   2830: goto +7 -> 2837
    //   2833: aload 39
    //   2835: astore 35
    //   2837: aload 38
    //   2839: ldc_w 687
    //   2842: aload 35
    //   2844: invokevirtual 99	com/google/android/gms/measurement/internal/x:a	(Ljava/lang/String;Ljava/lang/Object;)V
    //   2847: aload 39
    //   2849: ifnonnull +19 -> 2868
    //   2852: aload 28
    //   2854: iload 36
    //   2856: invokestatic 421	java/lang/Integer:valueOf	(I)Ljava/lang/Integer;
    //   2859: invokeinterface 105 2 0
    //   2864: pop
    //   2865: goto +65 -> 2930
    //   2868: aload 6
    //   2870: aload 37
    //   2872: getfield 667	KG:d	Ljava/lang/Integer;
    //   2875: invokevirtual 408	java/lang/Integer:intValue	()I
    //   2878: invokevirtual 500	java/util/BitSet:set	(I)V
    //   2881: aload 39
    //   2883: invokevirtual 50	java/lang/Boolean:booleanValue	()Z
    //   2886: ifeq +44 -> 2930
    //   2889: aload 34
    //   2891: aload 37
    //   2893: getfield 667	KG:d	Ljava/lang/Integer;
    //   2896: invokevirtual 408	java/lang/Integer:intValue	()I
    //   2899: invokevirtual 500	java/util/BitSet:set	(I)V
    //   2902: goto +28 -> 2930
    //   2905: aload_0
    //   2906: invokevirtual 77	com/google/android/gms/measurement/internal/wa:c	()Lcom/google/android/gms/measurement/internal/v;
    //   2909: invokevirtual 83	com/google/android/gms/measurement/internal/v:v	()Lcom/google/android/gms/measurement/internal/x;
    //   2912: ldc_w 695
    //   2915: aload_1
    //   2916: invokestatic 624	com/google/android/gms/measurement/internal/v:a	(Ljava/lang/String;)Ljava/lang/Object;
    //   2919: aload 37
    //   2921: getfield 667	KG:d	Ljava/lang/Integer;
    //   2924: invokestatic 698	java/lang/String:valueOf	(Ljava/lang/Object;)Ljava/lang/String;
    //   2927: invokevirtual 176	com/google/android/gms/measurement/internal/x:a	(Ljava/lang/String;Ljava/lang/Object;Ljava/lang/Object;)V
    //   2930: goto -602 -> 2328
    //   2933: aload 18
    //   2935: astore 6
    //   2937: aload 9
    //   2939: astore 8
    //   2941: aload 10
    //   2943: astore 9
    //   2945: aload 7
    //   2947: astore 35
    //   2949: aload 28
    //   2951: astore 10
    //   2953: aload 4
    //   2955: astore 34
    //   2957: aload 26
    //   2959: astore 4
    //   2961: aload 14
    //   2963: astore 18
    //   2965: goto -1028 -> 1937
    //   2968: aload 10
    //   2970: astore 7
    //   2972: aload 22
    //   2974: astore 17
    //   2976: aload 6
    //   2978: astore 10
    //   2980: aload 15
    //   2982: astore 14
    //   2984: aload 11
    //   2986: astore 15
    //   2988: aload 4
    //   2990: astore 6
    //   2992: aload 21
    //   2994: astore 11
    //   2996: aload 7
    //   2998: astore 4
    //   3000: aload 14
    //   3002: astore 7
    //   3004: iinc 19 1
    //   3007: aload 11
    //   3009: astore 21
    //   3011: aload 16
    //   3013: astore 14
    //   3015: aload 6
    //   3017: astore 16
    //   3019: aload 9
    //   3021: astore 6
    //   3023: aload 18
    //   3025: astore 20
    //   3027: aload 10
    //   3029: astore 9
    //   3031: aload 4
    //   3033: astore 10
    //   3035: aload 7
    //   3037: astore 11
    //   3039: aload 17
    //   3041: astore 7
    //   3043: aload 8
    //   3045: astore 18
    //   3047: aload 20
    //   3049: astore 17
    //   3051: aload 21
    //   3053: astore 8
    //   3055: aload 14
    //   3057: astore 4
    //   3059: goto -2253 -> 806
    //   3062: aload 25
    //   3064: astore 9
    //   3066: aload 27
    //   3068: astore 11
    //   3070: aload 28
    //   3072: astore_2
    //   3073: aload 22
    //   3075: astore 6
    //   3077: aload 20
    //   3079: astore 18
    //   3081: aload 14
    //   3083: astore 4
    //   3085: aload_3
    //   3086: astore 14
    //   3088: aload_2
    //   3089: astore 8
    //   3091: aload 4
    //   3093: astore 16
    //   3095: aload 9
    //   3097: astore 10
    //   3099: aload 18
    //   3101: astore 15
    //   3103: aload 6
    //   3105: astore 17
    //   3107: aload 14
    //   3109: ifnull +1277 -> 4386
    //   3112: new 107	gd
    //   3115: dup
    //   3116: invokespecial 108	gd:<init>	()V
    //   3119: astore 7
    //   3121: aload 14
    //   3123: arraylength
    //   3124: istore 23
    //   3126: iconst_0
    //   3127: istore 24
    //   3129: aload 26
    //   3131: astore 14
    //   3133: aload_2
    //   3134: astore 8
    //   3136: aload 4
    //   3138: astore 16
    //   3140: aload 9
    //   3142: astore 10
    //   3144: aload 18
    //   3146: astore 15
    //   3148: aload 6
    //   3150: astore 17
    //   3152: iload 24
    //   3154: iload 23
    //   3156: if_icmpge +1230 -> 4386
    //   3159: aload_3
    //   3160: iload 24
    //   3162: aaload
    //   3163: astore 25
    //   3165: aload 7
    //   3167: aload 25
    //   3169: invokevirtual 246	FG:m	()Ljava/lang/String;
    //   3172: invokeinterface 191 2 0
    //   3177: checkcast 146	java/util/Map
    //   3180: astore 15
    //   3182: aload 15
    //   3184: ifnonnull +54 -> 3238
    //   3187: aload_0
    //   3188: invokevirtual 465	com/google/android/gms/measurement/internal/Vb:o	()Lcom/google/android/gms/measurement/internal/zc;
    //   3191: aload_1
    //   3192: aload 25
    //   3194: invokevirtual 246	FG:m	()Ljava/lang/String;
    //   3197: invokevirtual 700	com/google/android/gms/measurement/internal/zc:h	(Ljava/lang/String;Ljava/lang/String;)Ljava/util/Map;
    //   3200: astore 10
    //   3202: aload 10
    //   3204: astore 15
    //   3206: aload 10
    //   3208: ifnonnull +12 -> 3220
    //   3211: new 107	gd
    //   3214: dup
    //   3215: invokespecial 108	gd:<init>	()V
    //   3218: astore 15
    //   3220: aload 7
    //   3222: aload 25
    //   3224: invokevirtual 246	FG:m	()Ljava/lang/String;
    //   3227: aload 15
    //   3229: invokeinterface 150 3 0
    //   3234: pop
    //   3235: goto +3 -> 3238
    //   3238: aload 15
    //   3240: invokeinterface 402 1 0
    //   3245: invokeinterface 403 1 0
    //   3250: astore 17
    //   3252: aload 14
    //   3254: astore 8
    //   3256: aload 7
    //   3258: astore 10
    //   3260: aload 17
    //   3262: invokeinterface 119 1 0
    //   3267: ifeq +1105 -> 4372
    //   3270: aload 17
    //   3272: invokeinterface 123 1 0
    //   3277: checkcast 405	java/lang/Integer
    //   3280: invokevirtual 408	java/lang/Integer:intValue	()I
    //   3283: istore 31
    //   3285: aload 21
    //   3287: iload 31
    //   3289: invokestatic 421	java/lang/Integer:valueOf	(I)Ljava/lang/Integer;
    //   3292: invokeinterface 132 2 0
    //   3297: ifeq +23 -> 3320
    //   3300: aload_0
    //   3301: invokevirtual 77	com/google/android/gms/measurement/internal/wa:c	()Lcom/google/android/gms/measurement/internal/v;
    //   3304: invokevirtual 229	com/google/android/gms/measurement/internal/v:A	()Lcom/google/android/gms/measurement/internal/x;
    //   3307: aload 8
    //   3309: iload 31
    //   3311: invokestatic 421	java/lang/Integer:valueOf	(I)Ljava/lang/Integer;
    //   3314: invokevirtual 99	com/google/android/gms/measurement/internal/x:a	(Ljava/lang/String;Ljava/lang/Object;)V
    //   3317: goto -57 -> 3260
    //   3320: aload 8
    //   3322: astore 28
    //   3324: aload 18
    //   3326: iload 31
    //   3328: invokestatic 421	java/lang/Integer:valueOf	(I)Ljava/lang/Integer;
    //   3331: invokeinterface 191 2 0
    //   3336: checkcast 474	java/util/BitSet
    //   3339: astore 22
    //   3341: aload 6
    //   3343: astore 27
    //   3345: aload 27
    //   3347: iload 31
    //   3349: invokestatic 421	java/lang/Integer:valueOf	(I)Ljava/lang/Integer;
    //   3352: invokeinterface 191 2 0
    //   3357: checkcast 474	java/util/BitSet
    //   3360: astore 7
    //   3362: iload 12
    //   3364: ifeq +40 -> 3404
    //   3367: aload 4
    //   3369: iload 31
    //   3371: invokestatic 421	java/lang/Integer:valueOf	(I)Ljava/lang/Integer;
    //   3374: invokeinterface 191 2 0
    //   3379: checkcast 146	java/util/Map
    //   3382: astore 8
    //   3384: aload 9
    //   3386: iload 31
    //   3388: invokestatic 421	java/lang/Integer:valueOf	(I)Ljava/lang/Integer;
    //   3391: invokeinterface 191 2 0
    //   3396: checkcast 146	java/util/Map
    //   3399: astore 6
    //   3401: goto +9 -> 3410
    //   3404: aconst_null
    //   3405: astore 8
    //   3407: aconst_null
    //   3408: astore 6
    //   3410: aload 10
    //   3412: astore 16
    //   3414: aload 9
    //   3416: astore 10
    //   3418: aload 4
    //   3420: astore 26
    //   3422: aload_2
    //   3423: iload 31
    //   3425: invokestatic 421	java/lang/Integer:valueOf	(I)Ljava/lang/Integer;
    //   3428: invokeinterface 191 2 0
    //   3433: checkcast 507	yG
    //   3436: ifnonnull +154 -> 3590
    //   3439: invokestatic 511	yG:u	()LyG$a;
    //   3442: astore 4
    //   3444: aload 4
    //   3446: iconst_1
    //   3447: invokevirtual 516	yG$a:a	(Z)LyG$a;
    //   3450: pop
    //   3451: aload_2
    //   3452: iload 31
    //   3454: invokestatic 421	java/lang/Integer:valueOf	(I)Ljava/lang/Integer;
    //   3457: aload 4
    //   3459: invokevirtual 430	kI$a:J	()LTI;
    //   3462: checkcast 507	yG
    //   3465: invokeinterface 150 3 0
    //   3470: pop
    //   3471: new 474	java/util/BitSet
    //   3474: dup
    //   3475: invokespecial 488	java/util/BitSet:<init>	()V
    //   3478: astore 22
    //   3480: aload 18
    //   3482: iload 31
    //   3484: invokestatic 421	java/lang/Integer:valueOf	(I)Ljava/lang/Integer;
    //   3487: aload 22
    //   3489: invokeinterface 150 3 0
    //   3494: pop
    //   3495: new 474	java/util/BitSet
    //   3498: dup
    //   3499: invokespecial 488	java/util/BitSet:<init>	()V
    //   3502: astore 7
    //   3504: aload 27
    //   3506: iload 31
    //   3508: invokestatic 421	java/lang/Integer:valueOf	(I)Ljava/lang/Integer;
    //   3511: aload 7
    //   3513: invokeinterface 150 3 0
    //   3518: pop
    //   3519: iload 12
    //   3521: ifeq +54 -> 3575
    //   3524: new 107	gd
    //   3527: dup
    //   3528: invokespecial 108	gd:<init>	()V
    //   3531: astore 8
    //   3533: aload 26
    //   3535: iload 31
    //   3537: invokestatic 421	java/lang/Integer:valueOf	(I)Ljava/lang/Integer;
    //   3540: aload 8
    //   3542: invokeinterface 150 3 0
    //   3547: pop
    //   3548: new 107	gd
    //   3551: dup
    //   3552: invokespecial 108	gd:<init>	()V
    //   3555: astore 4
    //   3557: aload 10
    //   3559: iload 31
    //   3561: invokestatic 421	java/lang/Integer:valueOf	(I)Ljava/lang/Integer;
    //   3564: aload 4
    //   3566: invokeinterface 150 3 0
    //   3571: pop
    //   3572: goto +7 -> 3579
    //   3575: aload 6
    //   3577: astore 4
    //   3579: aload 4
    //   3581: astore 14
    //   3583: aload 8
    //   3585: astore 20
    //   3587: goto +11 -> 3598
    //   3590: aload 8
    //   3592: astore 20
    //   3594: aload 6
    //   3596: astore 14
    //   3598: aload 15
    //   3600: iload 31
    //   3602: invokestatic 421	java/lang/Integer:valueOf	(I)Ljava/lang/Integer;
    //   3605: invokeinterface 191 2 0
    //   3610: checkcast 110	java/util/List
    //   3613: invokeinterface 114 1 0
    //   3618: astore 8
    //   3620: aload 27
    //   3622: astore 4
    //   3624: aload 28
    //   3626: astore 9
    //   3628: aload 8
    //   3630: astore 28
    //   3632: aload 10
    //   3634: astore 8
    //   3636: aload 26
    //   3638: astore 10
    //   3640: aload 28
    //   3642: invokeinterface 119 1 0
    //   3647: ifeq +694 -> 4341
    //   3650: aload 28
    //   3652: invokeinterface 123 1 0
    //   3657: checkcast 238	OG
    //   3660: astore 26
    //   3662: aload_0
    //   3663: invokevirtual 77	com/google/android/gms/measurement/internal/wa:c	()Lcom/google/android/gms/measurement/internal/v;
    //   3666: astore 27
    //   3668: aload 9
    //   3670: astore 6
    //   3672: aload 27
    //   3674: iconst_2
    //   3675: invokevirtual 662	com/google/android/gms/measurement/internal/v:a	(I)Z
    //   3678: ifeq +62 -> 3740
    //   3681: aload_0
    //   3682: invokevirtual 77	com/google/android/gms/measurement/internal/wa:c	()Lcom/google/android/gms/measurement/internal/v;
    //   3685: invokevirtual 229	com/google/android/gms/measurement/internal/v:A	()Lcom/google/android/gms/measurement/internal/x;
    //   3688: ldc_w 702
    //   3691: iload 31
    //   3693: invokestatic 421	java/lang/Integer:valueOf	(I)Ljava/lang/Integer;
    //   3696: aload 26
    //   3698: getfield 703	OG:d	Ljava/lang/Integer;
    //   3701: aload_0
    //   3702: invokevirtual 89	com/google/android/gms/measurement/internal/wa:d	()Lcom/google/android/gms/measurement/internal/t;
    //   3705: aload 26
    //   3707: getfield 704	OG:e	Ljava/lang/String;
    //   3710: invokevirtual 248	com/google/android/gms/measurement/internal/t:c	(Ljava/lang/String;)Ljava/lang/String;
    //   3713: invokevirtual 671	com/google/android/gms/measurement/internal/x:a	(Ljava/lang/String;Ljava/lang/Object;Ljava/lang/Object;Ljava/lang/Object;)V
    //   3716: aload_0
    //   3717: invokevirtual 77	com/google/android/gms/measurement/internal/wa:c	()Lcom/google/android/gms/measurement/internal/v;
    //   3720: invokevirtual 229	com/google/android/gms/measurement/internal/v:A	()Lcom/google/android/gms/measurement/internal/x;
    //   3723: aload 11
    //   3725: aload_0
    //   3726: invokevirtual 556	com/google/android/gms/measurement/internal/Vb:l	()Lcom/google/android/gms/measurement/internal/cc;
    //   3729: aload 26
    //   3731: invokevirtual 707	com/google/android/gms/measurement/internal/cc:a	(LOG;)Ljava/lang/String;
    //   3734: invokevirtual 99	com/google/android/gms/measurement/internal/x:a	(Ljava/lang/String;Ljava/lang/Object;)V
    //   3737: goto +3 -> 3740
    //   3740: aload 8
    //   3742: astore 9
    //   3744: aload 26
    //   3746: getfield 703	OG:d	Ljava/lang/Integer;
    //   3749: astore 8
    //   3751: aload 8
    //   3753: ifnull +523 -> 4276
    //   3756: aload 8
    //   3758: invokevirtual 408	java/lang/Integer:intValue	()I
    //   3761: sipush 256
    //   3764: if_icmple +6 -> 3770
    //   3767: goto +509 -> 4276
    //   3770: iload 12
    //   3772: ifeq +335 -> 4107
    //   3775: aload 26
    //   3777: invokestatic 709	com/google/android/gms/measurement/internal/rc:a	(LOG;)Z
    //   3780: istore 41
    //   3782: aload 26
    //   3784: ifnull +29 -> 3813
    //   3787: aload 26
    //   3789: getfield 711	OG:h	Ljava/lang/Boolean;
    //   3792: astore 8
    //   3794: aload 8
    //   3796: ifnull +17 -> 3813
    //   3799: aload 8
    //   3801: invokevirtual 50	java/lang/Boolean:booleanValue	()Z
    //   3804: ifeq +9 -> 3813
    //   3807: iconst_1
    //   3808: istore 19
    //   3810: goto +6 -> 3816
    //   3813: iconst_0
    //   3814: istore 19
    //   3816: aload 22
    //   3818: aload 26
    //   3820: getfield 703	OG:d	Ljava/lang/Integer;
    //   3823: invokevirtual 408	java/lang/Integer:intValue	()I
    //   3826: invokevirtual 679	java/util/BitSet:get	(I)Z
    //   3829: ifeq +39 -> 3868
    //   3832: iload 41
    //   3834: ifne +34 -> 3868
    //   3837: iload 19
    //   3839: ifne +29 -> 3868
    //   3842: aload_0
    //   3843: invokevirtual 77	com/google/android/gms/measurement/internal/wa:c	()Lcom/google/android/gms/measurement/internal/v;
    //   3846: invokevirtual 229	com/google/android/gms/measurement/internal/v:A	()Lcom/google/android/gms/measurement/internal/x;
    //   3849: ldc_w 713
    //   3852: iload 31
    //   3854: invokestatic 421	java/lang/Integer:valueOf	(I)Ljava/lang/Integer;
    //   3857: aload 26
    //   3859: getfield 703	OG:d	Ljava/lang/Integer;
    //   3862: invokevirtual 176	com/google/android/gms/measurement/internal/x:a	(Ljava/lang/String;Ljava/lang/Object;Ljava/lang/Object;)V
    //   3865: goto +287 -> 4152
    //   3868: aload_0
    //   3869: aload 26
    //   3871: aload 25
    //   3873: invokespecial 715	com/google/android/gms/measurement/internal/rc:a	(LOG;LFG;)Ljava/lang/Boolean;
    //   3876: astore 27
    //   3878: aload_0
    //   3879: invokevirtual 77	com/google/android/gms/measurement/internal/wa:c	()Lcom/google/android/gms/measurement/internal/v;
    //   3882: invokevirtual 229	com/google/android/gms/measurement/internal/v:A	()Lcom/google/android/gms/measurement/internal/x;
    //   3885: astore 5
    //   3887: aload 27
    //   3889: ifnonnull +11 -> 3900
    //   3892: ldc_w 685
    //   3895: astore 8
    //   3897: goto +7 -> 3904
    //   3900: aload 27
    //   3902: astore 8
    //   3904: aload 5
    //   3906: ldc_w 717
    //   3909: aload 8
    //   3911: invokevirtual 99	com/google/android/gms/measurement/internal/x:a	(Ljava/lang/String;Ljava/lang/Object;)V
    //   3914: aload 27
    //   3916: ifnonnull +22 -> 3938
    //   3919: aload 21
    //   3921: iload 31
    //   3923: invokestatic 421	java/lang/Integer:valueOf	(I)Ljava/lang/Integer;
    //   3926: invokeinterface 105 2 0
    //   3931: pop
    //   3932: aload_2
    //   3933: astore 8
    //   3935: goto +214 -> 4149
    //   3938: aload 7
    //   3940: aload 26
    //   3942: getfield 703	OG:d	Ljava/lang/Integer;
    //   3945: invokevirtual 408	java/lang/Integer:intValue	()I
    //   3948: invokevirtual 500	java/util/BitSet:set	(I)V
    //   3951: iload 13
    //   3953: ifeq +48 -> 4001
    //   3956: aload 22
    //   3958: aload 26
    //   3960: getfield 703	OG:d	Ljava/lang/Integer;
    //   3963: invokevirtual 408	java/lang/Integer:intValue	()I
    //   3966: invokevirtual 679	java/util/BitSet:get	(I)Z
    //   3969: ifeq +11 -> 3980
    //   3972: aload 26
    //   3974: invokestatic 709	com/google/android/gms/measurement/internal/rc:a	(LOG;)Z
    //   3977: ifeq +42 -> 4019
    //   3980: aload 22
    //   3982: aload 26
    //   3984: getfield 703	OG:d	Ljava/lang/Integer;
    //   3987: invokevirtual 408	java/lang/Integer:intValue	()I
    //   3990: aload 27
    //   3992: invokevirtual 50	java/lang/Boolean:booleanValue	()Z
    //   3995: invokevirtual 720	java/util/BitSet:set	(IZ)V
    //   3998: goto +21 -> 4019
    //   4001: aload 22
    //   4003: aload 26
    //   4005: getfield 703	OG:d	Ljava/lang/Integer;
    //   4008: invokevirtual 408	java/lang/Integer:intValue	()I
    //   4011: aload 27
    //   4013: invokevirtual 50	java/lang/Boolean:booleanValue	()Z
    //   4016: invokevirtual 720	java/util/BitSet:set	(IZ)V
    //   4019: aload_2
    //   4020: astore 8
    //   4022: aload 27
    //   4024: invokevirtual 50	java/lang/Boolean:booleanValue	()Z
    //   4027: ifeq +122 -> 4149
    //   4030: iload 41
    //   4032: ifne +11 -> 4043
    //   4035: aload_2
    //   4036: astore 8
    //   4038: iload 19
    //   4040: ifeq +109 -> 4149
    //   4043: aload_2
    //   4044: astore 8
    //   4046: aload 25
    //   4048: invokevirtual 722	FG:u	()Z
    //   4051: ifeq +98 -> 4149
    //   4054: iload 19
    //   4056: ifeq +27 -> 4083
    //   4059: aload 14
    //   4061: aload 26
    //   4063: getfield 703	OG:d	Ljava/lang/Integer;
    //   4066: invokevirtual 408	java/lang/Integer:intValue	()I
    //   4069: aload 25
    //   4071: invokevirtual 724	FG:v	()J
    //   4074: invokestatic 689	com/google/android/gms/measurement/internal/rc:b	(Ljava/util/Map;IJ)V
    //   4077: aload_2
    //   4078: astore 8
    //   4080: goto +69 -> 4149
    //   4083: aload 20
    //   4085: aload 26
    //   4087: getfield 703	OG:d	Ljava/lang/Integer;
    //   4090: invokevirtual 408	java/lang/Integer:intValue	()I
    //   4093: aload 25
    //   4095: invokevirtual 724	FG:v	()J
    //   4098: invokestatic 691	com/google/android/gms/measurement/internal/rc:a	(Ljava/util/Map;IJ)V
    //   4101: aload_2
    //   4102: astore 8
    //   4104: goto +45 -> 4149
    //   4107: aload 22
    //   4109: aload 26
    //   4111: getfield 703	OG:d	Ljava/lang/Integer;
    //   4114: invokevirtual 408	java/lang/Integer:intValue	()I
    //   4117: invokevirtual 679	java/util/BitSet:get	(I)Z
    //   4120: ifeq +43 -> 4163
    //   4123: aload_0
    //   4124: invokevirtual 77	com/google/android/gms/measurement/internal/wa:c	()Lcom/google/android/gms/measurement/internal/v;
    //   4127: invokevirtual 229	com/google/android/gms/measurement/internal/v:A	()Lcom/google/android/gms/measurement/internal/x;
    //   4130: ldc_w 726
    //   4133: iload 31
    //   4135: invokestatic 421	java/lang/Integer:valueOf	(I)Ljava/lang/Integer;
    //   4138: aload 26
    //   4140: getfield 703	OG:d	Ljava/lang/Integer;
    //   4143: invokevirtual 176	com/google/android/gms/measurement/internal/x:a	(Ljava/lang/String;Ljava/lang/Object;Ljava/lang/Object;)V
    //   4146: aload_2
    //   4147: astore 8
    //   4149: aload 8
    //   4151: astore_2
    //   4152: aload 9
    //   4154: astore 8
    //   4156: aload 6
    //   4158: astore 9
    //   4160: goto -520 -> 3640
    //   4163: aload_0
    //   4164: aload 26
    //   4166: aload 25
    //   4168: invokespecial 715	com/google/android/gms/measurement/internal/rc:a	(LOG;LFG;)Ljava/lang/Boolean;
    //   4171: astore 27
    //   4173: aload_0
    //   4174: invokevirtual 77	com/google/android/gms/measurement/internal/wa:c	()Lcom/google/android/gms/measurement/internal/v;
    //   4177: invokevirtual 229	com/google/android/gms/measurement/internal/v:A	()Lcom/google/android/gms/measurement/internal/x;
    //   4180: astore 5
    //   4182: aload 27
    //   4184: ifnonnull +11 -> 4195
    //   4187: ldc_w 685
    //   4190: astore 8
    //   4192: goto +7 -> 4199
    //   4195: aload 27
    //   4197: astore 8
    //   4199: aload 5
    //   4201: ldc_w 717
    //   4204: aload 8
    //   4206: invokevirtual 99	com/google/android/gms/measurement/internal/x:a	(Ljava/lang/String;Ljava/lang/Object;)V
    //   4209: aload 27
    //   4211: ifnonnull +22 -> 4233
    //   4214: aload 21
    //   4216: iload 31
    //   4218: invokestatic 421	java/lang/Integer:valueOf	(I)Ljava/lang/Integer;
    //   4221: invokeinterface 105 2 0
    //   4226: pop
    //   4227: aload_2
    //   4228: astore 8
    //   4230: goto -81 -> 4149
    //   4233: aload 7
    //   4235: aload 26
    //   4237: getfield 703	OG:d	Ljava/lang/Integer;
    //   4240: invokevirtual 408	java/lang/Integer:intValue	()I
    //   4243: invokevirtual 500	java/util/BitSet:set	(I)V
    //   4246: aload_2
    //   4247: astore 8
    //   4249: aload 27
    //   4251: invokevirtual 50	java/lang/Boolean:booleanValue	()Z
    //   4254: ifeq -105 -> 4149
    //   4257: aload 22
    //   4259: aload 26
    //   4261: getfield 703	OG:d	Ljava/lang/Integer;
    //   4264: invokevirtual 408	java/lang/Integer:intValue	()I
    //   4267: invokevirtual 500	java/util/BitSet:set	(I)V
    //   4270: aload_2
    //   4271: astore 8
    //   4273: goto -124 -> 4149
    //   4276: aload_0
    //   4277: invokevirtual 77	com/google/android/gms/measurement/internal/wa:c	()Lcom/google/android/gms/measurement/internal/v;
    //   4280: invokevirtual 83	com/google/android/gms/measurement/internal/v:v	()Lcom/google/android/gms/measurement/internal/x;
    //   4283: ldc_w 728
    //   4286: aload_1
    //   4287: invokestatic 624	com/google/android/gms/measurement/internal/v:a	(Ljava/lang/String;)Ljava/lang/Object;
    //   4290: aload 26
    //   4292: getfield 703	OG:d	Ljava/lang/Integer;
    //   4295: invokestatic 698	java/lang/String:valueOf	(Ljava/lang/Object;)Ljava/lang/String;
    //   4298: invokevirtual 176	com/google/android/gms/measurement/internal/x:a	(Ljava/lang/String;Ljava/lang/Object;Ljava/lang/Object;)V
    //   4301: aload 21
    //   4303: iload 31
    //   4305: invokestatic 421	java/lang/Integer:valueOf	(I)Ljava/lang/Integer;
    //   4308: invokeinterface 105 2 0
    //   4313: pop
    //   4314: aload 16
    //   4316: astore 8
    //   4318: aload 4
    //   4320: astore 16
    //   4322: aload 10
    //   4324: astore 4
    //   4326: aload 8
    //   4328: astore 10
    //   4330: aload 6
    //   4332: astore 8
    //   4334: aload 16
    //   4336: astore 6
    //   4338: goto -1078 -> 3260
    //   4341: aload 16
    //   4343: astore 7
    //   4345: aload 9
    //   4347: astore 16
    //   4349: aload 4
    //   4351: astore 6
    //   4353: aload 10
    //   4355: astore 4
    //   4357: aload 7
    //   4359: astore 10
    //   4361: aload 8
    //   4363: astore 9
    //   4365: aload 16
    //   4367: astore 8
    //   4369: goto -1109 -> 3260
    //   4372: iinc 24 1
    //   4375: aload 10
    //   4377: astore 7
    //   4379: aload 8
    //   4381: astore 14
    //   4383: goto -1250 -> 3133
    //   4386: aload 17
    //   4388: astore 4
    //   4390: aload 15
    //   4392: invokeinterface 397 1 0
    //   4397: anewarray 507	yG
    //   4400: astore 11
    //   4402: aload 15
    //   4404: invokeinterface 402 1 0
    //   4409: invokeinterface 403 1 0
    //   4414: astore_3
    //   4415: iconst_0
    //   4416: istore 23
    //   4418: aload 10
    //   4420: astore 18
    //   4422: aload 8
    //   4424: astore 6
    //   4426: aload 16
    //   4428: astore 10
    //   4430: aload 21
    //   4432: astore_2
    //   4433: aload_3
    //   4434: invokeinterface 119 1 0
    //   4439: ifeq +1009 -> 5448
    //   4442: aload_3
    //   4443: invokeinterface 123 1 0
    //   4448: checkcast 405	java/lang/Integer
    //   4451: invokevirtual 408	java/lang/Integer:intValue	()I
    //   4454: istore 19
    //   4456: aload_2
    //   4457: iload 19
    //   4459: invokestatic 421	java/lang/Integer:valueOf	(I)Ljava/lang/Integer;
    //   4462: invokeinterface 132 2 0
    //   4467: ifne +978 -> 5445
    //   4470: aload 6
    //   4472: iload 19
    //   4474: invokestatic 421	java/lang/Integer:valueOf	(I)Ljava/lang/Integer;
    //   4477: invokeinterface 191 2 0
    //   4482: checkcast 507	yG
    //   4485: astore 9
    //   4487: aload 9
    //   4489: ifnonnull +11 -> 4500
    //   4492: invokestatic 511	yG:u	()LyG$a;
    //   4495: astore 17
    //   4497: goto +13 -> 4510
    //   4500: aload 9
    //   4502: invokevirtual 733	kI:j	()LkI$a;
    //   4505: checkcast 513	yG$a
    //   4508: astore 17
    //   4510: aload 17
    //   4512: iload 19
    //   4514: invokevirtual 736	yG$a:a	(I)LyG$a;
    //   4517: pop
    //   4518: invokestatic 522	DG:u	()LDG$a;
    //   4521: astore 7
    //   4523: aload 7
    //   4525: aload 15
    //   4527: iload 19
    //   4529: invokestatic 421	java/lang/Integer:valueOf	(I)Ljava/lang/Integer;
    //   4532: invokeinterface 191 2 0
    //   4537: checkcast 474	java/util/BitSet
    //   4540: invokestatic 525	com/google/android/gms/measurement/internal/cc:a	(Ljava/util/BitSet;)Ljava/util/List;
    //   4543: invokevirtual 530	DG$a:b	(Ljava/lang/Iterable;)LDG$a;
    //   4546: pop
    //   4547: aload 7
    //   4549: aload 4
    //   4551: iload 19
    //   4553: invokestatic 421	java/lang/Integer:valueOf	(I)Ljava/lang/Integer;
    //   4556: invokeinterface 191 2 0
    //   4561: checkcast 474	java/util/BitSet
    //   4564: invokestatic 525	com/google/android/gms/measurement/internal/cc:a	(Ljava/util/BitSet;)Ljava/util/List;
    //   4567: invokevirtual 532	DG$a:a	(Ljava/lang/Iterable;)LDG$a;
    //   4570: pop
    //   4571: iload 12
    //   4573: ifeq +668 -> 5241
    //   4576: aload 7
    //   4578: aload 10
    //   4580: iload 19
    //   4582: invokestatic 421	java/lang/Integer:valueOf	(I)Ljava/lang/Integer;
    //   4585: invokeinterface 191 2 0
    //   4590: checkcast 146	java/util/Map
    //   4593: invokestatic 534	com/google/android/gms/measurement/internal/rc:a	(Ljava/util/Map;)Ljava/util/List;
    //   4596: invokevirtual 536	DG$a:c	(Ljava/lang/Iterable;)LDG$a;
    //   4599: pop
    //   4600: aload 18
    //   4602: iload 19
    //   4604: invokestatic 421	java/lang/Integer:valueOf	(I)Ljava/lang/Integer;
    //   4607: invokeinterface 191 2 0
    //   4612: checkcast 146	java/util/Map
    //   4615: astore 8
    //   4617: aload 8
    //   4619: ifnonnull +15 -> 4634
    //   4622: invokestatic 741	java/util/Collections:emptyList	()Ljava/util/List;
    //   4625: astore 9
    //   4627: aload 4
    //   4629: astore 8
    //   4631: goto +184 -> 4815
    //   4634: new 312	java/util/ArrayList
    //   4637: dup
    //   4638: aload 8
    //   4640: invokeinterface 397 1 0
    //   4645: invokespecial 398	java/util/ArrayList:<init>	(I)V
    //   4648: astore 16
    //   4650: aload 8
    //   4652: invokeinterface 402 1 0
    //   4657: invokeinterface 403 1 0
    //   4662: astore 14
    //   4664: aload 4
    //   4666: astore 9
    //   4668: aload 8
    //   4670: astore 4
    //   4672: aload 14
    //   4674: invokeinterface 119 1 0
    //   4679: ifeq +125 -> 4804
    //   4682: aload 14
    //   4684: invokeinterface 123 1 0
    //   4689: checkcast 405	java/lang/Integer
    //   4692: astore 8
    //   4694: invokestatic 746	EG:q	()LEG$a;
    //   4697: astore 21
    //   4699: aload 21
    //   4701: aload 8
    //   4703: invokevirtual 408	java/lang/Integer:intValue	()I
    //   4706: invokevirtual 751	EG$a:a	(I)LEG$a;
    //   4709: pop
    //   4710: aload 4
    //   4712: aload 8
    //   4714: invokeinterface 191 2 0
    //   4719: checkcast 110	java/util/List
    //   4722: astore 20
    //   4724: aload 4
    //   4726: astore 8
    //   4728: aload 20
    //   4730: ifnull +53 -> 4783
    //   4733: aload 20
    //   4735: invokestatic 755	java/util/Collections:sort	(Ljava/util/List;)V
    //   4738: aload 20
    //   4740: invokeinterface 114 1 0
    //   4745: astore 20
    //   4747: aload 4
    //   4749: astore 8
    //   4751: aload 20
    //   4753: invokeinterface 119 1 0
    //   4758: ifeq +25 -> 4783
    //   4761: aload 21
    //   4763: aload 20
    //   4765: invokeinterface 123 1 0
    //   4770: checkcast 141	java/lang/Long
    //   4773: invokevirtual 199	java/lang/Long:longValue	()J
    //   4776: invokevirtual 758	EG$a:a	(J)LEG$a;
    //   4779: pop
    //   4780: goto -33 -> 4747
    //   4783: aload 16
    //   4785: aload 21
    //   4787: invokevirtual 430	kI$a:J	()LTI;
    //   4790: checkcast 743	EG
    //   4793: invokevirtual 431	java/util/ArrayList:add	(Ljava/lang/Object;)Z
    //   4796: pop
    //   4797: aload 8
    //   4799: astore 4
    //   4801: goto -129 -> 4672
    //   4804: aload 9
    //   4806: astore 4
    //   4808: aload 16
    //   4810: astore 9
    //   4812: goto -185 -> 4627
    //   4815: iload 13
    //   4817: ifeq +31 -> 4848
    //   4820: aload 17
    //   4822: invokevirtual 760	yG$a:j	()Z
    //   4825: ifeq +23 -> 4848
    //   4828: aload 17
    //   4830: invokevirtual 764	yG$a:k	()LDG;
    //   4833: invokevirtual 766	DG:s	()Ljava/util/List;
    //   4836: astore 4
    //   4838: aload 4
    //   4840: invokeinterface 608 1 0
    //   4845: ifeq +10 -> 4855
    //   4848: aload 10
    //   4850: astore 4
    //   4852: goto +370 -> 5222
    //   4855: new 312	java/util/ArrayList
    //   4858: dup
    //   4859: aload 9
    //   4861: invokespecial 769	java/util/ArrayList:<init>	(Ljava/util/Collection;)V
    //   4864: astore 9
    //   4866: new 107	gd
    //   4869: dup
    //   4870: invokespecial 108	gd:<init>	()V
    //   4873: astore 16
    //   4875: aload 4
    //   4877: invokeinterface 114 1 0
    //   4882: astore 14
    //   4884: aload 14
    //   4886: invokeinterface 119 1 0
    //   4891: ifeq +65 -> 4956
    //   4894: aload 14
    //   4896: invokeinterface 123 1 0
    //   4901: checkcast 743	EG
    //   4904: astore 4
    //   4906: aload 4
    //   4908: invokevirtual 770	EG:n	()Z
    //   4911: ifeq -27 -> 4884
    //   4914: aload 4
    //   4916: invokevirtual 772	EG:p	()I
    //   4919: ifle -35 -> 4884
    //   4922: aload 16
    //   4924: aload 4
    //   4926: invokevirtual 773	EG:m	()I
    //   4929: invokestatic 421	java/lang/Integer:valueOf	(I)Ljava/lang/Integer;
    //   4932: aload 4
    //   4934: aload 4
    //   4936: invokevirtual 772	EG:p	()I
    //   4939: iconst_1
    //   4940: isub
    //   4941: invokevirtual 776	EG:b	(I)J
    //   4944: invokestatic 144	java/lang/Long:valueOf	(J)Ljava/lang/Long;
    //   4947: invokeinterface 150 3 0
    //   4952: pop
    //   4953: goto -69 -> 4884
    //   4956: iconst_0
    //   4957: istore 24
    //   4959: iload 24
    //   4961: aload 9
    //   4963: invokeinterface 323 1 0
    //   4968: if_icmpge +158 -> 5126
    //   4971: aload 9
    //   4973: iload 24
    //   4975: invokeinterface 779 2 0
    //   4980: checkcast 743	EG
    //   4983: astore 14
    //   4985: aload 14
    //   4987: invokevirtual 770	EG:n	()Z
    //   4990: ifeq +16 -> 5006
    //   4993: aload 14
    //   4995: invokevirtual 773	EG:m	()I
    //   4998: invokestatic 421	java/lang/Integer:valueOf	(I)Ljava/lang/Integer;
    //   5001: astore 4
    //   5003: goto +6 -> 5009
    //   5006: aconst_null
    //   5007: astore 4
    //   5009: aload 16
    //   5011: aload 4
    //   5013: invokeinterface 505 2 0
    //   5018: checkcast 141	java/lang/Long
    //   5021: astore 21
    //   5023: aload 21
    //   5025: ifnull +95 -> 5120
    //   5028: new 312	java/util/ArrayList
    //   5031: dup
    //   5032: invokespecial 313	java/util/ArrayList:<init>	()V
    //   5035: astore 4
    //   5037: aload 21
    //   5039: invokevirtual 199	java/lang/Long:longValue	()J
    //   5042: aload 14
    //   5044: iconst_0
    //   5045: invokevirtual 776	EG:b	(I)J
    //   5048: lcmp
    //   5049: ifge +13 -> 5062
    //   5052: aload 4
    //   5054: aload 21
    //   5056: invokeinterface 314 2 0
    //   5061: pop
    //   5062: aload 4
    //   5064: aload 14
    //   5066: invokevirtual 780	EG:o	()Ljava/util/List;
    //   5069: invokeinterface 784 2 0
    //   5074: pop
    //   5075: aload 14
    //   5077: invokevirtual 733	kI:j	()LkI$a;
    //   5080: checkcast 748	EG$a
    //   5083: astore 14
    //   5085: aload 14
    //   5087: invokevirtual 786	EG$a:i	()LEG$a;
    //   5090: pop
    //   5091: aload 14
    //   5093: aload 4
    //   5095: invokevirtual 789	EG$a:a	(Ljava/lang/Iterable;)LEG$a;
    //   5098: pop
    //   5099: aload 9
    //   5101: iload 24
    //   5103: aload 14
    //   5105: invokevirtual 430	kI$a:J	()LTI;
    //   5108: checkcast 743	EG
    //   5111: invokeinterface 792 3 0
    //   5116: pop
    //   5117: goto +3 -> 5120
    //   5120: iinc 24 1
    //   5123: goto -164 -> 4959
    //   5126: aload 10
    //   5128: astore 4
    //   5130: aload 16
    //   5132: invokeinterface 402 1 0
    //   5137: invokeinterface 403 1 0
    //   5142: astore 10
    //   5144: aload 10
    //   5146: invokeinterface 119 1 0
    //   5151: ifeq +71 -> 5222
    //   5154: aload 10
    //   5156: invokeinterface 123 1 0
    //   5161: checkcast 405	java/lang/Integer
    //   5164: astore 14
    //   5166: invokestatic 746	EG:q	()LEG$a;
    //   5169: astore 21
    //   5171: aload 21
    //   5173: aload 14
    //   5175: invokevirtual 408	java/lang/Integer:intValue	()I
    //   5178: invokevirtual 751	EG$a:a	(I)LEG$a;
    //   5181: pop
    //   5182: aload 21
    //   5184: aload 16
    //   5186: aload 14
    //   5188: invokeinterface 191 2 0
    //   5193: checkcast 141	java/lang/Long
    //   5196: invokevirtual 199	java/lang/Long:longValue	()J
    //   5199: invokevirtual 758	EG$a:a	(J)LEG$a;
    //   5202: pop
    //   5203: aload 9
    //   5205: aload 21
    //   5207: invokevirtual 430	kI$a:J	()LTI;
    //   5210: checkcast 743	EG
    //   5213: invokeinterface 314 2 0
    //   5218: pop
    //   5219: goto -75 -> 5144
    //   5222: aload 7
    //   5224: aload 9
    //   5226: invokevirtual 794	DG$a:d	(Ljava/lang/Iterable;)LDG$a;
    //   5229: pop
    //   5230: aload 4
    //   5232: astore 10
    //   5234: aload 8
    //   5236: astore 4
    //   5238: goto +3 -> 5241
    //   5241: aload 17
    //   5243: aload 7
    //   5245: invokevirtual 539	yG$a:a	(LDG$a;)LyG$a;
    //   5248: pop
    //   5249: aload 6
    //   5251: iload 19
    //   5253: invokestatic 421	java/lang/Integer:valueOf	(I)Ljava/lang/Integer;
    //   5256: aload 17
    //   5258: invokevirtual 430	kI$a:J	()LTI;
    //   5261: checkcast 507	yG
    //   5264: invokeinterface 150 3 0
    //   5269: pop
    //   5270: aload 11
    //   5272: iload 23
    //   5274: aload 17
    //   5276: invokevirtual 430	kI$a:J	()LTI;
    //   5279: checkcast 507	yG
    //   5282: aastore
    //   5283: aload_0
    //   5284: invokevirtual 465	com/google/android/gms/measurement/internal/Vb:o	()Lcom/google/android/gms/measurement/internal/zc;
    //   5287: astore 8
    //   5289: aload 17
    //   5291: invokevirtual 796	yG$a:i	()LDG;
    //   5294: astore 9
    //   5296: aload 8
    //   5298: invokevirtual 798	com/google/android/gms/measurement/internal/Wb:r	()V
    //   5301: aload 8
    //   5303: invokevirtual 584	com/google/android/gms/measurement/internal/wa:j	()V
    //   5306: aload_1
    //   5307: invokestatic 444	com/google/android/gms/common/internal/t:b	(Ljava/lang/String;)Ljava/lang/String;
    //   5310: pop
    //   5311: aload 9
    //   5313: invokestatic 274	com/google/android/gms/common/internal/t:a	(Ljava/lang/Object;)Ljava/lang/Object;
    //   5316: pop
    //   5317: aload 9
    //   5319: invokevirtual 803	sH:f	()[B
    //   5322: astore 17
    //   5324: new 805	android/content/ContentValues
    //   5327: dup
    //   5328: invokespecial 806	android/content/ContentValues:<init>	()V
    //   5331: astore 9
    //   5333: aload 9
    //   5335: ldc_w 808
    //   5338: aload_1
    //   5339: invokevirtual 811	android/content/ContentValues:put	(Ljava/lang/String;Ljava/lang/String;)V
    //   5342: aload 9
    //   5344: ldc_w 813
    //   5347: iload 19
    //   5349: invokestatic 421	java/lang/Integer:valueOf	(I)Ljava/lang/Integer;
    //   5352: invokevirtual 816	android/content/ContentValues:put	(Ljava/lang/String;Ljava/lang/Integer;)V
    //   5355: aload 9
    //   5357: ldc_w 818
    //   5360: aload 17
    //   5362: invokevirtual 821	android/content/ContentValues:put	(Ljava/lang/String;[B)V
    //   5365: aload 8
    //   5367: invokevirtual 590	com/google/android/gms/measurement/internal/zc:w	()Landroid/database/sqlite/SQLiteDatabase;
    //   5370: astore 17
    //   5372: aload 17
    //   5374: ldc_w 823
    //   5377: aconst_null
    //   5378: aload 9
    //   5380: iconst_5
    //   5381: invokevirtual 827	android/database/sqlite/SQLiteDatabase:insertWithOnConflict	(Ljava/lang/String;Ljava/lang/String;Landroid/content/ContentValues;I)J
    //   5384: ldc2_w 828
    //   5387: lcmp
    //   5388: ifne +51 -> 5439
    //   5391: aload 8
    //   5393: invokevirtual 77	com/google/android/gms/measurement/internal/wa:c	()Lcom/google/android/gms/measurement/internal/v;
    //   5396: invokevirtual 567	com/google/android/gms/measurement/internal/v:s	()Lcom/google/android/gms/measurement/internal/x;
    //   5399: ldc_w 831
    //   5402: aload_1
    //   5403: invokestatic 624	com/google/android/gms/measurement/internal/v:a	(Ljava/lang/String;)Ljava/lang/Object;
    //   5406: invokevirtual 99	com/google/android/gms/measurement/internal/x:a	(Ljava/lang/String;Ljava/lang/Object;)V
    //   5409: goto +30 -> 5439
    //   5412: astore 9
    //   5414: goto +5 -> 5419
    //   5417: astore 9
    //   5419: aload 8
    //   5421: invokevirtual 77	com/google/android/gms/measurement/internal/wa:c	()Lcom/google/android/gms/measurement/internal/v;
    //   5424: invokevirtual 567	com/google/android/gms/measurement/internal/v:s	()Lcom/google/android/gms/measurement/internal/x;
    //   5427: ldc_w 833
    //   5430: aload_1
    //   5431: invokestatic 624	com/google/android/gms/measurement/internal/v:a	(Ljava/lang/String;)Ljava/lang/Object;
    //   5434: aload 9
    //   5436: invokevirtual 176	com/google/android/gms/measurement/internal/x:a	(Ljava/lang/String;Ljava/lang/Object;Ljava/lang/Object;)V
    //   5439: iinc 23 1
    //   5442: goto -1009 -> 4433
    //   5445: goto -1012 -> 4433
    //   5448: aload 11
    //   5450: iload 23
    //   5452: invokestatic 837	java/util/Arrays:copyOf	([Ljava/lang/Object;I)[Ljava/lang/Object;
    //   5455: checkcast 839	[LyG;
    //   5458: areturn
    // Exception table:
    //   from	to	target	type
    //   1159	1176	1179	android/database/sqlite/SQLiteException
    //   1152	1159	1188	android/database/sqlite/SQLiteException
    //   5372	5409	5412	android/database/sqlite/SQLiteException
    //   5365	5372	5417	android/database/sqlite/SQLiteException
  }
  
  protected final boolean t()
  {
    return false;
  }
}


/* Location:              /Applications/dex2jar/classes-dex2jar.jar!/com/google/android/gms/measurement/internal/rc.class
 * Java compiler version: 6 (50.0)
 * JD-Core Version:       0.7.1
 */