package com.google.android.gms.measurement.internal;

import qK;

final class yb
  implements Runnable
{
  yb(jb paramjb, String paramString1, String paramString2, pc parampc, qK paramqK) {}
  
  /* Error */
  public final void run()
  {
    // Byte code:
    //   0: new 36	java/util/ArrayList
    //   3: dup
    //   4: invokespecial 37	java/util/ArrayList:<init>	()V
    //   7: astore_1
    //   8: aload_1
    //   9: astore_2
    //   10: aload_1
    //   11: astore_3
    //   12: aload_0
    //   13: getfield 19	com/google/android/gms/measurement/internal/yb:e	Lcom/google/android/gms/measurement/internal/jb;
    //   16: invokestatic 42	com/google/android/gms/measurement/internal/jb:d	(Lcom/google/android/gms/measurement/internal/jb;)Lcom/google/android/gms/measurement/internal/n;
    //   19: astore 4
    //   21: aload 4
    //   23: ifnonnull +46 -> 69
    //   26: aload_1
    //   27: astore_2
    //   28: aload_1
    //   29: astore_3
    //   30: aload_0
    //   31: getfield 19	com/google/android/gms/measurement/internal/yb:e	Lcom/google/android/gms/measurement/internal/jb;
    //   34: invokevirtual 45	com/google/android/gms/measurement/internal/jb:c	()Lcom/google/android/gms/measurement/internal/v;
    //   37: invokevirtual 51	com/google/android/gms/measurement/internal/v:s	()Lcom/google/android/gms/measurement/internal/x;
    //   40: ldc 53
    //   42: aload_0
    //   43: getfield 21	com/google/android/gms/measurement/internal/yb:a	Ljava/lang/String;
    //   46: aload_0
    //   47: getfield 23	com/google/android/gms/measurement/internal/yb:b	Ljava/lang/String;
    //   50: invokevirtual 58	com/google/android/gms/measurement/internal/x:a	(Ljava/lang/String;Ljava/lang/Object;Ljava/lang/Object;)V
    //   53: aload_0
    //   54: getfield 19	com/google/android/gms/measurement/internal/yb:e	Lcom/google/android/gms/measurement/internal/jb;
    //   57: invokevirtual 61	com/google/android/gms/measurement/internal/jb:e	()Lcom/google/android/gms/measurement/internal/hc;
    //   60: aload_0
    //   61: getfield 27	com/google/android/gms/measurement/internal/yb:d	LqK;
    //   64: aload_1
    //   65: invokevirtual 66	com/google/android/gms/measurement/internal/hc:a	(LqK;Ljava/util/ArrayList;)V
    //   68: return
    //   69: aload_1
    //   70: astore_2
    //   71: aload_1
    //   72: astore_3
    //   73: aload 4
    //   75: aload_0
    //   76: getfield 21	com/google/android/gms/measurement/internal/yb:a	Ljava/lang/String;
    //   79: aload_0
    //   80: getfield 23	com/google/android/gms/measurement/internal/yb:b	Ljava/lang/String;
    //   83: aload_0
    //   84: getfield 25	com/google/android/gms/measurement/internal/yb:c	Lcom/google/android/gms/measurement/internal/pc;
    //   87: invokeinterface 71 4 0
    //   92: invokestatic 74	com/google/android/gms/measurement/internal/hc:b	(Ljava/util/List;)Ljava/util/ArrayList;
    //   95: astore_1
    //   96: aload_1
    //   97: astore_2
    //   98: aload_1
    //   99: astore_3
    //   100: aload_0
    //   101: getfield 19	com/google/android/gms/measurement/internal/yb:e	Lcom/google/android/gms/measurement/internal/jb;
    //   104: invokestatic 77	com/google/android/gms/measurement/internal/jb:e	(Lcom/google/android/gms/measurement/internal/jb;)V
    //   107: aload_0
    //   108: getfield 19	com/google/android/gms/measurement/internal/yb:e	Lcom/google/android/gms/measurement/internal/jb;
    //   111: invokevirtual 61	com/google/android/gms/measurement/internal/jb:e	()Lcom/google/android/gms/measurement/internal/hc;
    //   114: aload_0
    //   115: getfield 27	com/google/android/gms/measurement/internal/yb:d	LqK;
    //   118: aload_1
    //   119: invokevirtual 66	com/google/android/gms/measurement/internal/hc:a	(LqK;Ljava/util/ArrayList;)V
    //   122: return
    //   123: astore_3
    //   124: goto +46 -> 170
    //   127: astore_1
    //   128: aload_3
    //   129: astore_2
    //   130: aload_0
    //   131: getfield 19	com/google/android/gms/measurement/internal/yb:e	Lcom/google/android/gms/measurement/internal/jb;
    //   134: invokevirtual 45	com/google/android/gms/measurement/internal/jb:c	()Lcom/google/android/gms/measurement/internal/v;
    //   137: invokevirtual 51	com/google/android/gms/measurement/internal/v:s	()Lcom/google/android/gms/measurement/internal/x;
    //   140: ldc 53
    //   142: aload_0
    //   143: getfield 21	com/google/android/gms/measurement/internal/yb:a	Ljava/lang/String;
    //   146: aload_0
    //   147: getfield 23	com/google/android/gms/measurement/internal/yb:b	Ljava/lang/String;
    //   150: aload_1
    //   151: invokevirtual 80	com/google/android/gms/measurement/internal/x:a	(Ljava/lang/String;Ljava/lang/Object;Ljava/lang/Object;Ljava/lang/Object;)V
    //   154: aload_0
    //   155: getfield 19	com/google/android/gms/measurement/internal/yb:e	Lcom/google/android/gms/measurement/internal/jb;
    //   158: invokevirtual 61	com/google/android/gms/measurement/internal/jb:e	()Lcom/google/android/gms/measurement/internal/hc;
    //   161: aload_0
    //   162: getfield 27	com/google/android/gms/measurement/internal/yb:d	LqK;
    //   165: aload_3
    //   166: invokevirtual 66	com/google/android/gms/measurement/internal/hc:a	(LqK;Ljava/util/ArrayList;)V
    //   169: return
    //   170: aload_0
    //   171: getfield 19	com/google/android/gms/measurement/internal/yb:e	Lcom/google/android/gms/measurement/internal/jb;
    //   174: invokevirtual 61	com/google/android/gms/measurement/internal/jb:e	()Lcom/google/android/gms/measurement/internal/hc;
    //   177: aload_0
    //   178: getfield 27	com/google/android/gms/measurement/internal/yb:d	LqK;
    //   181: aload_2
    //   182: invokevirtual 66	com/google/android/gms/measurement/internal/hc:a	(LqK;Ljava/util/ArrayList;)V
    //   185: aload_3
    //   186: athrow
    // Local variable table:
    //   start	length	slot	name	signature
    //   0	187	0	this	yb
    //   7	112	1	localArrayList1	java.util.ArrayList
    //   127	24	1	localRemoteException	android.os.RemoteException
    //   9	173	2	localObject	Object
    //   11	89	3	localArrayList2	java.util.ArrayList
    //   123	63	3	localArrayList3	java.util.ArrayList
    //   19	55	4	localn	n
    // Exception table:
    //   from	to	target	type
    //   12	21	123	finally
    //   30	53	123	finally
    //   73	96	123	finally
    //   100	107	123	finally
    //   130	154	123	finally
    //   12	21	127	android/os/RemoteException
    //   30	53	127	android/os/RemoteException
    //   73	96	127	android/os/RemoteException
    //   100	107	127	android/os/RemoteException
  }
}


/* Location:              /Applications/dex2jar/classes-dex2jar.jar!/com/google/android/gms/measurement/internal/yb.class
 * Java compiler version: 6 (50.0)
 * JD-Core Version:       0.7.1
 */