import java.io.File;

final class _ha<T>
  implements SQa<T>
{
  _ha(File paramFile, RZ paramRZ) {}
  
  /* Error */
  public final void a(RQa<uia> paramRQa)
  {
    // Byte code:
    //   0: aload_1
    //   1: ldc 34
    //   3: invokestatic 39	oXa:b	(Ljava/lang/Object;Ljava/lang/String;)V
    //   6: new 41	uXa
    //   9: dup
    //   10: invokespecial 42	uXa:<init>	()V
    //   13: astore_2
    //   14: aload_2
    //   15: aconst_null
    //   16: putfield 45	uXa:a	Ljava/lang/Object;
    //   19: new 47	java/io/BufferedOutputStream
    //   22: astore_3
    //   23: new 49	java/io/FileOutputStream
    //   26: astore 4
    //   28: aload 4
    //   30: aload_0
    //   31: getfield 23	_ha:a	Ljava/io/File;
    //   34: invokespecial 52	java/io/FileOutputStream:<init>	(Ljava/io/File;)V
    //   37: aload_3
    //   38: aload 4
    //   40: invokespecial 55	java/io/BufferedOutputStream:<init>	(Ljava/io/OutputStream;)V
    //   43: aload_2
    //   44: aload_3
    //   45: putfield 45	uXa:a	Ljava/lang/Object;
    //   48: aload_0
    //   49: getfield 25	_ha:b	LRZ;
    //   52: invokevirtual 61	RZ:k	()LGT;
    //   55: invokevirtual 67	GT:size	()I
    //   58: istore 5
    //   60: getstatic 70	aia:a	Laia;
    //   63: iload 5
    //   65: invokestatic 73	aia:a	(Laia;I)I
    //   68: istore 6
    //   70: new 75	tXa
    //   73: astore 4
    //   75: aload 4
    //   77: invokespecial 76	tXa:<init>	()V
    //   80: aload 4
    //   82: iload 6
    //   84: iconst_0
    //   85: invokestatic 82	java/lang/Math:max	(II)I
    //   88: putfield 85	tXa:a	I
    //   91: new 16	Zha
    //   94: astore_3
    //   95: aload_3
    //   96: aload_0
    //   97: aload_2
    //   98: aload 4
    //   100: iload 5
    //   102: invokespecial 88	Zha:<init>	(L_ha;LuXa;LtXa;I)V
    //   105: aload_1
    //   106: aload_3
    //   107: invokeinterface 93 2 0
    //   112: sipush 8192
    //   115: newarray <illegal type>
    //   117: astore_3
    //   118: getstatic 98	Xha:b	LXha;
    //   121: astore 7
    //   123: aload_0
    //   124: getfield 25	_ha:b	LRZ;
    //   127: invokevirtual 61	RZ:k	()LGT;
    //   130: astore 8
    //   132: aload 8
    //   134: ldc 100
    //   136: invokestatic 102	oXa:a	(Ljava/lang/Object;Ljava/lang/String;)V
    //   139: aload 7
    //   141: aload 8
    //   143: aload 4
    //   145: getfield 85	tXa:a	I
    //   148: aload_3
    //   149: invokevirtual 105	Xha:a	(LGT;I[B)I
    //   152: istore 6
    //   154: iload 6
    //   156: ifle +108 -> 264
    //   159: aload_1
    //   160: invokeinterface 109 1 0
    //   165: ifne +99 -> 264
    //   168: aload_2
    //   169: getfield 45	uXa:a	Ljava/lang/Object;
    //   172: checkcast 47	java/io/BufferedOutputStream
    //   175: aload_3
    //   176: iconst_0
    //   177: iload 6
    //   179: invokevirtual 113	java/io/BufferedOutputStream:write	([BII)V
    //   182: aload 4
    //   184: aload 4
    //   186: getfield 85	tXa:a	I
    //   189: iload 6
    //   191: iadd
    //   192: putfield 85	tXa:a	I
    //   195: new 115	uia
    //   198: astore 7
    //   200: aload 7
    //   202: iload 5
    //   204: aload 4
    //   206: getfield 85	tXa:a	I
    //   209: iconst_0
    //   210: aload_0
    //   211: getfield 23	_ha:a	Ljava/io/File;
    //   214: invokespecial 118	uia:<init>	(IIZLjava/io/File;)V
    //   217: aload_1
    //   218: aload 7
    //   220: invokeinterface 123 2 0
    //   225: getstatic 98	Xha:b	LXha;
    //   228: astore 7
    //   230: aload_0
    //   231: getfield 25	_ha:b	LRZ;
    //   234: invokevirtual 61	RZ:k	()LGT;
    //   237: astore 8
    //   239: aload 8
    //   241: ldc 100
    //   243: invokestatic 102	oXa:a	(Ljava/lang/Object;Ljava/lang/String;)V
    //   246: aload 7
    //   248: aload 8
    //   250: aload 4
    //   252: getfield 85	tXa:a	I
    //   255: aload_3
    //   256: invokevirtual 105	Xha:a	(LGT;I[B)I
    //   259: istore 6
    //   261: goto -107 -> 154
    //   264: aload_2
    //   265: getfield 45	uXa:a	Ljava/lang/Object;
    //   268: checkcast 47	java/io/BufferedOutputStream
    //   271: invokevirtual 126	java/io/BufferedOutputStream:flush	()V
    //   274: new 115	uia
    //   277: astore_3
    //   278: aload_3
    //   279: iload 5
    //   281: aload 4
    //   283: getfield 85	tXa:a	I
    //   286: iconst_1
    //   287: aload_0
    //   288: getfield 23	_ha:a	Ljava/io/File;
    //   291: invokespecial 118	uia:<init>	(IIZLjava/io/File;)V
    //   294: aload_1
    //   295: aload_3
    //   296: invokeinterface 123 2 0
    //   301: aload_1
    //   302: invokeinterface 128 1 0
    //   307: aload_2
    //   308: getfield 45	uXa:a	Ljava/lang/Object;
    //   311: checkcast 47	java/io/BufferedOutputStream
    //   314: astore_1
    //   315: aload_1
    //   316: ifnull +40 -> 356
    //   319: aload_1
    //   320: invokevirtual 131	java/io/BufferedOutputStream:close	()V
    //   323: goto +33 -> 356
    //   326: astore_1
    //   327: goto +30 -> 357
    //   330: astore 4
    //   332: aload_1
    //   333: aload 4
    //   335: invokeinterface 134 2 0
    //   340: pop
    //   341: aload_2
    //   342: getfield 45	uXa:a	Ljava/lang/Object;
    //   345: checkcast 47	java/io/BufferedOutputStream
    //   348: astore_1
    //   349: aload_1
    //   350: ifnull +6 -> 356
    //   353: goto -34 -> 319
    //   356: return
    //   357: aload_2
    //   358: getfield 45	uXa:a	Ljava/lang/Object;
    //   361: checkcast 47	java/io/BufferedOutputStream
    //   364: astore_2
    //   365: aload_2
    //   366: ifnull +7 -> 373
    //   369: aload_2
    //   370: invokevirtual 131	java/io/BufferedOutputStream:close	()V
    //   373: aload_1
    //   374: athrow
    // Local variable table:
    //   start	length	slot	name	signature
    //   0	375	0	this	_ha
    //   0	375	1	paramRQa	RQa<uia>
    //   13	357	2	localObject1	Object
    //   22	274	3	localObject2	Object
    //   26	256	4	localObject3	Object
    //   330	4	4	localIOException	java.io.IOException
    //   58	222	5	i	int
    //   68	192	6	j	int
    //   121	126	7	localObject4	Object
    //   130	119	8	localGT	GT
    // Exception table:
    //   from	to	target	type
    //   19	154	326	finally
    //   159	261	326	finally
    //   264	307	326	finally
    //   332	341	326	finally
    //   19	154	330	java/io/IOException
    //   159	261	330	java/io/IOException
    //   264	307	330	java/io/IOException
  }
}


/* Location:              /Applications/dex2jar/classes-dex2jar.jar!/_ha.class
 * Java compiler version: 6 (50.0)
 * JD-Core Version:       0.7.1
 */