import java.io.IOException;

public final class baa
  extends PT<baa, baa.a>
  implements caa
{
  private static final baa d = new baa();
  private static volatile YT<baa> e;
  private String f = "";
  private String g = "";
  private String h = "";
  private boolean i;
  private String j = "";
  private daa k;
  private boolean l;
  
  static
  {
    d.h();
  }
  
  public static baa k()
  {
    return d;
  }
  
  public static YT<baa> parser()
  {
    return d.e();
  }
  
  /* Error */
  protected final Object a(PT.i parami, Object paramObject1, Object paramObject2)
  {
    // Byte code:
    //   0: getstatic 63	QY:a	[I
    //   3: aload_1
    //   4: invokevirtual 69	java/lang/Enum:ordinal	()I
    //   7: iaload
    //   8: tableswitch	default:+48->56, 1:+643->651, 2:+639->647, 3:+637->645, 4:+628->636, 5:+387->395, 6:+102->110, 7:+383->391, 8:+56->64
    //   56: new 71	java/lang/UnsupportedOperationException
    //   59: dup
    //   60: invokespecial 72	java/lang/UnsupportedOperationException:<init>	()V
    //   63: athrow
    //   64: getstatic 74	baa:e	LYT;
    //   67: ifnonnull +39 -> 106
    //   70: ldc 2
    //   72: monitorenter
    //   73: getstatic 74	baa:e	LYT;
    //   76: ifnonnull +18 -> 94
    //   79: new 76	PT$b
    //   82: astore_1
    //   83: aload_1
    //   84: getstatic 32	baa:d	Lbaa;
    //   87: invokespecial 79	PT$b:<init>	(LPT;)V
    //   90: aload_1
    //   91: putstatic 74	baa:e	LYT;
    //   94: ldc 2
    //   96: monitorexit
    //   97: goto +9 -> 106
    //   100: astore_1
    //   101: ldc 2
    //   103: monitorexit
    //   104: aload_1
    //   105: athrow
    //   106: getstatic 74	baa:e	LYT;
    //   109: areturn
    //   110: aload_2
    //   111: checkcast 81	HT
    //   114: astore_2
    //   115: aload_3
    //   116: checkcast 83	LT
    //   119: astore_3
    //   120: iconst_0
    //   121: istore 4
    //   123: iload 4
    //   125: ifne +266 -> 391
    //   128: aload_2
    //   129: invokevirtual 86	HT:n	()I
    //   132: istore 5
    //   134: iload 5
    //   136: ifeq +195 -> 331
    //   139: iload 5
    //   141: bipush 10
    //   143: if_icmpeq +177 -> 320
    //   146: iload 5
    //   148: bipush 18
    //   150: if_icmpeq +159 -> 309
    //   153: iload 5
    //   155: bipush 26
    //   157: if_icmpeq +141 -> 298
    //   160: iload 5
    //   162: bipush 32
    //   164: if_icmpeq +123 -> 287
    //   167: iload 5
    //   169: bipush 42
    //   171: if_icmpeq +105 -> 276
    //   174: iload 5
    //   176: bipush 50
    //   178: if_icmpeq +33 -> 211
    //   181: iload 5
    //   183: bipush 56
    //   185: if_icmpeq +15 -> 200
    //   188: aload_2
    //   189: iload 5
    //   191: invokevirtual 89	HT:e	(I)Z
    //   194: ifne -71 -> 123
    //   197: goto +134 -> 331
    //   200: aload_0
    //   201: aload_2
    //   202: invokevirtual 93	HT:b	()Z
    //   205: putfield 95	baa:l	Z
    //   208: goto -85 -> 123
    //   211: aload_0
    //   212: getfield 97	baa:k	Ldaa;
    //   215: ifnull +17 -> 232
    //   218: aload_0
    //   219: getfield 97	baa:k	Ldaa;
    //   222: invokevirtual 101	PT:c	()LPT$a;
    //   225: checkcast 103	daa$a
    //   228: astore_1
    //   229: goto +5 -> 234
    //   232: aconst_null
    //   233: astore_1
    //   234: aload_0
    //   235: aload_2
    //   236: invokestatic 107	daa:parser	()LYT;
    //   239: aload_3
    //   240: invokevirtual 110	HT:a	(LYT;LLT;)LVT;
    //   243: checkcast 105	daa
    //   246: putfield 97	baa:k	Ldaa;
    //   249: aload_1
    //   250: ifnull -127 -> 123
    //   253: aload_1
    //   254: aload_0
    //   255: getfield 97	baa:k	Ldaa;
    //   258: invokevirtual 115	PT$a:b	(LPT;)LPT$a;
    //   261: pop
    //   262: aload_0
    //   263: aload_1
    //   264: invokevirtual 118	PT$a:b	()LPT;
    //   267: checkcast 105	daa
    //   270: putfield 97	baa:k	Ldaa;
    //   273: goto -150 -> 123
    //   276: aload_0
    //   277: aload_2
    //   278: invokevirtual 122	HT:m	()Ljava/lang/String;
    //   281: putfield 46	baa:j	Ljava/lang/String;
    //   284: goto -161 -> 123
    //   287: aload_0
    //   288: aload_2
    //   289: invokevirtual 93	HT:b	()Z
    //   292: putfield 124	baa:i	Z
    //   295: goto -172 -> 123
    //   298: aload_0
    //   299: aload_2
    //   300: invokevirtual 122	HT:m	()Ljava/lang/String;
    //   303: putfield 44	baa:h	Ljava/lang/String;
    //   306: goto -183 -> 123
    //   309: aload_0
    //   310: aload_2
    //   311: invokevirtual 122	HT:m	()Ljava/lang/String;
    //   314: putfield 42	baa:g	Ljava/lang/String;
    //   317: goto -194 -> 123
    //   320: aload_0
    //   321: aload_2
    //   322: invokevirtual 122	HT:m	()Ljava/lang/String;
    //   325: putfield 40	baa:f	Ljava/lang/String;
    //   328: goto -205 -> 123
    //   331: iconst_1
    //   332: istore 4
    //   334: goto -211 -> 123
    //   337: astore_1
    //   338: goto +51 -> 389
    //   341: astore_2
    //   342: new 126	java/lang/RuntimeException
    //   345: astore_1
    //   346: new 56	RT
    //   349: astore_3
    //   350: aload_3
    //   351: aload_2
    //   352: invokevirtual 129	java/io/IOException:getMessage	()Ljava/lang/String;
    //   355: invokespecial 132	RT:<init>	(Ljava/lang/String;)V
    //   358: aload_3
    //   359: aload_0
    //   360: invokevirtual 135	RT:a	(LVT;)LRT;
    //   363: pop
    //   364: aload_1
    //   365: aload_3
    //   366: invokespecial 138	java/lang/RuntimeException:<init>	(Ljava/lang/Throwable;)V
    //   369: aload_1
    //   370: athrow
    //   371: astore_1
    //   372: new 126	java/lang/RuntimeException
    //   375: astore_2
    //   376: aload_1
    //   377: aload_0
    //   378: invokevirtual 135	RT:a	(LVT;)LRT;
    //   381: pop
    //   382: aload_2
    //   383: aload_1
    //   384: invokespecial 138	java/lang/RuntimeException:<init>	(Ljava/lang/Throwable;)V
    //   387: aload_2
    //   388: athrow
    //   389: aload_1
    //   390: athrow
    //   391: getstatic 32	baa:d	Lbaa;
    //   394: areturn
    //   395: aload_2
    //   396: checkcast 140	PT$j
    //   399: astore_1
    //   400: aload_3
    //   401: checkcast 2	baa
    //   404: astore_2
    //   405: aload_0
    //   406: aload_1
    //   407: aload_0
    //   408: getfield 40	baa:f	Ljava/lang/String;
    //   411: invokevirtual 145	java/lang/String:isEmpty	()Z
    //   414: iconst_1
    //   415: ixor
    //   416: aload_0
    //   417: getfield 40	baa:f	Ljava/lang/String;
    //   420: aload_2
    //   421: getfield 40	baa:f	Ljava/lang/String;
    //   424: invokevirtual 145	java/lang/String:isEmpty	()Z
    //   427: iconst_1
    //   428: ixor
    //   429: aload_2
    //   430: getfield 40	baa:f	Ljava/lang/String;
    //   433: invokeinterface 148 5 0
    //   438: putfield 40	baa:f	Ljava/lang/String;
    //   441: aload_0
    //   442: aload_1
    //   443: aload_0
    //   444: getfield 42	baa:g	Ljava/lang/String;
    //   447: invokevirtual 145	java/lang/String:isEmpty	()Z
    //   450: iconst_1
    //   451: ixor
    //   452: aload_0
    //   453: getfield 42	baa:g	Ljava/lang/String;
    //   456: aload_2
    //   457: getfield 42	baa:g	Ljava/lang/String;
    //   460: invokevirtual 145	java/lang/String:isEmpty	()Z
    //   463: iconst_1
    //   464: ixor
    //   465: aload_2
    //   466: getfield 42	baa:g	Ljava/lang/String;
    //   469: invokeinterface 148 5 0
    //   474: putfield 42	baa:g	Ljava/lang/String;
    //   477: aload_0
    //   478: aload_1
    //   479: aload_0
    //   480: getfield 44	baa:h	Ljava/lang/String;
    //   483: invokevirtual 145	java/lang/String:isEmpty	()Z
    //   486: iconst_1
    //   487: ixor
    //   488: aload_0
    //   489: getfield 44	baa:h	Ljava/lang/String;
    //   492: aload_2
    //   493: getfield 44	baa:h	Ljava/lang/String;
    //   496: invokevirtual 145	java/lang/String:isEmpty	()Z
    //   499: iconst_1
    //   500: ixor
    //   501: aload_2
    //   502: getfield 44	baa:h	Ljava/lang/String;
    //   505: invokeinterface 148 5 0
    //   510: putfield 44	baa:h	Ljava/lang/String;
    //   513: aload_0
    //   514: getfield 124	baa:i	Z
    //   517: istore 6
    //   519: aload_2
    //   520: getfield 124	baa:i	Z
    //   523: istore 7
    //   525: aload_0
    //   526: aload_1
    //   527: iload 6
    //   529: iload 6
    //   531: iload 7
    //   533: iload 7
    //   535: invokeinterface 151 5 0
    //   540: putfield 124	baa:i	Z
    //   543: aload_0
    //   544: aload_1
    //   545: aload_0
    //   546: getfield 46	baa:j	Ljava/lang/String;
    //   549: invokevirtual 145	java/lang/String:isEmpty	()Z
    //   552: iconst_1
    //   553: ixor
    //   554: aload_0
    //   555: getfield 46	baa:j	Ljava/lang/String;
    //   558: iconst_1
    //   559: aload_2
    //   560: getfield 46	baa:j	Ljava/lang/String;
    //   563: invokevirtual 145	java/lang/String:isEmpty	()Z
    //   566: ixor
    //   567: aload_2
    //   568: getfield 46	baa:j	Ljava/lang/String;
    //   571: invokeinterface 148 5 0
    //   576: putfield 46	baa:j	Ljava/lang/String;
    //   579: aload_0
    //   580: aload_1
    //   581: aload_0
    //   582: getfield 97	baa:k	Ldaa;
    //   585: aload_2
    //   586: getfield 97	baa:k	Ldaa;
    //   589: invokeinterface 154 3 0
    //   594: checkcast 105	daa
    //   597: putfield 97	baa:k	Ldaa;
    //   600: aload_0
    //   601: getfield 95	baa:l	Z
    //   604: istore 6
    //   606: aload_2
    //   607: getfield 95	baa:l	Z
    //   610: istore 7
    //   612: aload_0
    //   613: aload_1
    //   614: iload 6
    //   616: iload 6
    //   618: iload 7
    //   620: iload 7
    //   622: invokeinterface 151 5 0
    //   627: putfield 95	baa:l	Z
    //   630: getstatic 159	PT$h:a	LPT$h;
    //   633: astore_1
    //   634: aload_0
    //   635: areturn
    //   636: new 9	baa$a
    //   639: dup
    //   640: aconst_null
    //   641: invokespecial 162	baa$a:<init>	(LQY;)V
    //   644: areturn
    //   645: aconst_null
    //   646: areturn
    //   647: getstatic 32	baa:d	Lbaa;
    //   650: areturn
    //   651: new 2	baa
    //   654: dup
    //   655: invokespecial 30	baa:<init>	()V
    //   658: areturn
    // Local variable table:
    //   start	length	slot	name	signature
    //   0	659	0	this	baa
    //   0	659	1	parami	PT.i
    //   0	659	2	paramObject1	Object
    //   0	659	3	paramObject2	Object
    //   121	212	4	m	int
    //   132	58	5	n	int
    //   517	100	6	bool1	boolean
    //   523	98	7	bool2	boolean
    // Exception table:
    //   from	to	target	type
    //   73	94	100	finally
    //   94	97	100	finally
    //   101	104	100	finally
    //   128	134	337	finally
    //   188	197	337	finally
    //   200	208	337	finally
    //   211	229	337	finally
    //   234	249	337	finally
    //   253	273	337	finally
    //   276	284	337	finally
    //   287	295	337	finally
    //   298	306	337	finally
    //   309	317	337	finally
    //   320	328	337	finally
    //   342	371	337	finally
    //   372	389	337	finally
    //   128	134	341	java/io/IOException
    //   188	197	341	java/io/IOException
    //   200	208	341	java/io/IOException
    //   211	229	341	java/io/IOException
    //   234	249	341	java/io/IOException
    //   253	273	341	java/io/IOException
    //   276	284	341	java/io/IOException
    //   287	295	341	java/io/IOException
    //   298	306	341	java/io/IOException
    //   309	317	341	java/io/IOException
    //   320	328	341	java/io/IOException
    //   128	134	371	RT
    //   188	197	371	RT
    //   200	208	371	RT
    //   211	229	371	RT
    //   234	249	371	RT
    //   253	273	371	RT
    //   276	284	371	RT
    //   287	295	371	RT
    //   298	306	371	RT
    //   309	317	371	RT
    //   320	328	371	RT
  }
  
  public void a(JT paramJT)
    throws IOException
  {
    if (!this.f.isEmpty()) {
      paramJT.b(1, l());
    }
    if (!this.g.isEmpty()) {
      paramJT.b(2, r());
    }
    if (!this.h.isEmpty()) {
      paramJT.b(3, q());
    }
    boolean bool = this.i;
    if (bool) {
      paramJT.b(4, bool);
    }
    if (!this.j.isEmpty()) {
      paramJT.b(5, m());
    }
    if (this.k != null) {
      paramJT.b(6, p());
    }
    bool = this.l;
    if (bool) {
      paramJT.b(7, bool);
    }
  }
  
  public int d()
  {
    int m = this.c;
    if (m != -1) {
      return m;
    }
    int n = 0;
    if (!this.f.isEmpty()) {
      n = 0 + JT.a(1, l());
    }
    m = n;
    if (!this.g.isEmpty()) {
      m = n + JT.a(2, r());
    }
    n = m;
    if (!this.h.isEmpty()) {
      n = m + JT.a(3, q());
    }
    boolean bool = this.i;
    m = n;
    if (bool) {
      m = n + JT.a(4, bool);
    }
    n = m;
    if (!this.j.isEmpty()) {
      n = m + JT.a(5, m());
    }
    m = n;
    if (this.k != null) {
      m = n + JT.a(6, p());
    }
    bool = this.l;
    n = m;
    if (bool) {
      n = m + JT.a(7, bool);
    }
    this.c = n;
    return n;
  }
  
  public String l()
  {
    return this.f;
  }
  
  public String m()
  {
    return this.j;
  }
  
  public boolean n()
  {
    return this.i;
  }
  
  public boolean o()
  {
    return this.l;
  }
  
  public daa p()
  {
    daa localdaa1 = this.k;
    daa localdaa2 = localdaa1;
    if (localdaa1 == null) {
      localdaa2 = daa.k();
    }
    return localdaa2;
  }
  
  public String q()
  {
    return this.h;
  }
  
  public String r()
  {
    return this.g;
  }
  
  public boolean s()
  {
    boolean bool;
    if (this.k != null) {
      bool = true;
    } else {
      bool = false;
    }
    return bool;
  }
  
  public static final class a
    extends PT.a<baa, a>
    implements caa
  {
    private a()
    {
      super();
    }
  }
}


/* Location:              /Applications/dex2jar/classes-dex2jar.jar!/baa.class
 * Java compiler version: 6 (50.0)
 * JD-Core Version:       0.7.1
 */