import java.io.File;

final class dha<T>
  implements SQa<T>
{
  dha(tbb paramtbb, File paramFile) {}
  
  /* Error */
  public final void a(RQa<tia> paramRQa)
  {
    // Byte code:
    //   0: aload_1
    //   1: ldc 34
    //   3: invokestatic 39	oXa:b	(Ljava/lang/Object;Ljava/lang/String;)V
    //   6: new 41	uXa
    //   9: dup
    //   10: invokespecial 42	uXa:<init>	()V
    //   13: astore_2
    //   14: aload_2
    //   15: aconst_null
    //   16: putfield 45	uXa:a	Ljava/lang/Object;
    //   19: new 41	uXa
    //   22: dup
    //   23: invokespecial 42	uXa:<init>	()V
    //   26: astore_3
    //   27: aload_3
    //   28: aconst_null
    //   29: putfield 45	uXa:a	Ljava/lang/Object;
    //   32: aload_0
    //   33: getfield 23	dha:a	Ltbb;
    //   36: invokevirtual 51	tbb:d	()Z
    //   39: ifeq +317 -> 356
    //   42: aload_0
    //   43: getfield 23	dha:a	Ltbb;
    //   46: invokevirtual 54	tbb:a	()Ljava/lang/Object;
    //   49: astore 4
    //   51: aload 4
    //   53: ifnull +298 -> 351
    //   56: aload_2
    //   57: aload 4
    //   59: checkcast 56	DZa
    //   62: invokevirtual 59	DZa:a	()Ljava/io/InputStream;
    //   65: putfield 45	uXa:a	Ljava/lang/Object;
    //   68: ldc 61
    //   70: ldc 63
    //   72: invokestatic 69	java/io/File:createTempFile	(Ljava/lang/String;Ljava/lang/String;)Ljava/io/File;
    //   75: astore 4
    //   77: aload_0
    //   78: getfield 25	dha:b	Ljava/io/File;
    //   81: astore 5
    //   83: aload_0
    //   84: getfield 23	dha:a	Ltbb;
    //   87: invokevirtual 54	tbb:a	()Ljava/lang/Object;
    //   90: astore 6
    //   92: aload 6
    //   94: ifnull +252 -> 346
    //   97: aload 6
    //   99: checkcast 56	DZa
    //   102: invokevirtual 73	DZa:c	()J
    //   105: l2i
    //   106: istore 7
    //   108: new 75	tXa
    //   111: astore 6
    //   113: aload 6
    //   115: invokespecial 76	tXa:<init>	()V
    //   118: aload 6
    //   120: iconst_0
    //   121: putfield 79	tXa:a	I
    //   124: aload_3
    //   125: aload 4
    //   127: invokestatic 84	vab:a	(Ljava/io/File;)LDab;
    //   130: invokestatic 87	vab:a	(LDab;)Lkab;
    //   133: putfield 45	uXa:a	Ljava/lang/Object;
    //   136: new 16	cha
    //   139: astore 8
    //   141: aload 8
    //   143: aload_2
    //   144: aload_3
    //   145: aload 6
    //   147: iload 7
    //   149: aload 4
    //   151: invokespecial 90	cha:<init>	(LuXa;LuXa;LtXa;ILjava/io/File;)V
    //   154: aload_1
    //   155: aload 8
    //   157: invokeinterface 95 2 0
    //   162: sipush 10240
    //   165: newarray <illegal type>
    //   167: astore 9
    //   169: aload_2
    //   170: getfield 45	uXa:a	Ljava/lang/Object;
    //   173: checkcast 97	java/io/InputStream
    //   176: aload 9
    //   178: invokevirtual 101	java/io/InputStream:read	([B)I
    //   181: istore 10
    //   183: iload 10
    //   185: iconst_m1
    //   186: if_icmpeq +97 -> 283
    //   189: aload_1
    //   190: invokeinterface 104 1 0
    //   195: ifne +88 -> 283
    //   198: new 106	tia
    //   201: astore 8
    //   203: aload 8
    //   205: aload 6
    //   207: getfield 79	tXa:a	I
    //   210: iload 7
    //   212: invokespecial 109	tia:<init>	(II)V
    //   215: aload_1
    //   216: aload 8
    //   218: invokeinterface 114 2 0
    //   223: aload 6
    //   225: aload 6
    //   227: getfield 79	tXa:a	I
    //   230: iload 10
    //   232: iadd
    //   233: putfield 79	tXa:a	I
    //   236: aload_3
    //   237: getfield 45	uXa:a	Ljava/lang/Object;
    //   240: checkcast 116	kab
    //   243: aload 9
    //   245: iconst_0
    //   246: iload 10
    //   248: invokeinterface 120 4 0
    //   253: pop
    //   254: aload_3
    //   255: getfield 45	uXa:a	Ljava/lang/Object;
    //   258: checkcast 116	kab
    //   261: invokeinterface 123 1 0
    //   266: aload_2
    //   267: getfield 45	uXa:a	Ljava/lang/Object;
    //   270: checkcast 97	java/io/InputStream
    //   273: aload 9
    //   275: invokevirtual 101	java/io/InputStream:read	([B)I
    //   278: istore 10
    //   280: goto -97 -> 183
    //   283: aload 4
    //   285: aload 5
    //   287: invokevirtual 127	java/io/File:renameTo	(Ljava/io/File;)Z
    //   290: pop
    //   291: new 106	tia
    //   294: astore 4
    //   296: aload 6
    //   298: getfield 79	tXa:a	I
    //   301: istore 11
    //   303: iload 7
    //   305: istore 10
    //   307: iload 7
    //   309: iconst_m1
    //   310: if_icmpne +10 -> 320
    //   313: aload 6
    //   315: getfield 79	tXa:a	I
    //   318: istore 10
    //   320: aload 4
    //   322: iload 11
    //   324: iload 10
    //   326: invokespecial 109	tia:<init>	(II)V
    //   329: aload_1
    //   330: aload 4
    //   332: invokeinterface 114 2 0
    //   337: aload_1
    //   338: invokeinterface 129 1 0
    //   343: goto +13 -> 356
    //   346: invokestatic 130	oXa:a	()V
    //   349: aconst_null
    //   350: athrow
    //   351: invokestatic 130	oXa:a	()V
    //   354: aconst_null
    //   355: athrow
    //   356: aload_2
    //   357: getfield 45	uXa:a	Ljava/lang/Object;
    //   360: checkcast 97	java/io/InputStream
    //   363: astore_1
    //   364: aload_1
    //   365: ifnull +7 -> 372
    //   368: aload_1
    //   369: invokevirtual 133	java/io/InputStream:close	()V
    //   372: aload_3
    //   373: getfield 45	uXa:a	Ljava/lang/Object;
    //   376: checkcast 116	kab
    //   379: astore_1
    //   380: aload_1
    //   381: ifnull +58 -> 439
    //   384: aload_1
    //   385: invokeinterface 136 1 0
    //   390: goto +49 -> 439
    //   393: astore_1
    //   394: goto +46 -> 440
    //   397: astore 4
    //   399: aload_1
    //   400: aload 4
    //   402: invokeinterface 139 2 0
    //   407: pop
    //   408: aload_2
    //   409: getfield 45	uXa:a	Ljava/lang/Object;
    //   412: checkcast 97	java/io/InputStream
    //   415: astore_1
    //   416: aload_1
    //   417: ifnull +7 -> 424
    //   420: aload_1
    //   421: invokevirtual 133	java/io/InputStream:close	()V
    //   424: aload_3
    //   425: getfield 45	uXa:a	Ljava/lang/Object;
    //   428: checkcast 116	kab
    //   431: astore_1
    //   432: aload_1
    //   433: ifnull +6 -> 439
    //   436: goto -52 -> 384
    //   439: return
    //   440: aload_2
    //   441: getfield 45	uXa:a	Ljava/lang/Object;
    //   444: checkcast 97	java/io/InputStream
    //   447: astore_2
    //   448: aload_2
    //   449: ifnull +7 -> 456
    //   452: aload_2
    //   453: invokevirtual 133	java/io/InputStream:close	()V
    //   456: aload_3
    //   457: getfield 45	uXa:a	Ljava/lang/Object;
    //   460: checkcast 116	kab
    //   463: astore_3
    //   464: aload_3
    //   465: ifnull +9 -> 474
    //   468: aload_3
    //   469: invokeinterface 136 1 0
    //   474: aload_1
    //   475: athrow
    // Local variable table:
    //   start	length	slot	name	signature
    //   0	476	0	this	dha
    //   0	476	1	paramRQa	RQa<tia>
    //   13	440	2	localObject1	Object
    //   26	443	3	localObject2	Object
    //   49	282	4	localObject3	Object
    //   397	4	4	localIOException	java.io.IOException
    //   81	205	5	localFile	File
    //   90	224	6	localObject4	Object
    //   106	205	7	i	int
    //   139	78	8	localObject5	Object
    //   167	107	9	arrayOfByte	byte[]
    //   181	144	10	j	int
    //   301	22	11	k	int
    // Exception table:
    //   from	to	target	type
    //   32	51	393	finally
    //   56	92	393	finally
    //   97	183	393	finally
    //   189	280	393	finally
    //   283	303	393	finally
    //   313	320	393	finally
    //   320	343	393	finally
    //   346	349	393	finally
    //   351	354	393	finally
    //   399	408	393	finally
    //   32	51	397	java/io/IOException
    //   56	92	397	java/io/IOException
    //   97	183	397	java/io/IOException
    //   189	280	397	java/io/IOException
    //   283	303	397	java/io/IOException
    //   313	320	397	java/io/IOException
    //   320	343	397	java/io/IOException
    //   346	349	397	java/io/IOException
    //   351	354	397	java/io/IOException
  }
}


/* Location:              /Applications/dex2jar/classes-dex2jar.jar!/dha.class
 * Java compiler version: 6 (50.0)
 * JD-Core Version:       0.7.1
 */