import java.io.IOException;

public final class Faa$d
  extends PT<d, Faa.d.a>
  implements Faa.e
{
  private static final d d = new d();
  private static volatile YT<d> e;
  private int f = 0;
  private Object g;
  
  static
  {
    d.h();
  }
  
  private void a(Faa.d.b paramb)
  {
    if (paramb != null)
    {
      this.g = paramb;
      this.f = 2;
      return;
    }
    throw new NullPointerException();
  }
  
  private void a(Faa.d.d paramd)
  {
    if (paramd != null)
    {
      this.g = paramd;
      this.f = 3;
      return;
    }
    throw new NullPointerException();
  }
  
  private void a(Faa.d.g paramg)
  {
    if (paramg != null)
    {
      this.g = paramg;
      this.f = 1;
      return;
    }
    throw new NullPointerException();
  }
  
  private void a(Faa.d.i parami)
  {
    if (parami != null)
    {
      this.g = parami;
      this.f = 8;
      return;
    }
    throw new NullPointerException();
  }
  
  private void b(Faa.d.b paramb)
  {
    if (paramb != null)
    {
      this.g = paramb;
      this.f = 4;
      return;
    }
    throw new NullPointerException();
  }
  
  private void b(Faa.d.i parami)
  {
    if (parami != null)
    {
      this.g = parami;
      this.f = 9;
      return;
    }
    throw new NullPointerException();
  }
  
  private void c(Faa.d.b paramb)
  {
    if (paramb != null)
    {
      this.g = paramb;
      this.f = 16;
      return;
    }
    throw new NullPointerException();
  }
  
  private void c(Faa.d.i parami)
  {
    if (parami != null)
    {
      this.g = parami;
      this.f = 20;
      return;
    }
    throw new NullPointerException();
  }
  
  private void d(Faa.d.i parami)
  {
    if (parami != null)
    {
      this.g = parami;
      this.f = 6;
      return;
    }
    throw new NullPointerException();
  }
  
  private void e(Faa.d.i parami)
  {
    if (parami != null)
    {
      this.g = parami;
      this.f = 10;
      return;
    }
    throw new NullPointerException();
  }
  
  private void f(Faa.d.i parami)
  {
    if (parami != null)
    {
      this.g = parami;
      this.f = 19;
      return;
    }
    throw new NullPointerException();
  }
  
  private void g(Faa.d.i parami)
  {
    if (parami != null)
    {
      this.g = parami;
      this.f = 11;
      return;
    }
    throw new NullPointerException();
  }
  
  private void h(Faa.d.i parami)
  {
    if (parami != null)
    {
      this.g = parami;
      this.f = 7;
      return;
    }
    throw new NullPointerException();
  }
  
  public static Faa.d.a l()
  {
    return (Faa.d.a)d.c();
  }
  
  public static YT<d> parser()
  {
    return d.e();
  }
  
  /* Error */
  protected final Object a(PT.i parami, Object paramObject1, Object paramObject2)
  {
    // Byte code:
    //   0: getstatic 126	QY:a	[I
    //   3: aload_1
    //   4: invokevirtual 132	java/lang/Enum:ordinal	()I
    //   7: iaload
    //   8: tableswitch	default:+48->56, 1:+2343->2351, 2:+2339->2347, 3:+2337->2345, 4:+2328->2336, 5:+1517->1525, 6:+102->110, 7:+1513->1521, 8:+56->64
    //   56: new 134	java/lang/UnsupportedOperationException
    //   59: dup
    //   60: invokespecial 135	java/lang/UnsupportedOperationException:<init>	()V
    //   63: athrow
    //   64: getstatic 137	Faa$d:e	LYT;
    //   67: ifnonnull +39 -> 106
    //   70: ldc 2
    //   72: monitorenter
    //   73: getstatic 137	Faa$d:e	LYT;
    //   76: ifnonnull +18 -> 94
    //   79: new 139	PT$b
    //   82: astore_1
    //   83: aload_1
    //   84: getstatic 59	Faa$d:d	LFaa$d;
    //   87: invokespecial 142	PT$b:<init>	(LPT;)V
    //   90: aload_1
    //   91: putstatic 137	Faa$d:e	LYT;
    //   94: ldc 2
    //   96: monitorexit
    //   97: goto +9 -> 106
    //   100: astore_1
    //   101: ldc 2
    //   103: monitorexit
    //   104: aload_1
    //   105: athrow
    //   106: getstatic 137	Faa$d:e	LYT;
    //   109: areturn
    //   110: aload_2
    //   111: checkcast 144	HT
    //   114: astore_2
    //   115: aload_3
    //   116: checkcast 146	LT
    //   119: astore_3
    //   120: iconst_0
    //   121: istore 4
    //   123: iload 4
    //   125: ifne +1396 -> 1521
    //   128: aload_2
    //   129: invokevirtual 149	HT:n	()I
    //   132: istore 5
    //   134: iload 5
    //   136: lookupswitch	default:+148->284, 0:+1317->1453, 10:+1246->1382, 18:+1175->1311, 26:+1104->1240, 34:+1033->1169, 42:+962->1098, 50:+889->1025, 58:+816->952, 66:+743->879, 74:+670->806, 82:+597->733, 90:+524->660, 130:+451->587, 138:+378->514, 146:+305->441, 154:+232->368, 162:+159->295
    //   284: aload_2
    //   285: iload 5
    //   287: invokevirtual 152	HT:e	(I)Z
    //   290: istore 6
    //   292: goto +1167 -> 1459
    //   295: aload_0
    //   296: getfield 65	Faa$d:f	I
    //   299: bipush 20
    //   301: if_icmpne +20 -> 321
    //   304: aload_0
    //   305: getfield 68	Faa$d:g	Ljava/lang/Object;
    //   308: checkcast 41	Faa$d$i
    //   311: invokevirtual 110	PT:c	()LPT$a;
    //   314: checkcast 44	Faa$d$i$a
    //   317: astore_1
    //   318: goto +5 -> 323
    //   321: aconst_null
    //   322: astore_1
    //   323: aload_0
    //   324: aload_2
    //   325: invokestatic 154	Faa$d$i:parser	()LYT;
    //   328: aload_3
    //   329: invokevirtual 157	HT:a	(LYT;LLT;)LVT;
    //   332: putfield 68	Faa$d:g	Ljava/lang/Object;
    //   335: aload_1
    //   336: ifnull +23 -> 359
    //   339: aload_1
    //   340: aload_0
    //   341: getfield 68	Faa$d:g	Ljava/lang/Object;
    //   344: checkcast 41	Faa$d$i
    //   347: invokevirtual 162	PT$a:b	(LPT;)LPT$a;
    //   350: pop
    //   351: aload_0
    //   352: aload_1
    //   353: invokevirtual 165	PT$a:b	()LPT;
    //   356: putfield 68	Faa$d:g	Ljava/lang/Object;
    //   359: aload_0
    //   360: bipush 20
    //   362: putfield 65	Faa$d:f	I
    //   365: goto -242 -> 123
    //   368: aload_0
    //   369: getfield 65	Faa$d:f	I
    //   372: bipush 19
    //   374: if_icmpne +20 -> 394
    //   377: aload_0
    //   378: getfield 68	Faa$d:g	Ljava/lang/Object;
    //   381: checkcast 41	Faa$d$i
    //   384: invokevirtual 110	PT:c	()LPT$a;
    //   387: checkcast 44	Faa$d$i$a
    //   390: astore_1
    //   391: goto +5 -> 396
    //   394: aconst_null
    //   395: astore_1
    //   396: aload_0
    //   397: aload_2
    //   398: invokestatic 154	Faa$d$i:parser	()LYT;
    //   401: aload_3
    //   402: invokevirtual 157	HT:a	(LYT;LLT;)LVT;
    //   405: putfield 68	Faa$d:g	Ljava/lang/Object;
    //   408: aload_1
    //   409: ifnull +23 -> 432
    //   412: aload_1
    //   413: aload_0
    //   414: getfield 68	Faa$d:g	Ljava/lang/Object;
    //   417: checkcast 41	Faa$d$i
    //   420: invokevirtual 162	PT$a:b	(LPT;)LPT$a;
    //   423: pop
    //   424: aload_0
    //   425: aload_1
    //   426: invokevirtual 165	PT$a:b	()LPT;
    //   429: putfield 68	Faa$d:g	Ljava/lang/Object;
    //   432: aload_0
    //   433: bipush 19
    //   435: putfield 65	Faa$d:f	I
    //   438: goto -315 -> 123
    //   441: aload_0
    //   442: getfield 65	Faa$d:f	I
    //   445: bipush 18
    //   447: if_icmpne +20 -> 467
    //   450: aload_0
    //   451: getfield 68	Faa$d:g	Ljava/lang/Object;
    //   454: checkcast 41	Faa$d$i
    //   457: invokevirtual 110	PT:c	()LPT$a;
    //   460: checkcast 44	Faa$d$i$a
    //   463: astore_1
    //   464: goto +5 -> 469
    //   467: aconst_null
    //   468: astore_1
    //   469: aload_0
    //   470: aload_2
    //   471: invokestatic 154	Faa$d$i:parser	()LYT;
    //   474: aload_3
    //   475: invokevirtual 157	HT:a	(LYT;LLT;)LVT;
    //   478: putfield 68	Faa$d:g	Ljava/lang/Object;
    //   481: aload_1
    //   482: ifnull +23 -> 505
    //   485: aload_1
    //   486: aload_0
    //   487: getfield 68	Faa$d:g	Ljava/lang/Object;
    //   490: checkcast 41	Faa$d$i
    //   493: invokevirtual 162	PT$a:b	(LPT;)LPT$a;
    //   496: pop
    //   497: aload_0
    //   498: aload_1
    //   499: invokevirtual 165	PT$a:b	()LPT;
    //   502: putfield 68	Faa$d:g	Ljava/lang/Object;
    //   505: aload_0
    //   506: bipush 18
    //   508: putfield 65	Faa$d:f	I
    //   511: goto -388 -> 123
    //   514: aload_0
    //   515: getfield 65	Faa$d:f	I
    //   518: bipush 17
    //   520: if_icmpne +20 -> 540
    //   523: aload_0
    //   524: getfield 68	Faa$d:g	Ljava/lang/Object;
    //   527: checkcast 41	Faa$d$i
    //   530: invokevirtual 110	PT:c	()LPT$a;
    //   533: checkcast 44	Faa$d$i$a
    //   536: astore_1
    //   537: goto +5 -> 542
    //   540: aconst_null
    //   541: astore_1
    //   542: aload_0
    //   543: aload_2
    //   544: invokestatic 154	Faa$d$i:parser	()LYT;
    //   547: aload_3
    //   548: invokevirtual 157	HT:a	(LYT;LLT;)LVT;
    //   551: putfield 68	Faa$d:g	Ljava/lang/Object;
    //   554: aload_1
    //   555: ifnull +23 -> 578
    //   558: aload_1
    //   559: aload_0
    //   560: getfield 68	Faa$d:g	Ljava/lang/Object;
    //   563: checkcast 41	Faa$d$i
    //   566: invokevirtual 162	PT$a:b	(LPT;)LPT$a;
    //   569: pop
    //   570: aload_0
    //   571: aload_1
    //   572: invokevirtual 165	PT$a:b	()LPT;
    //   575: putfield 68	Faa$d:g	Ljava/lang/Object;
    //   578: aload_0
    //   579: bipush 17
    //   581: putfield 65	Faa$d:f	I
    //   584: goto -461 -> 123
    //   587: aload_0
    //   588: getfield 65	Faa$d:f	I
    //   591: bipush 16
    //   593: if_icmpne +20 -> 613
    //   596: aload_0
    //   597: getfield 68	Faa$d:g	Ljava/lang/Object;
    //   600: checkcast 15	Faa$d$b
    //   603: invokevirtual 110	PT:c	()LPT$a;
    //   606: checkcast 18	Faa$d$b$a
    //   609: astore_1
    //   610: goto +5 -> 615
    //   613: aconst_null
    //   614: astore_1
    //   615: aload_0
    //   616: aload_2
    //   617: invokestatic 166	Faa$d$b:parser	()LYT;
    //   620: aload_3
    //   621: invokevirtual 157	HT:a	(LYT;LLT;)LVT;
    //   624: putfield 68	Faa$d:g	Ljava/lang/Object;
    //   627: aload_1
    //   628: ifnull +23 -> 651
    //   631: aload_1
    //   632: aload_0
    //   633: getfield 68	Faa$d:g	Ljava/lang/Object;
    //   636: checkcast 15	Faa$d$b
    //   639: invokevirtual 162	PT$a:b	(LPT;)LPT$a;
    //   642: pop
    //   643: aload_0
    //   644: aload_1
    //   645: invokevirtual 165	PT$a:b	()LPT;
    //   648: putfield 68	Faa$d:g	Ljava/lang/Object;
    //   651: aload_0
    //   652: bipush 16
    //   654: putfield 65	Faa$d:f	I
    //   657: goto -534 -> 123
    //   660: aload_0
    //   661: getfield 65	Faa$d:f	I
    //   664: bipush 11
    //   666: if_icmpne +20 -> 686
    //   669: aload_0
    //   670: getfield 68	Faa$d:g	Ljava/lang/Object;
    //   673: checkcast 41	Faa$d$i
    //   676: invokevirtual 110	PT:c	()LPT$a;
    //   679: checkcast 44	Faa$d$i$a
    //   682: astore_1
    //   683: goto +5 -> 688
    //   686: aconst_null
    //   687: astore_1
    //   688: aload_0
    //   689: aload_2
    //   690: invokestatic 154	Faa$d$i:parser	()LYT;
    //   693: aload_3
    //   694: invokevirtual 157	HT:a	(LYT;LLT;)LVT;
    //   697: putfield 68	Faa$d:g	Ljava/lang/Object;
    //   700: aload_1
    //   701: ifnull +23 -> 724
    //   704: aload_1
    //   705: aload_0
    //   706: getfield 68	Faa$d:g	Ljava/lang/Object;
    //   709: checkcast 41	Faa$d$i
    //   712: invokevirtual 162	PT$a:b	(LPT;)LPT$a;
    //   715: pop
    //   716: aload_0
    //   717: aload_1
    //   718: invokevirtual 165	PT$a:b	()LPT;
    //   721: putfield 68	Faa$d:g	Ljava/lang/Object;
    //   724: aload_0
    //   725: bipush 11
    //   727: putfield 65	Faa$d:f	I
    //   730: goto -607 -> 123
    //   733: aload_0
    //   734: getfield 65	Faa$d:f	I
    //   737: bipush 10
    //   739: if_icmpne +20 -> 759
    //   742: aload_0
    //   743: getfield 68	Faa$d:g	Ljava/lang/Object;
    //   746: checkcast 41	Faa$d$i
    //   749: invokevirtual 110	PT:c	()LPT$a;
    //   752: checkcast 44	Faa$d$i$a
    //   755: astore_1
    //   756: goto +5 -> 761
    //   759: aconst_null
    //   760: astore_1
    //   761: aload_0
    //   762: aload_2
    //   763: invokestatic 154	Faa$d$i:parser	()LYT;
    //   766: aload_3
    //   767: invokevirtual 157	HT:a	(LYT;LLT;)LVT;
    //   770: putfield 68	Faa$d:g	Ljava/lang/Object;
    //   773: aload_1
    //   774: ifnull +23 -> 797
    //   777: aload_1
    //   778: aload_0
    //   779: getfield 68	Faa$d:g	Ljava/lang/Object;
    //   782: checkcast 41	Faa$d$i
    //   785: invokevirtual 162	PT$a:b	(LPT;)LPT$a;
    //   788: pop
    //   789: aload_0
    //   790: aload_1
    //   791: invokevirtual 165	PT$a:b	()LPT;
    //   794: putfield 68	Faa$d:g	Ljava/lang/Object;
    //   797: aload_0
    //   798: bipush 10
    //   800: putfield 65	Faa$d:f	I
    //   803: goto -680 -> 123
    //   806: aload_0
    //   807: getfield 65	Faa$d:f	I
    //   810: bipush 9
    //   812: if_icmpne +20 -> 832
    //   815: aload_0
    //   816: getfield 68	Faa$d:g	Ljava/lang/Object;
    //   819: checkcast 41	Faa$d$i
    //   822: invokevirtual 110	PT:c	()LPT$a;
    //   825: checkcast 44	Faa$d$i$a
    //   828: astore_1
    //   829: goto +5 -> 834
    //   832: aconst_null
    //   833: astore_1
    //   834: aload_0
    //   835: aload_2
    //   836: invokestatic 154	Faa$d$i:parser	()LYT;
    //   839: aload_3
    //   840: invokevirtual 157	HT:a	(LYT;LLT;)LVT;
    //   843: putfield 68	Faa$d:g	Ljava/lang/Object;
    //   846: aload_1
    //   847: ifnull +23 -> 870
    //   850: aload_1
    //   851: aload_0
    //   852: getfield 68	Faa$d:g	Ljava/lang/Object;
    //   855: checkcast 41	Faa$d$i
    //   858: invokevirtual 162	PT$a:b	(LPT;)LPT$a;
    //   861: pop
    //   862: aload_0
    //   863: aload_1
    //   864: invokevirtual 165	PT$a:b	()LPT;
    //   867: putfield 68	Faa$d:g	Ljava/lang/Object;
    //   870: aload_0
    //   871: bipush 9
    //   873: putfield 65	Faa$d:f	I
    //   876: goto -753 -> 123
    //   879: aload_0
    //   880: getfield 65	Faa$d:f	I
    //   883: bipush 8
    //   885: if_icmpne +20 -> 905
    //   888: aload_0
    //   889: getfield 68	Faa$d:g	Ljava/lang/Object;
    //   892: checkcast 41	Faa$d$i
    //   895: invokevirtual 110	PT:c	()LPT$a;
    //   898: checkcast 44	Faa$d$i$a
    //   901: astore_1
    //   902: goto +5 -> 907
    //   905: aconst_null
    //   906: astore_1
    //   907: aload_0
    //   908: aload_2
    //   909: invokestatic 154	Faa$d$i:parser	()LYT;
    //   912: aload_3
    //   913: invokevirtual 157	HT:a	(LYT;LLT;)LVT;
    //   916: putfield 68	Faa$d:g	Ljava/lang/Object;
    //   919: aload_1
    //   920: ifnull +23 -> 943
    //   923: aload_1
    //   924: aload_0
    //   925: getfield 68	Faa$d:g	Ljava/lang/Object;
    //   928: checkcast 41	Faa$d$i
    //   931: invokevirtual 162	PT$a:b	(LPT;)LPT$a;
    //   934: pop
    //   935: aload_0
    //   936: aload_1
    //   937: invokevirtual 165	PT$a:b	()LPT;
    //   940: putfield 68	Faa$d:g	Ljava/lang/Object;
    //   943: aload_0
    //   944: bipush 8
    //   946: putfield 65	Faa$d:f	I
    //   949: goto -826 -> 123
    //   952: aload_0
    //   953: getfield 65	Faa$d:f	I
    //   956: bipush 7
    //   958: if_icmpne +20 -> 978
    //   961: aload_0
    //   962: getfield 68	Faa$d:g	Ljava/lang/Object;
    //   965: checkcast 41	Faa$d$i
    //   968: invokevirtual 110	PT:c	()LPT$a;
    //   971: checkcast 44	Faa$d$i$a
    //   974: astore_1
    //   975: goto +5 -> 980
    //   978: aconst_null
    //   979: astore_1
    //   980: aload_0
    //   981: aload_2
    //   982: invokestatic 154	Faa$d$i:parser	()LYT;
    //   985: aload_3
    //   986: invokevirtual 157	HT:a	(LYT;LLT;)LVT;
    //   989: putfield 68	Faa$d:g	Ljava/lang/Object;
    //   992: aload_1
    //   993: ifnull +23 -> 1016
    //   996: aload_1
    //   997: aload_0
    //   998: getfield 68	Faa$d:g	Ljava/lang/Object;
    //   1001: checkcast 41	Faa$d$i
    //   1004: invokevirtual 162	PT$a:b	(LPT;)LPT$a;
    //   1007: pop
    //   1008: aload_0
    //   1009: aload_1
    //   1010: invokevirtual 165	PT$a:b	()LPT;
    //   1013: putfield 68	Faa$d:g	Ljava/lang/Object;
    //   1016: aload_0
    //   1017: bipush 7
    //   1019: putfield 65	Faa$d:f	I
    //   1022: goto -899 -> 123
    //   1025: aload_0
    //   1026: getfield 65	Faa$d:f	I
    //   1029: bipush 6
    //   1031: if_icmpne +20 -> 1051
    //   1034: aload_0
    //   1035: getfield 68	Faa$d:g	Ljava/lang/Object;
    //   1038: checkcast 41	Faa$d$i
    //   1041: invokevirtual 110	PT:c	()LPT$a;
    //   1044: checkcast 44	Faa$d$i$a
    //   1047: astore_1
    //   1048: goto +5 -> 1053
    //   1051: aconst_null
    //   1052: astore_1
    //   1053: aload_0
    //   1054: aload_2
    //   1055: invokestatic 154	Faa$d$i:parser	()LYT;
    //   1058: aload_3
    //   1059: invokevirtual 157	HT:a	(LYT;LLT;)LVT;
    //   1062: putfield 68	Faa$d:g	Ljava/lang/Object;
    //   1065: aload_1
    //   1066: ifnull +23 -> 1089
    //   1069: aload_1
    //   1070: aload_0
    //   1071: getfield 68	Faa$d:g	Ljava/lang/Object;
    //   1074: checkcast 41	Faa$d$i
    //   1077: invokevirtual 162	PT$a:b	(LPT;)LPT$a;
    //   1080: pop
    //   1081: aload_0
    //   1082: aload_1
    //   1083: invokevirtual 165	PT$a:b	()LPT;
    //   1086: putfield 68	Faa$d:g	Ljava/lang/Object;
    //   1089: aload_0
    //   1090: bipush 6
    //   1092: putfield 65	Faa$d:f	I
    //   1095: goto -972 -> 123
    //   1098: aload_0
    //   1099: getfield 65	Faa$d:f	I
    //   1102: iconst_5
    //   1103: if_icmpne +20 -> 1123
    //   1106: aload_0
    //   1107: getfield 68	Faa$d:g	Ljava/lang/Object;
    //   1110: checkcast 15	Faa$d$b
    //   1113: invokevirtual 110	PT:c	()LPT$a;
    //   1116: checkcast 18	Faa$d$b$a
    //   1119: astore_1
    //   1120: goto +5 -> 1125
    //   1123: aconst_null
    //   1124: astore_1
    //   1125: aload_0
    //   1126: aload_2
    //   1127: invokestatic 166	Faa$d$b:parser	()LYT;
    //   1130: aload_3
    //   1131: invokevirtual 157	HT:a	(LYT;LLT;)LVT;
    //   1134: putfield 68	Faa$d:g	Ljava/lang/Object;
    //   1137: aload_1
    //   1138: ifnull +23 -> 1161
    //   1141: aload_1
    //   1142: aload_0
    //   1143: getfield 68	Faa$d:g	Ljava/lang/Object;
    //   1146: checkcast 15	Faa$d$b
    //   1149: invokevirtual 162	PT$a:b	(LPT;)LPT$a;
    //   1152: pop
    //   1153: aload_0
    //   1154: aload_1
    //   1155: invokevirtual 165	PT$a:b	()LPT;
    //   1158: putfield 68	Faa$d:g	Ljava/lang/Object;
    //   1161: aload_0
    //   1162: iconst_5
    //   1163: putfield 65	Faa$d:f	I
    //   1166: goto -1043 -> 123
    //   1169: aload_0
    //   1170: getfield 65	Faa$d:f	I
    //   1173: iconst_4
    //   1174: if_icmpne +20 -> 1194
    //   1177: aload_0
    //   1178: getfield 68	Faa$d:g	Ljava/lang/Object;
    //   1181: checkcast 15	Faa$d$b
    //   1184: invokevirtual 110	PT:c	()LPT$a;
    //   1187: checkcast 18	Faa$d$b$a
    //   1190: astore_1
    //   1191: goto +5 -> 1196
    //   1194: aconst_null
    //   1195: astore_1
    //   1196: aload_0
    //   1197: aload_2
    //   1198: invokestatic 166	Faa$d$b:parser	()LYT;
    //   1201: aload_3
    //   1202: invokevirtual 157	HT:a	(LYT;LLT;)LVT;
    //   1205: putfield 68	Faa$d:g	Ljava/lang/Object;
    //   1208: aload_1
    //   1209: ifnull +23 -> 1232
    //   1212: aload_1
    //   1213: aload_0
    //   1214: getfield 68	Faa$d:g	Ljava/lang/Object;
    //   1217: checkcast 15	Faa$d$b
    //   1220: invokevirtual 162	PT$a:b	(LPT;)LPT$a;
    //   1223: pop
    //   1224: aload_0
    //   1225: aload_1
    //   1226: invokevirtual 165	PT$a:b	()LPT;
    //   1229: putfield 68	Faa$d:g	Ljava/lang/Object;
    //   1232: aload_0
    //   1233: iconst_4
    //   1234: putfield 65	Faa$d:f	I
    //   1237: goto -1114 -> 123
    //   1240: aload_0
    //   1241: getfield 65	Faa$d:f	I
    //   1244: iconst_3
    //   1245: if_icmpne +20 -> 1265
    //   1248: aload_0
    //   1249: getfield 68	Faa$d:g	Ljava/lang/Object;
    //   1252: checkcast 23	Faa$d$d
    //   1255: invokevirtual 110	PT:c	()LPT$a;
    //   1258: checkcast 25	Faa$d$d$a
    //   1261: astore_1
    //   1262: goto +5 -> 1267
    //   1265: aconst_null
    //   1266: astore_1
    //   1267: aload_0
    //   1268: aload_2
    //   1269: invokestatic 167	Faa$d$d:parser	()LYT;
    //   1272: aload_3
    //   1273: invokevirtual 157	HT:a	(LYT;LLT;)LVT;
    //   1276: putfield 68	Faa$d:g	Ljava/lang/Object;
    //   1279: aload_1
    //   1280: ifnull +23 -> 1303
    //   1283: aload_1
    //   1284: aload_0
    //   1285: getfield 68	Faa$d:g	Ljava/lang/Object;
    //   1288: checkcast 23	Faa$d$d
    //   1291: invokevirtual 162	PT$a:b	(LPT;)LPT$a;
    //   1294: pop
    //   1295: aload_0
    //   1296: aload_1
    //   1297: invokevirtual 165	PT$a:b	()LPT;
    //   1300: putfield 68	Faa$d:g	Ljava/lang/Object;
    //   1303: aload_0
    //   1304: iconst_3
    //   1305: putfield 65	Faa$d:f	I
    //   1308: goto -1185 -> 123
    //   1311: aload_0
    //   1312: getfield 65	Faa$d:f	I
    //   1315: iconst_2
    //   1316: if_icmpne +20 -> 1336
    //   1319: aload_0
    //   1320: getfield 68	Faa$d:g	Ljava/lang/Object;
    //   1323: checkcast 15	Faa$d$b
    //   1326: invokevirtual 110	PT:c	()LPT$a;
    //   1329: checkcast 18	Faa$d$b$a
    //   1332: astore_1
    //   1333: goto +5 -> 1338
    //   1336: aconst_null
    //   1337: astore_1
    //   1338: aload_0
    //   1339: aload_2
    //   1340: invokestatic 166	Faa$d$b:parser	()LYT;
    //   1343: aload_3
    //   1344: invokevirtual 157	HT:a	(LYT;LLT;)LVT;
    //   1347: putfield 68	Faa$d:g	Ljava/lang/Object;
    //   1350: aload_1
    //   1351: ifnull +23 -> 1374
    //   1354: aload_1
    //   1355: aload_0
    //   1356: getfield 68	Faa$d:g	Ljava/lang/Object;
    //   1359: checkcast 15	Faa$d$b
    //   1362: invokevirtual 162	PT$a:b	(LPT;)LPT$a;
    //   1365: pop
    //   1366: aload_0
    //   1367: aload_1
    //   1368: invokevirtual 165	PT$a:b	()LPT;
    //   1371: putfield 68	Faa$d:g	Ljava/lang/Object;
    //   1374: aload_0
    //   1375: iconst_2
    //   1376: putfield 65	Faa$d:f	I
    //   1379: goto -1256 -> 123
    //   1382: aload_0
    //   1383: getfield 65	Faa$d:f	I
    //   1386: iconst_1
    //   1387: if_icmpne +20 -> 1407
    //   1390: aload_0
    //   1391: getfield 68	Faa$d:g	Ljava/lang/Object;
    //   1394: checkcast 33	Faa$d$g
    //   1397: invokevirtual 110	PT:c	()LPT$a;
    //   1400: checkcast 36	Faa$d$g$a
    //   1403: astore_1
    //   1404: goto +5 -> 1409
    //   1407: aconst_null
    //   1408: astore_1
    //   1409: aload_0
    //   1410: aload_2
    //   1411: invokestatic 168	Faa$d$g:parser	()LYT;
    //   1414: aload_3
    //   1415: invokevirtual 157	HT:a	(LYT;LLT;)LVT;
    //   1418: putfield 68	Faa$d:g	Ljava/lang/Object;
    //   1421: aload_1
    //   1422: ifnull +23 -> 1445
    //   1425: aload_1
    //   1426: aload_0
    //   1427: getfield 68	Faa$d:g	Ljava/lang/Object;
    //   1430: checkcast 33	Faa$d$g
    //   1433: invokevirtual 162	PT$a:b	(LPT;)LPT$a;
    //   1436: pop
    //   1437: aload_0
    //   1438: aload_1
    //   1439: invokevirtual 165	PT$a:b	()LPT;
    //   1442: putfield 68	Faa$d:g	Ljava/lang/Object;
    //   1445: aload_0
    //   1446: iconst_1
    //   1447: putfield 65	Faa$d:f	I
    //   1450: goto -1327 -> 123
    //   1453: iconst_1
    //   1454: istore 4
    //   1456: goto -1333 -> 123
    //   1459: iload 6
    //   1461: ifne -1338 -> 123
    //   1464: goto -11 -> 1453
    //   1467: astore_1
    //   1468: goto +51 -> 1519
    //   1471: astore_1
    //   1472: new 170	java/lang/RuntimeException
    //   1475: astore_2
    //   1476: new 119	RT
    //   1479: astore_3
    //   1480: aload_3
    //   1481: aload_1
    //   1482: invokevirtual 174	java/io/IOException:getMessage	()Ljava/lang/String;
    //   1485: invokespecial 177	RT:<init>	(Ljava/lang/String;)V
    //   1488: aload_3
    //   1489: aload_0
    //   1490: invokevirtual 180	RT:a	(LVT;)LRT;
    //   1493: pop
    //   1494: aload_2
    //   1495: aload_3
    //   1496: invokespecial 183	java/lang/RuntimeException:<init>	(Ljava/lang/Throwable;)V
    //   1499: aload_2
    //   1500: athrow
    //   1501: astore_2
    //   1502: new 170	java/lang/RuntimeException
    //   1505: astore_1
    //   1506: aload_2
    //   1507: aload_0
    //   1508: invokevirtual 180	RT:a	(LVT;)LRT;
    //   1511: pop
    //   1512: aload_1
    //   1513: aload_2
    //   1514: invokespecial 183	java/lang/RuntimeException:<init>	(Ljava/lang/Throwable;)V
    //   1517: aload_1
    //   1518: athrow
    //   1519: aload_1
    //   1520: athrow
    //   1521: getstatic 59	Faa$d:d	LFaa$d;
    //   1524: areturn
    //   1525: aload_2
    //   1526: checkcast 185	PT$j
    //   1529: astore_1
    //   1530: aload_3
    //   1531: checkcast 2	Faa$d
    //   1534: astore_2
    //   1535: getstatic 187	QY:e	[I
    //   1538: aload_2
    //   1539: invokevirtual 191	Faa$d:k	()LFaa$d$f;
    //   1542: invokevirtual 132	java/lang/Enum:ordinal	()I
    //   1545: iaload
    //   1546: tableswitch	default:+82->1628, 1:+723->2269, 2:+683->2229, 3:+643->2189, 4:+602->2148, 5:+562->2108, 6:+521->2067, 7:+480->2026, 8:+439->1985, 9:+398->1944, 10:+357->1903, 11:+316->1862, 12:+275->1821, 13:+234->1780, 14:+193->1739, 15:+152->1698, 16:+112->1658, 17:+85->1631
    //   1628: goto +682 -> 2310
    //   1631: aload_0
    //   1632: getfield 65	Faa$d:f	I
    //   1635: ifeq +9 -> 1644
    //   1638: iconst_1
    //   1639: istore 6
    //   1641: goto +6 -> 1647
    //   1644: iconst_0
    //   1645: istore 6
    //   1647: aload_1
    //   1648: iload 6
    //   1650: invokeinterface 194 2 0
    //   1655: goto +655 -> 2310
    //   1658: aload_0
    //   1659: getfield 65	Faa$d:f	I
    //   1662: iconst_3
    //   1663: if_icmpne +9 -> 1672
    //   1666: iconst_1
    //   1667: istore 6
    //   1669: goto +6 -> 1675
    //   1672: iconst_0
    //   1673: istore 6
    //   1675: aload_0
    //   1676: aload_1
    //   1677: iload 6
    //   1679: aload_0
    //   1680: getfield 68	Faa$d:g	Ljava/lang/Object;
    //   1683: aload_2
    //   1684: getfield 68	Faa$d:g	Ljava/lang/Object;
    //   1687: invokeinterface 197 4 0
    //   1692: putfield 68	Faa$d:g	Ljava/lang/Object;
    //   1695: goto +615 -> 2310
    //   1698: aload_0
    //   1699: getfield 65	Faa$d:f	I
    //   1702: bipush 20
    //   1704: if_icmpne +9 -> 1713
    //   1707: iconst_1
    //   1708: istore 6
    //   1710: goto +6 -> 1716
    //   1713: iconst_0
    //   1714: istore 6
    //   1716: aload_0
    //   1717: aload_1
    //   1718: iload 6
    //   1720: aload_0
    //   1721: getfield 68	Faa$d:g	Ljava/lang/Object;
    //   1724: aload_2
    //   1725: getfield 68	Faa$d:g	Ljava/lang/Object;
    //   1728: invokeinterface 197 4 0
    //   1733: putfield 68	Faa$d:g	Ljava/lang/Object;
    //   1736: goto +574 -> 2310
    //   1739: aload_0
    //   1740: getfield 65	Faa$d:f	I
    //   1743: bipush 19
    //   1745: if_icmpne +9 -> 1754
    //   1748: iconst_1
    //   1749: istore 6
    //   1751: goto +6 -> 1757
    //   1754: iconst_0
    //   1755: istore 6
    //   1757: aload_0
    //   1758: aload_1
    //   1759: iload 6
    //   1761: aload_0
    //   1762: getfield 68	Faa$d:g	Ljava/lang/Object;
    //   1765: aload_2
    //   1766: getfield 68	Faa$d:g	Ljava/lang/Object;
    //   1769: invokeinterface 197 4 0
    //   1774: putfield 68	Faa$d:g	Ljava/lang/Object;
    //   1777: goto +533 -> 2310
    //   1780: aload_0
    //   1781: getfield 65	Faa$d:f	I
    //   1784: bipush 18
    //   1786: if_icmpne +9 -> 1795
    //   1789: iconst_1
    //   1790: istore 6
    //   1792: goto +6 -> 1798
    //   1795: iconst_0
    //   1796: istore 6
    //   1798: aload_0
    //   1799: aload_1
    //   1800: iload 6
    //   1802: aload_0
    //   1803: getfield 68	Faa$d:g	Ljava/lang/Object;
    //   1806: aload_2
    //   1807: getfield 68	Faa$d:g	Ljava/lang/Object;
    //   1810: invokeinterface 197 4 0
    //   1815: putfield 68	Faa$d:g	Ljava/lang/Object;
    //   1818: goto +492 -> 2310
    //   1821: aload_0
    //   1822: getfield 65	Faa$d:f	I
    //   1825: bipush 17
    //   1827: if_icmpne +9 -> 1836
    //   1830: iconst_1
    //   1831: istore 6
    //   1833: goto +6 -> 1839
    //   1836: iconst_0
    //   1837: istore 6
    //   1839: aload_0
    //   1840: aload_1
    //   1841: iload 6
    //   1843: aload_0
    //   1844: getfield 68	Faa$d:g	Ljava/lang/Object;
    //   1847: aload_2
    //   1848: getfield 68	Faa$d:g	Ljava/lang/Object;
    //   1851: invokeinterface 197 4 0
    //   1856: putfield 68	Faa$d:g	Ljava/lang/Object;
    //   1859: goto +451 -> 2310
    //   1862: aload_0
    //   1863: getfield 65	Faa$d:f	I
    //   1866: bipush 11
    //   1868: if_icmpne +9 -> 1877
    //   1871: iconst_1
    //   1872: istore 6
    //   1874: goto +6 -> 1880
    //   1877: iconst_0
    //   1878: istore 6
    //   1880: aload_0
    //   1881: aload_1
    //   1882: iload 6
    //   1884: aload_0
    //   1885: getfield 68	Faa$d:g	Ljava/lang/Object;
    //   1888: aload_2
    //   1889: getfield 68	Faa$d:g	Ljava/lang/Object;
    //   1892: invokeinterface 197 4 0
    //   1897: putfield 68	Faa$d:g	Ljava/lang/Object;
    //   1900: goto +410 -> 2310
    //   1903: aload_0
    //   1904: getfield 65	Faa$d:f	I
    //   1907: bipush 10
    //   1909: if_icmpne +9 -> 1918
    //   1912: iconst_1
    //   1913: istore 6
    //   1915: goto +6 -> 1921
    //   1918: iconst_0
    //   1919: istore 6
    //   1921: aload_0
    //   1922: aload_1
    //   1923: iload 6
    //   1925: aload_0
    //   1926: getfield 68	Faa$d:g	Ljava/lang/Object;
    //   1929: aload_2
    //   1930: getfield 68	Faa$d:g	Ljava/lang/Object;
    //   1933: invokeinterface 197 4 0
    //   1938: putfield 68	Faa$d:g	Ljava/lang/Object;
    //   1941: goto +369 -> 2310
    //   1944: aload_0
    //   1945: getfield 65	Faa$d:f	I
    //   1948: bipush 9
    //   1950: if_icmpne +9 -> 1959
    //   1953: iconst_1
    //   1954: istore 6
    //   1956: goto +6 -> 1962
    //   1959: iconst_0
    //   1960: istore 6
    //   1962: aload_0
    //   1963: aload_1
    //   1964: iload 6
    //   1966: aload_0
    //   1967: getfield 68	Faa$d:g	Ljava/lang/Object;
    //   1970: aload_2
    //   1971: getfield 68	Faa$d:g	Ljava/lang/Object;
    //   1974: invokeinterface 197 4 0
    //   1979: putfield 68	Faa$d:g	Ljava/lang/Object;
    //   1982: goto +328 -> 2310
    //   1985: aload_0
    //   1986: getfield 65	Faa$d:f	I
    //   1989: bipush 8
    //   1991: if_icmpne +9 -> 2000
    //   1994: iconst_1
    //   1995: istore 6
    //   1997: goto +6 -> 2003
    //   2000: iconst_0
    //   2001: istore 6
    //   2003: aload_0
    //   2004: aload_1
    //   2005: iload 6
    //   2007: aload_0
    //   2008: getfield 68	Faa$d:g	Ljava/lang/Object;
    //   2011: aload_2
    //   2012: getfield 68	Faa$d:g	Ljava/lang/Object;
    //   2015: invokeinterface 197 4 0
    //   2020: putfield 68	Faa$d:g	Ljava/lang/Object;
    //   2023: goto +287 -> 2310
    //   2026: aload_0
    //   2027: getfield 65	Faa$d:f	I
    //   2030: bipush 7
    //   2032: if_icmpne +9 -> 2041
    //   2035: iconst_1
    //   2036: istore 6
    //   2038: goto +6 -> 2044
    //   2041: iconst_0
    //   2042: istore 6
    //   2044: aload_0
    //   2045: aload_1
    //   2046: iload 6
    //   2048: aload_0
    //   2049: getfield 68	Faa$d:g	Ljava/lang/Object;
    //   2052: aload_2
    //   2053: getfield 68	Faa$d:g	Ljava/lang/Object;
    //   2056: invokeinterface 197 4 0
    //   2061: putfield 68	Faa$d:g	Ljava/lang/Object;
    //   2064: goto +246 -> 2310
    //   2067: aload_0
    //   2068: getfield 65	Faa$d:f	I
    //   2071: bipush 6
    //   2073: if_icmpne +9 -> 2082
    //   2076: iconst_1
    //   2077: istore 6
    //   2079: goto +6 -> 2085
    //   2082: iconst_0
    //   2083: istore 6
    //   2085: aload_0
    //   2086: aload_1
    //   2087: iload 6
    //   2089: aload_0
    //   2090: getfield 68	Faa$d:g	Ljava/lang/Object;
    //   2093: aload_2
    //   2094: getfield 68	Faa$d:g	Ljava/lang/Object;
    //   2097: invokeinterface 197 4 0
    //   2102: putfield 68	Faa$d:g	Ljava/lang/Object;
    //   2105: goto +205 -> 2310
    //   2108: aload_0
    //   2109: getfield 65	Faa$d:f	I
    //   2112: iconst_5
    //   2113: if_icmpne +9 -> 2122
    //   2116: iconst_1
    //   2117: istore 6
    //   2119: goto +6 -> 2125
    //   2122: iconst_0
    //   2123: istore 6
    //   2125: aload_0
    //   2126: aload_1
    //   2127: iload 6
    //   2129: aload_0
    //   2130: getfield 68	Faa$d:g	Ljava/lang/Object;
    //   2133: aload_2
    //   2134: getfield 68	Faa$d:g	Ljava/lang/Object;
    //   2137: invokeinterface 197 4 0
    //   2142: putfield 68	Faa$d:g	Ljava/lang/Object;
    //   2145: goto +165 -> 2310
    //   2148: aload_0
    //   2149: getfield 65	Faa$d:f	I
    //   2152: bipush 16
    //   2154: if_icmpne +9 -> 2163
    //   2157: iconst_1
    //   2158: istore 6
    //   2160: goto +6 -> 2166
    //   2163: iconst_0
    //   2164: istore 6
    //   2166: aload_0
    //   2167: aload_1
    //   2168: iload 6
    //   2170: aload_0
    //   2171: getfield 68	Faa$d:g	Ljava/lang/Object;
    //   2174: aload_2
    //   2175: getfield 68	Faa$d:g	Ljava/lang/Object;
    //   2178: invokeinterface 197 4 0
    //   2183: putfield 68	Faa$d:g	Ljava/lang/Object;
    //   2186: goto +124 -> 2310
    //   2189: aload_0
    //   2190: getfield 65	Faa$d:f	I
    //   2193: iconst_4
    //   2194: if_icmpne +9 -> 2203
    //   2197: iconst_1
    //   2198: istore 6
    //   2200: goto +6 -> 2206
    //   2203: iconst_0
    //   2204: istore 6
    //   2206: aload_0
    //   2207: aload_1
    //   2208: iload 6
    //   2210: aload_0
    //   2211: getfield 68	Faa$d:g	Ljava/lang/Object;
    //   2214: aload_2
    //   2215: getfield 68	Faa$d:g	Ljava/lang/Object;
    //   2218: invokeinterface 197 4 0
    //   2223: putfield 68	Faa$d:g	Ljava/lang/Object;
    //   2226: goto +84 -> 2310
    //   2229: aload_0
    //   2230: getfield 65	Faa$d:f	I
    //   2233: iconst_2
    //   2234: if_icmpne +9 -> 2243
    //   2237: iconst_1
    //   2238: istore 6
    //   2240: goto +6 -> 2246
    //   2243: iconst_0
    //   2244: istore 6
    //   2246: aload_0
    //   2247: aload_1
    //   2248: iload 6
    //   2250: aload_0
    //   2251: getfield 68	Faa$d:g	Ljava/lang/Object;
    //   2254: aload_2
    //   2255: getfield 68	Faa$d:g	Ljava/lang/Object;
    //   2258: invokeinterface 197 4 0
    //   2263: putfield 68	Faa$d:g	Ljava/lang/Object;
    //   2266: goto +44 -> 2310
    //   2269: aload_0
    //   2270: getfield 65	Faa$d:f	I
    //   2273: istore 4
    //   2275: iconst_1
    //   2276: istore 6
    //   2278: iload 4
    //   2280: iconst_1
    //   2281: if_icmpne +6 -> 2287
    //   2284: goto +6 -> 2290
    //   2287: iconst_0
    //   2288: istore 6
    //   2290: aload_0
    //   2291: aload_1
    //   2292: iload 6
    //   2294: aload_0
    //   2295: getfield 68	Faa$d:g	Ljava/lang/Object;
    //   2298: aload_2
    //   2299: getfield 68	Faa$d:g	Ljava/lang/Object;
    //   2302: invokeinterface 197 4 0
    //   2307: putfield 68	Faa$d:g	Ljava/lang/Object;
    //   2310: aload_1
    //   2311: getstatic 202	PT$h:a	LPT$h;
    //   2314: if_acmpne +20 -> 2334
    //   2317: aload_2
    //   2318: getfield 65	Faa$d:f	I
    //   2321: istore 4
    //   2323: iload 4
    //   2325: ifeq +9 -> 2334
    //   2328: aload_0
    //   2329: iload 4
    //   2331: putfield 65	Faa$d:f	I
    //   2334: aload_0
    //   2335: areturn
    //   2336: new 12	Faa$d$a
    //   2339: dup
    //   2340: aconst_null
    //   2341: invokespecial 205	Faa$d$a:<init>	(LQY;)V
    //   2344: areturn
    //   2345: aconst_null
    //   2346: areturn
    //   2347: getstatic 59	Faa$d:d	LFaa$d;
    //   2350: areturn
    //   2351: new 2	Faa$d
    //   2354: dup
    //   2355: invokespecial 57	Faa$d:<init>	()V
    //   2358: areturn
    // Local variable table:
    //   start	length	slot	name	signature
    //   0	2359	0	this	d
    //   0	2359	1	parami	PT.i
    //   0	2359	2	paramObject1	Object
    //   0	2359	3	paramObject2	Object
    //   121	2209	4	i	int
    //   132	154	5	j	int
    //   290	2003	6	bool	boolean
    // Exception table:
    //   from	to	target	type
    //   73	94	100	finally
    //   94	97	100	finally
    //   101	104	100	finally
    //   128	134	1467	finally
    //   284	292	1467	finally
    //   295	318	1467	finally
    //   323	335	1467	finally
    //   339	359	1467	finally
    //   359	365	1467	finally
    //   368	391	1467	finally
    //   396	408	1467	finally
    //   412	432	1467	finally
    //   432	438	1467	finally
    //   441	464	1467	finally
    //   469	481	1467	finally
    //   485	505	1467	finally
    //   505	511	1467	finally
    //   514	537	1467	finally
    //   542	554	1467	finally
    //   558	578	1467	finally
    //   578	584	1467	finally
    //   587	610	1467	finally
    //   615	627	1467	finally
    //   631	651	1467	finally
    //   651	657	1467	finally
    //   660	683	1467	finally
    //   688	700	1467	finally
    //   704	724	1467	finally
    //   724	730	1467	finally
    //   733	756	1467	finally
    //   761	773	1467	finally
    //   777	797	1467	finally
    //   797	803	1467	finally
    //   806	829	1467	finally
    //   834	846	1467	finally
    //   850	870	1467	finally
    //   870	876	1467	finally
    //   879	902	1467	finally
    //   907	919	1467	finally
    //   923	943	1467	finally
    //   943	949	1467	finally
    //   952	975	1467	finally
    //   980	992	1467	finally
    //   996	1016	1467	finally
    //   1016	1022	1467	finally
    //   1025	1048	1467	finally
    //   1053	1065	1467	finally
    //   1069	1089	1467	finally
    //   1089	1095	1467	finally
    //   1098	1120	1467	finally
    //   1125	1137	1467	finally
    //   1141	1161	1467	finally
    //   1161	1166	1467	finally
    //   1169	1191	1467	finally
    //   1196	1208	1467	finally
    //   1212	1232	1467	finally
    //   1232	1237	1467	finally
    //   1240	1262	1467	finally
    //   1267	1279	1467	finally
    //   1283	1303	1467	finally
    //   1303	1308	1467	finally
    //   1311	1333	1467	finally
    //   1338	1350	1467	finally
    //   1354	1374	1467	finally
    //   1374	1379	1467	finally
    //   1382	1404	1467	finally
    //   1409	1421	1467	finally
    //   1425	1445	1467	finally
    //   1445	1450	1467	finally
    //   1472	1501	1467	finally
    //   1502	1519	1467	finally
    //   128	134	1471	java/io/IOException
    //   284	292	1471	java/io/IOException
    //   295	318	1471	java/io/IOException
    //   323	335	1471	java/io/IOException
    //   339	359	1471	java/io/IOException
    //   359	365	1471	java/io/IOException
    //   368	391	1471	java/io/IOException
    //   396	408	1471	java/io/IOException
    //   412	432	1471	java/io/IOException
    //   432	438	1471	java/io/IOException
    //   441	464	1471	java/io/IOException
    //   469	481	1471	java/io/IOException
    //   485	505	1471	java/io/IOException
    //   505	511	1471	java/io/IOException
    //   514	537	1471	java/io/IOException
    //   542	554	1471	java/io/IOException
    //   558	578	1471	java/io/IOException
    //   578	584	1471	java/io/IOException
    //   587	610	1471	java/io/IOException
    //   615	627	1471	java/io/IOException
    //   631	651	1471	java/io/IOException
    //   651	657	1471	java/io/IOException
    //   660	683	1471	java/io/IOException
    //   688	700	1471	java/io/IOException
    //   704	724	1471	java/io/IOException
    //   724	730	1471	java/io/IOException
    //   733	756	1471	java/io/IOException
    //   761	773	1471	java/io/IOException
    //   777	797	1471	java/io/IOException
    //   797	803	1471	java/io/IOException
    //   806	829	1471	java/io/IOException
    //   834	846	1471	java/io/IOException
    //   850	870	1471	java/io/IOException
    //   870	876	1471	java/io/IOException
    //   879	902	1471	java/io/IOException
    //   907	919	1471	java/io/IOException
    //   923	943	1471	java/io/IOException
    //   943	949	1471	java/io/IOException
    //   952	975	1471	java/io/IOException
    //   980	992	1471	java/io/IOException
    //   996	1016	1471	java/io/IOException
    //   1016	1022	1471	java/io/IOException
    //   1025	1048	1471	java/io/IOException
    //   1053	1065	1471	java/io/IOException
    //   1069	1089	1471	java/io/IOException
    //   1089	1095	1471	java/io/IOException
    //   1098	1120	1471	java/io/IOException
    //   1125	1137	1471	java/io/IOException
    //   1141	1161	1471	java/io/IOException
    //   1161	1166	1471	java/io/IOException
    //   1169	1191	1471	java/io/IOException
    //   1196	1208	1471	java/io/IOException
    //   1212	1232	1471	java/io/IOException
    //   1232	1237	1471	java/io/IOException
    //   1240	1262	1471	java/io/IOException
    //   1267	1279	1471	java/io/IOException
    //   1283	1303	1471	java/io/IOException
    //   1303	1308	1471	java/io/IOException
    //   1311	1333	1471	java/io/IOException
    //   1338	1350	1471	java/io/IOException
    //   1354	1374	1471	java/io/IOException
    //   1374	1379	1471	java/io/IOException
    //   1382	1404	1471	java/io/IOException
    //   1409	1421	1471	java/io/IOException
    //   1425	1445	1471	java/io/IOException
    //   1445	1450	1471	java/io/IOException
    //   128	134	1501	RT
    //   284	292	1501	RT
    //   295	318	1501	RT
    //   323	335	1501	RT
    //   339	359	1501	RT
    //   359	365	1501	RT
    //   368	391	1501	RT
    //   396	408	1501	RT
    //   412	432	1501	RT
    //   432	438	1501	RT
    //   441	464	1501	RT
    //   469	481	1501	RT
    //   485	505	1501	RT
    //   505	511	1501	RT
    //   514	537	1501	RT
    //   542	554	1501	RT
    //   558	578	1501	RT
    //   578	584	1501	RT
    //   587	610	1501	RT
    //   615	627	1501	RT
    //   631	651	1501	RT
    //   651	657	1501	RT
    //   660	683	1501	RT
    //   688	700	1501	RT
    //   704	724	1501	RT
    //   724	730	1501	RT
    //   733	756	1501	RT
    //   761	773	1501	RT
    //   777	797	1501	RT
    //   797	803	1501	RT
    //   806	829	1501	RT
    //   834	846	1501	RT
    //   850	870	1501	RT
    //   870	876	1501	RT
    //   879	902	1501	RT
    //   907	919	1501	RT
    //   923	943	1501	RT
    //   943	949	1501	RT
    //   952	975	1501	RT
    //   980	992	1501	RT
    //   996	1016	1501	RT
    //   1016	1022	1501	RT
    //   1025	1048	1501	RT
    //   1053	1065	1501	RT
    //   1069	1089	1501	RT
    //   1089	1095	1501	RT
    //   1098	1120	1501	RT
    //   1125	1137	1501	RT
    //   1141	1161	1501	RT
    //   1161	1166	1501	RT
    //   1169	1191	1501	RT
    //   1196	1208	1501	RT
    //   1212	1232	1501	RT
    //   1232	1237	1501	RT
    //   1240	1262	1501	RT
    //   1267	1279	1501	RT
    //   1283	1303	1501	RT
    //   1303	1308	1501	RT
    //   1311	1333	1501	RT
    //   1338	1350	1501	RT
    //   1354	1374	1501	RT
    //   1374	1379	1501	RT
    //   1382	1404	1501	RT
    //   1409	1421	1501	RT
    //   1425	1445	1501	RT
    //   1445	1450	1501	RT
  }
  
  public void a(JT paramJT)
    throws IOException
  {
    if (this.f == 1) {
      paramJT.b(1, (Faa.d.g)this.g);
    }
    if (this.f == 2) {
      paramJT.b(2, (Faa.d.b)this.g);
    }
    if (this.f == 3) {
      paramJT.b(3, (Faa.d.d)this.g);
    }
    if (this.f == 4) {
      paramJT.b(4, (Faa.d.b)this.g);
    }
    if (this.f == 5) {
      paramJT.b(5, (Faa.d.b)this.g);
    }
    if (this.f == 6) {
      paramJT.b(6, (Faa.d.i)this.g);
    }
    if (this.f == 7) {
      paramJT.b(7, (Faa.d.i)this.g);
    }
    if (this.f == 8) {
      paramJT.b(8, (Faa.d.i)this.g);
    }
    if (this.f == 9) {
      paramJT.b(9, (Faa.d.i)this.g);
    }
    if (this.f == 10) {
      paramJT.b(10, (Faa.d.i)this.g);
    }
    if (this.f == 11) {
      paramJT.b(11, (Faa.d.i)this.g);
    }
    if (this.f == 16) {
      paramJT.b(16, (Faa.d.b)this.g);
    }
    if (this.f == 17) {
      paramJT.b(17, (Faa.d.i)this.g);
    }
    if (this.f == 18) {
      paramJT.b(18, (Faa.d.i)this.g);
    }
    if (this.f == 19) {
      paramJT.b(19, (Faa.d.i)this.g);
    }
    if (this.f == 20) {
      paramJT.b(20, (Faa.d.i)this.g);
    }
  }
  
  public int d()
  {
    int i = this.c;
    if (i != -1) {
      return i;
    }
    i = 0;
    if (this.f == 1) {
      i = 0 + JT.a(1, (Faa.d.g)this.g);
    }
    int j = i;
    if (this.f == 2) {
      j = i + JT.a(2, (Faa.d.b)this.g);
    }
    i = j;
    if (this.f == 3) {
      i = j + JT.a(3, (Faa.d.d)this.g);
    }
    j = i;
    if (this.f == 4) {
      j = i + JT.a(4, (Faa.d.b)this.g);
    }
    i = j;
    if (this.f == 5) {
      i = j + JT.a(5, (Faa.d.b)this.g);
    }
    j = i;
    if (this.f == 6) {
      j = i + JT.a(6, (Faa.d.i)this.g);
    }
    int k = j;
    if (this.f == 7) {
      k = j + JT.a(7, (Faa.d.i)this.g);
    }
    i = k;
    if (this.f == 8) {
      i = k + JT.a(8, (Faa.d.i)this.g);
    }
    j = i;
    if (this.f == 9) {
      j = i + JT.a(9, (Faa.d.i)this.g);
    }
    i = j;
    if (this.f == 10) {
      i = j + JT.a(10, (Faa.d.i)this.g);
    }
    k = i;
    if (this.f == 11) {
      k = i + JT.a(11, (Faa.d.i)this.g);
    }
    j = k;
    if (this.f == 16) {
      j = k + JT.a(16, (Faa.d.b)this.g);
    }
    i = j;
    if (this.f == 17) {
      i = j + JT.a(17, (Faa.d.i)this.g);
    }
    j = i;
    if (this.f == 18) {
      j = i + JT.a(18, (Faa.d.i)this.g);
    }
    i = j;
    if (this.f == 19) {
      i = j + JT.a(19, (Faa.d.i)this.g);
    }
    j = i;
    if (this.f == 20) {
      j = i + JT.a(20, (Faa.d.i)this.g);
    }
    this.c = j;
    return j;
  }
  
  public Faa.d.f k()
  {
    return Faa.d.f.a(this.f);
  }
  
  public static final class a
    extends PT.a<Faa.d, a>
    implements Faa.e
  {
    private a()
    {
      super();
    }
    
    public a a(Faa.d.b paramb)
    {
      c();
      Faa.d.a((Faa.d)this.b, paramb);
      return this;
    }
    
    public a a(Faa.d.d paramd)
    {
      c();
      Faa.d.a((Faa.d)this.b, paramd);
      return this;
    }
    
    public a a(Faa.d.g paramg)
    {
      c();
      Faa.d.a((Faa.d)this.b, paramg);
      return this;
    }
    
    public a a(Faa.d.i parami)
    {
      c();
      Faa.d.c((Faa.d)this.b, parami);
      return this;
    }
    
    public a b(Faa.d.b paramb)
    {
      c();
      Faa.d.b((Faa.d)this.b, paramb);
      return this;
    }
    
    public a b(Faa.d.i parami)
    {
      c();
      Faa.d.d((Faa.d)this.b, parami);
      return this;
    }
    
    public a c(Faa.d.b paramb)
    {
      c();
      Faa.d.c((Faa.d)this.b, paramb);
      return this;
    }
    
    public a c(Faa.d.i parami)
    {
      c();
      Faa.d.h((Faa.d)this.b, parami);
      return this;
    }
    
    public a d(Faa.d.i parami)
    {
      c();
      Faa.d.a((Faa.d)this.b, parami);
      return this;
    }
    
    public a e(Faa.d.i parami)
    {
      c();
      Faa.d.e((Faa.d)this.b, parami);
      return this;
    }
    
    public a f(Faa.d.i parami)
    {
      c();
      Faa.d.g((Faa.d)this.b, parami);
      return this;
    }
    
    public a g(Faa.d.i parami)
    {
      c();
      Faa.d.f((Faa.d)this.b, parami);
      return this;
    }
    
    public a h(Faa.d.i parami)
    {
      c();
      Faa.d.b((Faa.d)this.b, parami);
      return this;
    }
  }
  
  public static final class b
    extends PT<b, Faa.d.b.a>
    implements Faa.d.c
  {
    private static final b d = new b();
    private static volatile YT<b> e;
    private String f = "";
    private float g;
    
    static
    {
      d.h();
    }
    
    private void a(float paramFloat)
    {
      this.g = paramFloat;
    }
    
    private void b(String paramString)
    {
      if (paramString != null)
      {
        this.f = paramString;
        return;
      }
      throw new NullPointerException();
    }
    
    public static Faa.d.b.a l()
    {
      return (Faa.d.b.a)d.c();
    }
    
    public static YT<b> parser()
    {
      return d.e();
    }
    
    /* Error */
    protected final Object a(PT.i parami, Object paramObject1, Object paramObject2)
    {
      // Byte code:
      //   0: getstatic 77	QY:a	[I
      //   3: aload_1
      //   4: invokevirtual 83	java/lang/Enum:ordinal	()I
      //   7: iaload
      //   8: istore 4
      //   10: iconst_0
      //   11: istore 5
      //   13: iconst_0
      //   14: istore 6
      //   16: iload 4
      //   18: tableswitch	default:+46->64, 1:+361->379, 2:+357->375, 3:+355->373, 4:+346->364, 5:+238->256, 6:+100->118, 7:+234->252, 8:+54->72
      //   64: new 85	java/lang/UnsupportedOperationException
      //   67: dup
      //   68: invokespecial 86	java/lang/UnsupportedOperationException:<init>	()V
      //   71: athrow
      //   72: getstatic 88	Faa$d$b:e	LYT;
      //   75: ifnonnull +39 -> 114
      //   78: ldc 2
      //   80: monitorenter
      //   81: getstatic 88	Faa$d$b:e	LYT;
      //   84: ifnonnull +18 -> 102
      //   87: new 90	PT$b
      //   90: astore_1
      //   91: aload_1
      //   92: getstatic 31	Faa$d$b:d	LFaa$d$b;
      //   95: invokespecial 93	PT$b:<init>	(LPT;)V
      //   98: aload_1
      //   99: putstatic 88	Faa$d$b:e	LYT;
      //   102: ldc 2
      //   104: monitorexit
      //   105: goto +9 -> 114
      //   108: astore_1
      //   109: ldc 2
      //   111: monitorexit
      //   112: aload_1
      //   113: athrow
      //   114: getstatic 88	Faa$d$b:e	LYT;
      //   117: areturn
      //   118: aload_2
      //   119: checkcast 95	HT
      //   122: astore_1
      //   123: aload_3
      //   124: checkcast 97	LT
      //   127: astore_2
      //   128: iload 6
      //   130: ifne +122 -> 252
      //   133: aload_1
      //   134: invokevirtual 100	HT:n	()I
      //   137: istore 4
      //   139: iload 4
      //   141: ifeq +51 -> 192
      //   144: iload 4
      //   146: bipush 10
      //   148: if_icmpeq +33 -> 181
      //   151: iload 4
      //   153: bipush 21
      //   155: if_icmpeq +15 -> 170
      //   158: aload_1
      //   159: iload 4
      //   161: invokevirtual 103	HT:e	(I)Z
      //   164: ifne -36 -> 128
      //   167: goto +25 -> 192
      //   170: aload_0
      //   171: aload_1
      //   172: invokevirtual 106	HT:e	()F
      //   175: putfield 43	Faa$d$b:g	F
      //   178: goto -50 -> 128
      //   181: aload_0
      //   182: aload_1
      //   183: invokevirtual 110	HT:m	()Ljava/lang/String;
      //   186: putfield 40	Faa$d$b:f	Ljava/lang/String;
      //   189: goto -61 -> 128
      //   192: iconst_1
      //   193: istore 6
      //   195: goto -67 -> 128
      //   198: astore_1
      //   199: goto +51 -> 250
      //   202: astore_2
      //   203: new 112	java/lang/RuntimeException
      //   206: astore_3
      //   207: new 70	RT
      //   210: astore_1
      //   211: aload_1
      //   212: aload_2
      //   213: invokevirtual 115	java/io/IOException:getMessage	()Ljava/lang/String;
      //   216: invokespecial 117	RT:<init>	(Ljava/lang/String;)V
      //   219: aload_1
      //   220: aload_0
      //   221: invokevirtual 120	RT:a	(LVT;)LRT;
      //   224: pop
      //   225: aload_3
      //   226: aload_1
      //   227: invokespecial 123	java/lang/RuntimeException:<init>	(Ljava/lang/Throwable;)V
      //   230: aload_3
      //   231: athrow
      //   232: astore_1
      //   233: new 112	java/lang/RuntimeException
      //   236: astore_2
      //   237: aload_1
      //   238: aload_0
      //   239: invokevirtual 120	RT:a	(LVT;)LRT;
      //   242: pop
      //   243: aload_2
      //   244: aload_1
      //   245: invokespecial 123	java/lang/RuntimeException:<init>	(Ljava/lang/Throwable;)V
      //   248: aload_2
      //   249: athrow
      //   250: aload_1
      //   251: athrow
      //   252: getstatic 31	Faa$d$b:d	LFaa$d$b;
      //   255: areturn
      //   256: aload_2
      //   257: checkcast 125	PT$j
      //   260: astore_1
      //   261: aload_3
      //   262: checkcast 2	Faa$d$b
      //   265: astore_2
      //   266: aload_0
      //   267: aload_1
      //   268: aload_0
      //   269: getfield 40	Faa$d$b:f	Ljava/lang/String;
      //   272: invokevirtual 131	java/lang/String:isEmpty	()Z
      //   275: iconst_1
      //   276: ixor
      //   277: aload_0
      //   278: getfield 40	Faa$d$b:f	Ljava/lang/String;
      //   281: aload_2
      //   282: getfield 40	Faa$d$b:f	Ljava/lang/String;
      //   285: invokevirtual 131	java/lang/String:isEmpty	()Z
      //   288: iconst_1
      //   289: ixor
      //   290: aload_2
      //   291: getfield 40	Faa$d$b:f	Ljava/lang/String;
      //   294: invokeinterface 134 5 0
      //   299: putfield 40	Faa$d$b:f	Ljava/lang/String;
      //   302: aload_0
      //   303: getfield 43	Faa$d$b:g	F
      //   306: fconst_0
      //   307: fcmpl
      //   308: ifeq +9 -> 317
      //   311: iconst_1
      //   312: istore 7
      //   314: goto +6 -> 320
      //   317: iconst_0
      //   318: istore 7
      //   320: aload_0
      //   321: getfield 43	Faa$d$b:g	F
      //   324: fstore 8
      //   326: aload_2
      //   327: getfield 43	Faa$d$b:g	F
      //   330: fconst_0
      //   331: fcmpl
      //   332: ifeq +6 -> 338
      //   335: iconst_1
      //   336: istore 5
      //   338: aload_0
      //   339: aload_1
      //   340: iload 7
      //   342: fload 8
      //   344: iload 5
      //   346: aload_2
      //   347: getfield 43	Faa$d$b:g	F
      //   350: invokeinterface 137 5 0
      //   355: putfield 43	Faa$d$b:g	F
      //   358: getstatic 142	PT$h:a	LPT$h;
      //   361: astore_1
      //   362: aload_0
      //   363: areturn
      //   364: new 15	Faa$d$b$a
      //   367: dup
      //   368: aconst_null
      //   369: invokespecial 145	Faa$d$b$a:<init>	(LQY;)V
      //   372: areturn
      //   373: aconst_null
      //   374: areturn
      //   375: getstatic 31	Faa$d$b:d	LFaa$d$b;
      //   378: areturn
      //   379: new 2	Faa$d$b
      //   382: dup
      //   383: invokespecial 29	Faa$d$b:<init>	()V
      //   386: areturn
      // Local variable table:
      //   start	length	slot	name	signature
      //   0	387	0	this	b
      //   0	387	1	parami	PT.i
      //   0	387	2	paramObject1	Object
      //   0	387	3	paramObject2	Object
      //   8	152	4	i	int
      //   11	334	5	bool1	boolean
      //   14	180	6	j	int
      //   312	29	7	bool2	boolean
      //   324	19	8	f1	float
      // Exception table:
      //   from	to	target	type
      //   81	102	108	finally
      //   102	105	108	finally
      //   109	112	108	finally
      //   133	139	198	finally
      //   158	167	198	finally
      //   170	178	198	finally
      //   181	189	198	finally
      //   203	232	198	finally
      //   233	250	198	finally
      //   133	139	202	java/io/IOException
      //   158	167	202	java/io/IOException
      //   170	178	202	java/io/IOException
      //   181	189	202	java/io/IOException
      //   133	139	232	RT
      //   158	167	232	RT
      //   170	178	232	RT
      //   181	189	232	RT
    }
    
    public void a(JT paramJT)
      throws IOException
    {
      if (!this.f.isEmpty()) {
        paramJT.b(1, k());
      }
      float f1 = this.g;
      if (f1 != 0.0F) {
        paramJT.b(2, f1);
      }
    }
    
    public int d()
    {
      int i = this.c;
      if (i != -1) {
        return i;
      }
      i = 0;
      if (!this.f.isEmpty()) {
        i = 0 + JT.a(1, k());
      }
      float f1 = this.g;
      int j = i;
      if (f1 != 0.0F) {
        j = i + JT.a(2, f1);
      }
      this.c = j;
      return j;
    }
    
    public String k()
    {
      return this.f;
    }
    
    public static final class a
      extends PT.a<Faa.d.b, a>
      implements Faa.d.c
    {
      private a()
      {
        super();
      }
      
      public a a(float paramFloat)
      {
        c();
        Faa.d.b.a((Faa.d.b)this.b, paramFloat);
        return this;
      }
      
      public a a(String paramString)
      {
        c();
        Faa.d.b.a((Faa.d.b)this.b, paramString);
        return this;
      }
    }
  }
  
  public static abstract interface c
    extends WT
  {}
  
  public static final class d
    extends PT<d, Faa.d.d.a>
    implements Faa.d.e
  {
    private static final d d = new d();
    private static volatile YT<d> e;
    private oZ f;
    
    static
    {
      d.h();
    }
    
    private void a(oZ paramoZ)
    {
      if (paramoZ != null)
      {
        this.f = paramoZ;
        return;
      }
      throw new NullPointerException();
    }
    
    public static Faa.d.d.a l()
    {
      return (Faa.d.d.a)d.c();
    }
    
    public static YT<d> parser()
    {
      return d.e();
    }
    
    /* Error */
    protected final Object a(PT.i parami, Object paramObject1, Object paramObject2)
    {
      // Byte code:
      //   0: getstatic 66	QY:a	[I
      //   3: aload_1
      //   4: invokevirtual 72	java/lang/Enum:ordinal	()I
      //   7: iaload
      //   8: tableswitch	default:+48->56, 1:+331->339, 2:+327->335, 3:+325->333, 4:+316->324, 5:+279->287, 6:+102->110, 7:+275->283, 8:+56->64
      //   56: new 74	java/lang/UnsupportedOperationException
      //   59: dup
      //   60: invokespecial 75	java/lang/UnsupportedOperationException:<init>	()V
      //   63: athrow
      //   64: getstatic 77	Faa$d$d:e	LYT;
      //   67: ifnonnull +39 -> 106
      //   70: ldc 2
      //   72: monitorenter
      //   73: getstatic 77	Faa$d$d:e	LYT;
      //   76: ifnonnull +18 -> 94
      //   79: new 79	PT$b
      //   82: astore_1
      //   83: aload_1
      //   84: getstatic 28	Faa$d$d:d	LFaa$d$d;
      //   87: invokespecial 82	PT$b:<init>	(LPT;)V
      //   90: aload_1
      //   91: putstatic 77	Faa$d$d:e	LYT;
      //   94: ldc 2
      //   96: monitorexit
      //   97: goto +9 -> 106
      //   100: astore_1
      //   101: ldc 2
      //   103: monitorexit
      //   104: aload_1
      //   105: athrow
      //   106: getstatic 77	Faa$d$d:e	LYT;
      //   109: areturn
      //   110: aload_2
      //   111: checkcast 84	HT
      //   114: astore_2
      //   115: aload_3
      //   116: checkcast 86	LT
      //   119: astore_3
      //   120: iconst_0
      //   121: istore 4
      //   123: iload 4
      //   125: ifne +158 -> 283
      //   128: aload_2
      //   129: invokevirtual 89	HT:n	()I
      //   132: istore 5
      //   134: iload 5
      //   136: ifeq +87 -> 223
      //   139: iload 5
      //   141: bipush 10
      //   143: if_icmpeq +15 -> 158
      //   146: aload_2
      //   147: iload 5
      //   149: invokevirtual 92	HT:e	(I)Z
      //   152: ifne -29 -> 123
      //   155: goto +68 -> 223
      //   158: aload_0
      //   159: getfield 39	Faa$d$d:f	LoZ;
      //   162: ifnull +17 -> 179
      //   165: aload_0
      //   166: getfield 39	Faa$d$d:f	LoZ;
      //   169: invokevirtual 50	PT:c	()LPT$a;
      //   172: checkcast 94	oZ$a
      //   175: astore_1
      //   176: goto +5 -> 181
      //   179: aconst_null
      //   180: astore_1
      //   181: aload_0
      //   182: aload_2
      //   183: invokestatic 98	oZ:parser	()LYT;
      //   186: aload_3
      //   187: invokevirtual 101	HT:a	(LYT;LLT;)LVT;
      //   190: checkcast 96	oZ
      //   193: putfield 39	Faa$d$d:f	LoZ;
      //   196: aload_1
      //   197: ifnull -74 -> 123
      //   200: aload_1
      //   201: aload_0
      //   202: getfield 39	Faa$d$d:f	LoZ;
      //   205: invokevirtual 107	PT$a:b	(LPT;)LPT$a;
      //   208: pop
      //   209: aload_0
      //   210: aload_1
      //   211: invokevirtual 110	PT$a:b	()LPT;
      //   214: checkcast 96	oZ
      //   217: putfield 39	Faa$d$d:f	LoZ;
      //   220: goto -97 -> 123
      //   223: iconst_1
      //   224: istore 4
      //   226: goto -103 -> 123
      //   229: astore_1
      //   230: goto +51 -> 281
      //   233: astore_3
      //   234: new 112	java/lang/RuntimeException
      //   237: astore_2
      //   238: new 59	RT
      //   241: astore_1
      //   242: aload_1
      //   243: aload_3
      //   244: invokevirtual 116	java/io/IOException:getMessage	()Ljava/lang/String;
      //   247: invokespecial 119	RT:<init>	(Ljava/lang/String;)V
      //   250: aload_1
      //   251: aload_0
      //   252: invokevirtual 122	RT:a	(LVT;)LRT;
      //   255: pop
      //   256: aload_2
      //   257: aload_1
      //   258: invokespecial 125	java/lang/RuntimeException:<init>	(Ljava/lang/Throwable;)V
      //   261: aload_2
      //   262: athrow
      //   263: astore_1
      //   264: new 112	java/lang/RuntimeException
      //   267: astore_2
      //   268: aload_1
      //   269: aload_0
      //   270: invokevirtual 122	RT:a	(LVT;)LRT;
      //   273: pop
      //   274: aload_2
      //   275: aload_1
      //   276: invokespecial 125	java/lang/RuntimeException:<init>	(Ljava/lang/Throwable;)V
      //   279: aload_2
      //   280: athrow
      //   281: aload_1
      //   282: athrow
      //   283: getstatic 28	Faa$d$d:d	LFaa$d$d;
      //   286: areturn
      //   287: aload_2
      //   288: checkcast 127	PT$j
      //   291: astore_1
      //   292: aload_3
      //   293: checkcast 2	Faa$d$d
      //   296: astore_2
      //   297: aload_0
      //   298: aload_1
      //   299: aload_0
      //   300: getfield 39	Faa$d$d:f	LoZ;
      //   303: aload_2
      //   304: getfield 39	Faa$d$d:f	LoZ;
      //   307: invokeinterface 130 3 0
      //   312: checkcast 96	oZ
      //   315: putfield 39	Faa$d$d:f	LoZ;
      //   318: getstatic 135	PT$h:a	LPT$h;
      //   321: astore_1
      //   322: aload_0
      //   323: areturn
      //   324: new 14	Faa$d$d$a
      //   327: dup
      //   328: aconst_null
      //   329: invokespecial 138	Faa$d$d$a:<init>	(LQY;)V
      //   332: areturn
      //   333: aconst_null
      //   334: areturn
      //   335: getstatic 28	Faa$d$d:d	LFaa$d$d;
      //   338: areturn
      //   339: new 2	Faa$d$d
      //   342: dup
      //   343: invokespecial 26	Faa$d$d:<init>	()V
      //   346: areturn
      // Local variable table:
      //   start	length	slot	name	signature
      //   0	347	0	this	d
      //   0	347	1	parami	PT.i
      //   0	347	2	paramObject1	Object
      //   0	347	3	paramObject2	Object
      //   121	104	4	i	int
      //   132	16	5	j	int
      // Exception table:
      //   from	to	target	type
      //   73	94	100	finally
      //   94	97	100	finally
      //   101	104	100	finally
      //   128	134	229	finally
      //   146	155	229	finally
      //   158	176	229	finally
      //   181	196	229	finally
      //   200	220	229	finally
      //   234	263	229	finally
      //   264	281	229	finally
      //   128	134	233	java/io/IOException
      //   146	155	233	java/io/IOException
      //   158	176	233	java/io/IOException
      //   181	196	233	java/io/IOException
      //   200	220	233	java/io/IOException
      //   128	134	263	RT
      //   146	155	263	RT
      //   158	176	263	RT
      //   181	196	263	RT
      //   200	220	263	RT
    }
    
    public void a(JT paramJT)
      throws IOException
    {
      if (this.f != null) {
        paramJT.b(1, k());
      }
    }
    
    public int d()
    {
      int i = this.c;
      if (i != -1) {
        return i;
      }
      i = 0;
      if (this.f != null) {
        i = 0 + JT.a(1, k());
      }
      this.c = i;
      return i;
    }
    
    public oZ k()
    {
      oZ localoZ1 = this.f;
      oZ localoZ2 = localoZ1;
      if (localoZ1 == null) {
        localoZ2 = oZ.l();
      }
      return localoZ2;
    }
    
    public static final class a
      extends PT.a<Faa.d.d, a>
      implements Faa.d.e
    {
      private a()
      {
        super();
      }
      
      public a a(oZ paramoZ)
      {
        c();
        Faa.d.d.a((Faa.d.d)this.b, paramoZ);
        return this;
      }
    }
  }
  
  public static abstract interface e
    extends WT
  {}
  
  public static enum f
    implements QT.a
  {
    private final int s;
    
    private f(int paramInt)
    {
      this.s = paramInt;
    }
    
    public static f a(int paramInt)
    {
      switch (paramInt)
      {
      case 12: 
      case 13: 
      case 14: 
      case 15: 
      default: 
        return null;
      case 20: 
        return o;
      case 19: 
        return n;
      case 18: 
        return m;
      case 17: 
        return l;
      case 16: 
        return d;
      case 11: 
        return k;
      case 10: 
        return j;
      case 9: 
        return i;
      case 8: 
        return h;
      case 7: 
        return g;
      case 6: 
        return f;
      case 5: 
        return e;
      case 4: 
        return c;
      case 3: 
        return p;
      case 2: 
        return b;
      case 1: 
        return a;
      }
      return q;
    }
  }
  
  public static final class g
    extends PT<g, Faa.d.g.a>
    implements Faa.d.h
  {
    private static final g d = new g();
    private static volatile YT<g> e;
    private String f = "";
    
    static
    {
      d.h();
    }
    
    private void b(String paramString)
    {
      if (paramString != null)
      {
        this.f = paramString;
        return;
      }
      throw new NullPointerException();
    }
    
    public static Faa.d.g.a l()
    {
      return (Faa.d.g.a)d.c();
    }
    
    public static YT<g> parser()
    {
      return d.e();
    }
    
    /* Error */
    protected final Object a(PT.i parami, Object paramObject1, Object paramObject2)
    {
      // Byte code:
      //   0: getstatic 70	QY:a	[I
      //   3: aload_1
      //   4: invokevirtual 76	java/lang/Enum:ordinal	()I
      //   7: iaload
      //   8: tableswitch	default:+48->56, 1:+292->300, 2:+288->296, 3:+286->294, 4:+277->285, 5:+225->233, 6:+102->110, 7:+221->229, 8:+56->64
      //   56: new 78	java/lang/UnsupportedOperationException
      //   59: dup
      //   60: invokespecial 79	java/lang/UnsupportedOperationException:<init>	()V
      //   63: athrow
      //   64: getstatic 81	Faa$d$g:e	LYT;
      //   67: ifnonnull +39 -> 106
      //   70: ldc 2
      //   72: monitorenter
      //   73: getstatic 81	Faa$d$g:e	LYT;
      //   76: ifnonnull +18 -> 94
      //   79: new 83	PT$b
      //   82: astore_1
      //   83: aload_1
      //   84: getstatic 29	Faa$d$g:d	LFaa$d$g;
      //   87: invokespecial 86	PT$b:<init>	(LPT;)V
      //   90: aload_1
      //   91: putstatic 81	Faa$d$g:e	LYT;
      //   94: ldc 2
      //   96: monitorexit
      //   97: goto +9 -> 106
      //   100: astore_1
      //   101: ldc 2
      //   103: monitorexit
      //   104: aload_1
      //   105: athrow
      //   106: getstatic 81	Faa$d$g:e	LYT;
      //   109: areturn
      //   110: aload_2
      //   111: checkcast 88	HT
      //   114: astore_1
      //   115: aload_3
      //   116: checkcast 90	LT
      //   119: astore_2
      //   120: iconst_0
      //   121: istore 4
      //   123: iload 4
      //   125: ifne +104 -> 229
      //   128: aload_1
      //   129: invokevirtual 93	HT:n	()I
      //   132: istore 5
      //   134: iload 5
      //   136: ifeq +33 -> 169
      //   139: iload 5
      //   141: bipush 10
      //   143: if_icmpeq +15 -> 158
      //   146: aload_1
      //   147: iload 5
      //   149: invokevirtual 96	HT:e	(I)Z
      //   152: ifne -29 -> 123
      //   155: goto +14 -> 169
      //   158: aload_0
      //   159: aload_1
      //   160: invokevirtual 100	HT:m	()Ljava/lang/String;
      //   163: putfield 38	Faa$d$g:f	Ljava/lang/String;
      //   166: goto -43 -> 123
      //   169: iconst_1
      //   170: istore 4
      //   172: goto -49 -> 123
      //   175: astore_1
      //   176: goto +51 -> 227
      //   179: astore_1
      //   180: new 102	java/lang/RuntimeException
      //   183: astore_2
      //   184: new 63	RT
      //   187: astore_3
      //   188: aload_3
      //   189: aload_1
      //   190: invokevirtual 105	java/io/IOException:getMessage	()Ljava/lang/String;
      //   193: invokespecial 107	RT:<init>	(Ljava/lang/String;)V
      //   196: aload_3
      //   197: aload_0
      //   198: invokevirtual 110	RT:a	(LVT;)LRT;
      //   201: pop
      //   202: aload_2
      //   203: aload_3
      //   204: invokespecial 113	java/lang/RuntimeException:<init>	(Ljava/lang/Throwable;)V
      //   207: aload_2
      //   208: athrow
      //   209: astore_2
      //   210: new 102	java/lang/RuntimeException
      //   213: astore_1
      //   214: aload_2
      //   215: aload_0
      //   216: invokevirtual 110	RT:a	(LVT;)LRT;
      //   219: pop
      //   220: aload_1
      //   221: aload_2
      //   222: invokespecial 113	java/lang/RuntimeException:<init>	(Ljava/lang/Throwable;)V
      //   225: aload_1
      //   226: athrow
      //   227: aload_1
      //   228: athrow
      //   229: getstatic 29	Faa$d$g:d	LFaa$d$g;
      //   232: areturn
      //   233: aload_2
      //   234: checkcast 115	PT$j
      //   237: astore_1
      //   238: aload_3
      //   239: checkcast 2	Faa$d$g
      //   242: astore_2
      //   243: aload_0
      //   244: aload_1
      //   245: aload_0
      //   246: getfield 38	Faa$d$g:f	Ljava/lang/String;
      //   249: invokevirtual 121	java/lang/String:isEmpty	()Z
      //   252: iconst_1
      //   253: ixor
      //   254: aload_0
      //   255: getfield 38	Faa$d$g:f	Ljava/lang/String;
      //   258: iconst_1
      //   259: aload_2
      //   260: getfield 38	Faa$d$g:f	Ljava/lang/String;
      //   263: invokevirtual 121	java/lang/String:isEmpty	()Z
      //   266: ixor
      //   267: aload_2
      //   268: getfield 38	Faa$d$g:f	Ljava/lang/String;
      //   271: invokeinterface 124 5 0
      //   276: putfield 38	Faa$d$g:f	Ljava/lang/String;
      //   279: getstatic 129	PT$h:a	LPT$h;
      //   282: astore_1
      //   283: aload_0
      //   284: areturn
      //   285: new 15	Faa$d$g$a
      //   288: dup
      //   289: aconst_null
      //   290: invokespecial 132	Faa$d$g$a:<init>	(LQY;)V
      //   293: areturn
      //   294: aconst_null
      //   295: areturn
      //   296: getstatic 29	Faa$d$g:d	LFaa$d$g;
      //   299: areturn
      //   300: new 2	Faa$d$g
      //   303: dup
      //   304: invokespecial 27	Faa$d$g:<init>	()V
      //   307: areturn
      // Local variable table:
      //   start	length	slot	name	signature
      //   0	308	0	this	g
      //   0	308	1	parami	PT.i
      //   0	308	2	paramObject1	Object
      //   0	308	3	paramObject2	Object
      //   121	50	4	i	int
      //   132	16	5	j	int
      // Exception table:
      //   from	to	target	type
      //   73	94	100	finally
      //   94	97	100	finally
      //   101	104	100	finally
      //   128	134	175	finally
      //   146	155	175	finally
      //   158	166	175	finally
      //   180	209	175	finally
      //   210	227	175	finally
      //   128	134	179	java/io/IOException
      //   146	155	179	java/io/IOException
      //   158	166	179	java/io/IOException
      //   128	134	209	RT
      //   146	155	209	RT
      //   158	166	209	RT
    }
    
    public void a(JT paramJT)
      throws IOException
    {
      if (!this.f.isEmpty()) {
        paramJT.b(1, k());
      }
    }
    
    public int d()
    {
      int i = this.c;
      if (i != -1) {
        return i;
      }
      i = 0;
      if (!this.f.isEmpty()) {
        i = 0 + JT.a(1, k());
      }
      this.c = i;
      return i;
    }
    
    public String k()
    {
      return this.f;
    }
    
    public static final class a
      extends PT.a<Faa.d.g, a>
      implements Faa.d.h
    {
      private a()
      {
        super();
      }
      
      public a a(String paramString)
      {
        c();
        Faa.d.g.a((Faa.d.g)this.b, paramString);
        return this;
      }
    }
  }
  
  public static abstract interface h
    extends WT
  {}
  
  public static final class i
    extends PT<i, Faa.d.i.a>
    implements Faa.d.j
  {
    private static final i d = new i();
    private static volatile YT<i> e;
    private float f;
    
    static
    {
      d.h();
    }
    
    private void a(float paramFloat)
    {
      this.f = paramFloat;
    }
    
    public static Faa.d.i.a k()
    {
      return (Faa.d.i.a)d.c();
    }
    
    public static YT<i> parser()
    {
      return d.e();
    }
    
    /* Error */
    protected final Object a(PT.i parami, Object paramObject1, Object paramObject2)
    {
      // Byte code:
      //   0: getstatic 64	QY:a	[I
      //   3: aload_1
      //   4: invokevirtual 70	java/lang/Enum:ordinal	()I
      //   7: iaload
      //   8: istore 4
      //   10: iconst_0
      //   11: istore 5
      //   13: iconst_0
      //   14: istore 6
      //   16: iload 4
      //   18: tableswitch	default:+46->64, 1:+307->325, 2:+303->321, 3:+301->319, 4:+292->310, 5:+220->238, 6:+100->118, 7:+216->234, 8:+54->72
      //   64: new 72	java/lang/UnsupportedOperationException
      //   67: dup
      //   68: invokespecial 73	java/lang/UnsupportedOperationException:<init>	()V
      //   71: athrow
      //   72: getstatic 75	Faa$d$i:e	LYT;
      //   75: ifnonnull +39 -> 114
      //   78: ldc 2
      //   80: monitorenter
      //   81: getstatic 75	Faa$d$i:e	LYT;
      //   84: ifnonnull +18 -> 102
      //   87: new 77	PT$b
      //   90: astore_1
      //   91: aload_1
      //   92: getstatic 29	Faa$d$i:d	LFaa$d$i;
      //   95: invokespecial 80	PT$b:<init>	(LPT;)V
      //   98: aload_1
      //   99: putstatic 75	Faa$d$i:e	LYT;
      //   102: ldc 2
      //   104: monitorexit
      //   105: goto +9 -> 114
      //   108: astore_1
      //   109: ldc 2
      //   111: monitorexit
      //   112: aload_1
      //   113: athrow
      //   114: getstatic 75	Faa$d$i:e	LYT;
      //   117: areturn
      //   118: aload_2
      //   119: checkcast 82	HT
      //   122: astore_1
      //   123: aload_3
      //   124: checkcast 84	LT
      //   127: astore_2
      //   128: iload 6
      //   130: ifne +104 -> 234
      //   133: aload_1
      //   134: invokevirtual 87	HT:n	()I
      //   137: istore 4
      //   139: iload 4
      //   141: ifeq +33 -> 174
      //   144: iload 4
      //   146: bipush 13
      //   148: if_icmpeq +15 -> 163
      //   151: aload_1
      //   152: iload 4
      //   154: invokevirtual 90	HT:e	(I)Z
      //   157: ifne -29 -> 128
      //   160: goto +14 -> 174
      //   163: aload_0
      //   164: aload_1
      //   165: invokevirtual 93	HT:e	()F
      //   168: putfield 37	Faa$d$i:f	F
      //   171: goto -43 -> 128
      //   174: iconst_1
      //   175: istore 6
      //   177: goto -49 -> 128
      //   180: astore_1
      //   181: goto +51 -> 232
      //   184: astore_1
      //   185: new 95	java/lang/RuntimeException
      //   188: astore_3
      //   189: new 57	RT
      //   192: astore_2
      //   193: aload_2
      //   194: aload_1
      //   195: invokevirtual 99	java/io/IOException:getMessage	()Ljava/lang/String;
      //   198: invokespecial 102	RT:<init>	(Ljava/lang/String;)V
      //   201: aload_2
      //   202: aload_0
      //   203: invokevirtual 105	RT:a	(LVT;)LRT;
      //   206: pop
      //   207: aload_3
      //   208: aload_2
      //   209: invokespecial 108	java/lang/RuntimeException:<init>	(Ljava/lang/Throwable;)V
      //   212: aload_3
      //   213: athrow
      //   214: astore_1
      //   215: new 95	java/lang/RuntimeException
      //   218: astore_2
      //   219: aload_1
      //   220: aload_0
      //   221: invokevirtual 105	RT:a	(LVT;)LRT;
      //   224: pop
      //   225: aload_2
      //   226: aload_1
      //   227: invokespecial 108	java/lang/RuntimeException:<init>	(Ljava/lang/Throwable;)V
      //   230: aload_2
      //   231: athrow
      //   232: aload_1
      //   233: athrow
      //   234: getstatic 29	Faa$d$i:d	LFaa$d$i;
      //   237: areturn
      //   238: aload_2
      //   239: checkcast 110	PT$j
      //   242: astore_1
      //   243: aload_3
      //   244: checkcast 2	Faa$d$i
      //   247: astore_2
      //   248: aload_0
      //   249: getfield 37	Faa$d$i:f	F
      //   252: fconst_0
      //   253: fcmpl
      //   254: ifeq +9 -> 263
      //   257: iconst_1
      //   258: istore 7
      //   260: goto +6 -> 266
      //   263: iconst_0
      //   264: istore 7
      //   266: aload_0
      //   267: getfield 37	Faa$d$i:f	F
      //   270: fstore 8
      //   272: aload_2
      //   273: getfield 37	Faa$d$i:f	F
      //   276: fconst_0
      //   277: fcmpl
      //   278: ifeq +6 -> 284
      //   281: iconst_1
      //   282: istore 5
      //   284: aload_0
      //   285: aload_1
      //   286: iload 7
      //   288: fload 8
      //   290: iload 5
      //   292: aload_2
      //   293: getfield 37	Faa$d$i:f	F
      //   296: invokeinterface 113 5 0
      //   301: putfield 37	Faa$d$i:f	F
      //   304: getstatic 118	PT$h:a	LPT$h;
      //   307: astore_1
      //   308: aload_0
      //   309: areturn
      //   310: new 15	Faa$d$i$a
      //   313: dup
      //   314: aconst_null
      //   315: invokespecial 121	Faa$d$i$a:<init>	(LQY;)V
      //   318: areturn
      //   319: aconst_null
      //   320: areturn
      //   321: getstatic 29	Faa$d$i:d	LFaa$d$i;
      //   324: areturn
      //   325: new 2	Faa$d$i
      //   328: dup
      //   329: invokespecial 27	Faa$d$i:<init>	()V
      //   332: areturn
      // Local variable table:
      //   start	length	slot	name	signature
      //   0	333	0	this	i
      //   0	333	1	parami	PT.i
      //   0	333	2	paramObject1	Object
      //   0	333	3	paramObject2	Object
      //   8	145	4	i	int
      //   11	280	5	bool1	boolean
      //   14	162	6	j	int
      //   258	29	7	bool2	boolean
      //   270	19	8	f1	float
      // Exception table:
      //   from	to	target	type
      //   81	102	108	finally
      //   102	105	108	finally
      //   109	112	108	finally
      //   133	139	180	finally
      //   151	160	180	finally
      //   163	171	180	finally
      //   185	214	180	finally
      //   215	232	180	finally
      //   133	139	184	java/io/IOException
      //   151	160	184	java/io/IOException
      //   163	171	184	java/io/IOException
      //   133	139	214	RT
      //   151	160	214	RT
      //   163	171	214	RT
    }
    
    public void a(JT paramJT)
      throws IOException
    {
      float f1 = this.f;
      if (f1 != 0.0F) {
        paramJT.b(1, f1);
      }
    }
    
    public int d()
    {
      int i = this.c;
      if (i != -1) {
        return i;
      }
      i = 0;
      float f1 = this.f;
      if (f1 != 0.0F) {
        i = 0 + JT.a(1, f1);
      }
      this.c = i;
      return i;
    }
    
    public static final class a
      extends PT.a<Faa.d.i, a>
      implements Faa.d.j
    {
      private a()
      {
        super();
      }
      
      public a a(float paramFloat)
      {
        c();
        Faa.d.i.a((Faa.d.i)this.b, paramFloat);
        return this;
      }
    }
  }
  
  public static abstract interface j
    extends WT
  {}
}


/* Location:              /Applications/dex2jar/classes-dex2jar.jar!/Faa$d.class
 * Java compiler version: 6 (50.0)
 * JD-Core Version:       0.7.1
 */