import java.io.IOException;
import java.util.List;

public final class laa
  extends PT<laa, laa.a>
  implements qaa
{
  private static final laa d = new laa();
  private static volatile YT<laa> e;
  private int f;
  private String g = "";
  private String h = "";
  private String i = "";
  private QT.c<maa> j = PT.g();
  private String k = "";
  private String l = "";
  
  static
  {
    d.h();
  }
  
  public static laa l()
  {
    return d;
  }
  
  public static YT<laa> parser()
  {
    return d.e();
  }
  
  /* Error */
  protected final Object a(PT.i parami, Object paramObject1, Object paramObject2)
  {
    // Byte code:
    //   0: getstatic 71	QY:a	[I
    //   3: aload_1
    //   4: invokevirtual 77	java/lang/Enum:ordinal	()I
    //   7: iaload
    //   8: tableswitch	default:+48->56, 1:+602->610, 2:+598->606, 3:+587->595, 4:+578->586, 5:+348->356, 6:+102->110, 7:+344->352, 8:+56->64
    //   56: new 79	java/lang/UnsupportedOperationException
    //   59: dup
    //   60: invokespecial 80	java/lang/UnsupportedOperationException:<init>	()V
    //   63: athrow
    //   64: getstatic 82	laa:e	LYT;
    //   67: ifnonnull +39 -> 106
    //   70: ldc 2
    //   72: monitorenter
    //   73: getstatic 82	laa:e	LYT;
    //   76: ifnonnull +18 -> 94
    //   79: new 84	PT$b
    //   82: astore_1
    //   83: aload_1
    //   84: getstatic 33	laa:d	Llaa;
    //   87: invokespecial 87	PT$b:<init>	(LPT;)V
    //   90: aload_1
    //   91: putstatic 82	laa:e	LYT;
    //   94: ldc 2
    //   96: monitorexit
    //   97: goto +9 -> 106
    //   100: astore_1
    //   101: ldc 2
    //   103: monitorexit
    //   104: aload_1
    //   105: athrow
    //   106: getstatic 82	laa:e	LYT;
    //   109: areturn
    //   110: aload_2
    //   111: checkcast 89	HT
    //   114: astore_1
    //   115: aload_3
    //   116: checkcast 91	LT
    //   119: astore_2
    //   120: iconst_0
    //   121: istore 4
    //   123: iload 4
    //   125: ifne +227 -> 352
    //   128: aload_1
    //   129: invokevirtual 94	HT:n	()I
    //   132: istore 5
    //   134: iload 5
    //   136: ifeq +156 -> 292
    //   139: iload 5
    //   141: bipush 10
    //   143: if_icmpeq +138 -> 281
    //   146: iload 5
    //   148: bipush 18
    //   150: if_icmpeq +120 -> 270
    //   153: iload 5
    //   155: bipush 26
    //   157: if_icmpeq +102 -> 259
    //   160: iload 5
    //   162: bipush 42
    //   164: if_icmpeq +51 -> 215
    //   167: iload 5
    //   169: bipush 50
    //   171: if_icmpeq +33 -> 204
    //   174: iload 5
    //   176: bipush 58
    //   178: if_icmpeq +15 -> 193
    //   181: aload_1
    //   182: iload 5
    //   184: invokevirtual 97	HT:e	(I)Z
    //   187: ifne -64 -> 123
    //   190: goto +102 -> 292
    //   193: aload_0
    //   194: aload_1
    //   195: invokevirtual 101	HT:m	()Ljava/lang/String;
    //   198: putfield 54	laa:l	Ljava/lang/String;
    //   201: goto -78 -> 123
    //   204: aload_0
    //   205: aload_1
    //   206: invokevirtual 101	HT:m	()Ljava/lang/String;
    //   209: putfield 52	laa:k	Ljava/lang/String;
    //   212: goto -89 -> 123
    //   215: aload_0
    //   216: getfield 50	laa:j	LQT$c;
    //   219: invokeinterface 106 1 0
    //   224: ifne +14 -> 238
    //   227: aload_0
    //   228: aload_0
    //   229: getfield 50	laa:j	LQT$c;
    //   232: invokestatic 109	PT:a	(LQT$c;)LQT$c;
    //   235: putfield 50	laa:j	LQT$c;
    //   238: aload_0
    //   239: getfield 50	laa:j	LQT$c;
    //   242: aload_1
    //   243: invokestatic 113	maa:parser	()LYT;
    //   246: aload_2
    //   247: invokevirtual 116	HT:a	(LYT;LLT;)LVT;
    //   250: invokeinterface 122 2 0
    //   255: pop
    //   256: goto -133 -> 123
    //   259: aload_0
    //   260: aload_1
    //   261: invokevirtual 101	HT:m	()Ljava/lang/String;
    //   264: putfield 45	laa:i	Ljava/lang/String;
    //   267: goto -144 -> 123
    //   270: aload_0
    //   271: aload_1
    //   272: invokevirtual 101	HT:m	()Ljava/lang/String;
    //   275: putfield 43	laa:h	Ljava/lang/String;
    //   278: goto -155 -> 123
    //   281: aload_0
    //   282: aload_1
    //   283: invokevirtual 101	HT:m	()Ljava/lang/String;
    //   286: putfield 41	laa:g	Ljava/lang/String;
    //   289: goto -166 -> 123
    //   292: iconst_1
    //   293: istore 4
    //   295: goto -172 -> 123
    //   298: astore_1
    //   299: goto +51 -> 350
    //   302: astore_2
    //   303: new 124	java/lang/RuntimeException
    //   306: astore_3
    //   307: new 64	RT
    //   310: astore_1
    //   311: aload_1
    //   312: aload_2
    //   313: invokevirtual 127	java/io/IOException:getMessage	()Ljava/lang/String;
    //   316: invokespecial 130	RT:<init>	(Ljava/lang/String;)V
    //   319: aload_1
    //   320: aload_0
    //   321: invokevirtual 133	RT:a	(LVT;)LRT;
    //   324: pop
    //   325: aload_3
    //   326: aload_1
    //   327: invokespecial 136	java/lang/RuntimeException:<init>	(Ljava/lang/Throwable;)V
    //   330: aload_3
    //   331: athrow
    //   332: astore_2
    //   333: new 124	java/lang/RuntimeException
    //   336: astore_1
    //   337: aload_2
    //   338: aload_0
    //   339: invokevirtual 133	RT:a	(LVT;)LRT;
    //   342: pop
    //   343: aload_1
    //   344: aload_2
    //   345: invokespecial 136	java/lang/RuntimeException:<init>	(Ljava/lang/Throwable;)V
    //   348: aload_1
    //   349: athrow
    //   350: aload_1
    //   351: athrow
    //   352: getstatic 33	laa:d	Llaa;
    //   355: areturn
    //   356: aload_2
    //   357: checkcast 138	PT$j
    //   360: astore_1
    //   361: aload_3
    //   362: checkcast 2	laa
    //   365: astore_2
    //   366: aload_0
    //   367: aload_1
    //   368: aload_0
    //   369: getfield 41	laa:g	Ljava/lang/String;
    //   372: invokevirtual 143	java/lang/String:isEmpty	()Z
    //   375: iconst_1
    //   376: ixor
    //   377: aload_0
    //   378: getfield 41	laa:g	Ljava/lang/String;
    //   381: aload_2
    //   382: getfield 41	laa:g	Ljava/lang/String;
    //   385: invokevirtual 143	java/lang/String:isEmpty	()Z
    //   388: iconst_1
    //   389: ixor
    //   390: aload_2
    //   391: getfield 41	laa:g	Ljava/lang/String;
    //   394: invokeinterface 146 5 0
    //   399: putfield 41	laa:g	Ljava/lang/String;
    //   402: aload_0
    //   403: aload_1
    //   404: aload_0
    //   405: getfield 43	laa:h	Ljava/lang/String;
    //   408: invokevirtual 143	java/lang/String:isEmpty	()Z
    //   411: iconst_1
    //   412: ixor
    //   413: aload_0
    //   414: getfield 43	laa:h	Ljava/lang/String;
    //   417: aload_2
    //   418: getfield 43	laa:h	Ljava/lang/String;
    //   421: invokevirtual 143	java/lang/String:isEmpty	()Z
    //   424: iconst_1
    //   425: ixor
    //   426: aload_2
    //   427: getfield 43	laa:h	Ljava/lang/String;
    //   430: invokeinterface 146 5 0
    //   435: putfield 43	laa:h	Ljava/lang/String;
    //   438: aload_0
    //   439: aload_1
    //   440: aload_0
    //   441: getfield 45	laa:i	Ljava/lang/String;
    //   444: invokevirtual 143	java/lang/String:isEmpty	()Z
    //   447: iconst_1
    //   448: ixor
    //   449: aload_0
    //   450: getfield 45	laa:i	Ljava/lang/String;
    //   453: aload_2
    //   454: getfield 45	laa:i	Ljava/lang/String;
    //   457: invokevirtual 143	java/lang/String:isEmpty	()Z
    //   460: iconst_1
    //   461: ixor
    //   462: aload_2
    //   463: getfield 45	laa:i	Ljava/lang/String;
    //   466: invokeinterface 146 5 0
    //   471: putfield 45	laa:i	Ljava/lang/String;
    //   474: aload_0
    //   475: aload_1
    //   476: aload_0
    //   477: getfield 50	laa:j	LQT$c;
    //   480: aload_2
    //   481: getfield 50	laa:j	LQT$c;
    //   484: invokeinterface 149 3 0
    //   489: putfield 50	laa:j	LQT$c;
    //   492: aload_0
    //   493: aload_1
    //   494: aload_0
    //   495: getfield 52	laa:k	Ljava/lang/String;
    //   498: invokevirtual 143	java/lang/String:isEmpty	()Z
    //   501: iconst_1
    //   502: ixor
    //   503: aload_0
    //   504: getfield 52	laa:k	Ljava/lang/String;
    //   507: aload_2
    //   508: getfield 52	laa:k	Ljava/lang/String;
    //   511: invokevirtual 143	java/lang/String:isEmpty	()Z
    //   514: iconst_1
    //   515: ixor
    //   516: aload_2
    //   517: getfield 52	laa:k	Ljava/lang/String;
    //   520: invokeinterface 146 5 0
    //   525: putfield 52	laa:k	Ljava/lang/String;
    //   528: aload_0
    //   529: aload_1
    //   530: aload_0
    //   531: getfield 54	laa:l	Ljava/lang/String;
    //   534: invokevirtual 143	java/lang/String:isEmpty	()Z
    //   537: iconst_1
    //   538: ixor
    //   539: aload_0
    //   540: getfield 54	laa:l	Ljava/lang/String;
    //   543: iconst_1
    //   544: aload_2
    //   545: getfield 54	laa:l	Ljava/lang/String;
    //   548: invokevirtual 143	java/lang/String:isEmpty	()Z
    //   551: ixor
    //   552: aload_2
    //   553: getfield 54	laa:l	Ljava/lang/String;
    //   556: invokeinterface 146 5 0
    //   561: putfield 54	laa:l	Ljava/lang/String;
    //   564: aload_1
    //   565: getstatic 154	PT$h:a	LPT$h;
    //   568: if_acmpne +16 -> 584
    //   571: aload_0
    //   572: aload_0
    //   573: getfield 156	laa:f	I
    //   576: aload_2
    //   577: getfield 156	laa:f	I
    //   580: ior
    //   581: putfield 156	laa:f	I
    //   584: aload_0
    //   585: areturn
    //   586: new 9	laa$a
    //   589: dup
    //   590: aconst_null
    //   591: invokespecial 159	laa$a:<init>	(LQY;)V
    //   594: areturn
    //   595: aload_0
    //   596: getfield 50	laa:j	LQT$c;
    //   599: invokeinterface 161 1 0
    //   604: aconst_null
    //   605: areturn
    //   606: getstatic 33	laa:d	Llaa;
    //   609: areturn
    //   610: new 2	laa
    //   613: dup
    //   614: invokespecial 31	laa:<init>	()V
    //   617: areturn
    // Local variable table:
    //   start	length	slot	name	signature
    //   0	618	0	this	laa
    //   0	618	1	parami	PT.i
    //   0	618	2	paramObject1	Object
    //   0	618	3	paramObject2	Object
    //   121	173	4	m	int
    //   132	51	5	n	int
    // Exception table:
    //   from	to	target	type
    //   73	94	100	finally
    //   94	97	100	finally
    //   101	104	100	finally
    //   128	134	298	finally
    //   181	190	298	finally
    //   193	201	298	finally
    //   204	212	298	finally
    //   215	238	298	finally
    //   238	256	298	finally
    //   259	267	298	finally
    //   270	278	298	finally
    //   281	289	298	finally
    //   303	332	298	finally
    //   333	350	298	finally
    //   128	134	302	java/io/IOException
    //   181	190	302	java/io/IOException
    //   193	201	302	java/io/IOException
    //   204	212	302	java/io/IOException
    //   215	238	302	java/io/IOException
    //   238	256	302	java/io/IOException
    //   259	267	302	java/io/IOException
    //   270	278	302	java/io/IOException
    //   281	289	302	java/io/IOException
    //   128	134	332	RT
    //   181	190	332	RT
    //   193	201	332	RT
    //   204	212	332	RT
    //   215	238	332	RT
    //   238	256	332	RT
    //   259	267	332	RT
    //   270	278	332	RT
    //   281	289	332	RT
  }
  
  public void a(JT paramJT)
    throws IOException
  {
    if (!this.g.isEmpty()) {
      paramJT.b(1, n());
    }
    if (!this.h.isEmpty()) {
      paramJT.b(2, q());
    }
    if (!this.i.isEmpty()) {
      paramJT.b(3, m());
    }
    for (int m = 0; m < this.j.size(); m++) {
      paramJT.b(5, (VT)this.j.get(m));
    }
    if (!this.k.isEmpty()) {
      paramJT.b(6, o());
    }
    if (!this.l.isEmpty()) {
      paramJT.b(7, p());
    }
  }
  
  public int d()
  {
    int m = this.c;
    if (m != -1) {
      return m;
    }
    boolean bool = this.g.isEmpty();
    int n = 0;
    if (!bool) {
      m = JT.a(1, n()) + 0;
    } else {
      m = 0;
    }
    int i1 = m;
    if (!this.h.isEmpty()) {
      i1 = m + JT.a(2, q());
    }
    m = i1;
    int i2 = n;
    if (!this.i.isEmpty()) {
      m = i1 + JT.a(3, m());
    }
    for (i2 = n; i2 < this.j.size(); i2++) {
      m += JT.a(5, (VT)this.j.get(i2));
    }
    i1 = m;
    if (!this.k.isEmpty()) {
      i1 = m + JT.a(6, o());
    }
    m = i1;
    if (!this.l.isEmpty()) {
      m = i1 + JT.a(7, p());
    }
    this.c = m;
    return m;
  }
  
  public List<maa> k()
  {
    return this.j;
  }
  
  public String m()
  {
    return this.i;
  }
  
  public String n()
  {
    return this.g;
  }
  
  public String o()
  {
    return this.k;
  }
  
  public String p()
  {
    return this.l;
  }
  
  public String q()
  {
    return this.h;
  }
  
  public static final class a
    extends PT.a<laa, a>
    implements qaa
  {
    private a()
    {
      super();
    }
  }
}


/* Location:              /Applications/dex2jar/classes-dex2jar.jar!/laa.class
 * Java compiler version: 6 (50.0)
 * JD-Core Version:       0.7.1
 */